Workbook

Sheet Start here
A1: CostVision rate card converter
A2: Put your own rates into CostVision without retyping them. Seven steps, about ten minutes the first time.
A4: WHAT THIS IS FOR
B5: You get a rate card in your own layout, with your own codes. CostVision needs its own ids,
B6: because those ids are what its costing formulas look for. This workbook joins the two.
B7: You paste your rates in. It fills in the file CostVision reads. Nothing is renamed, and
B8: there is no code to change. It is ordinary Excel formulas, so there are no macros to allow.
A10: BEFORE YOU START
B11: Have your machine rate card and your material rate card open.
B12: If labour comes as its own file, have that too. If it does not, you will not need one.
B13: Know the country you are costing in, and the period stamped on each file.
A15: THE SEVEN STEPS
A16: STEP 1 | B16: Paste the machine rates.
B17: a. Go to the tab called JLR Machines.
B18: b. Row 2 is an example. Click the row 2 number, right-click, and choose Delete Row.
B19: c. In your machine file, select all the rows of data. Not the header row.
B20: d. Come back here, click cell A2 , and paste. Use Paste Special → Values if you have it.
B21: e. Look across: MACHINE_CODE should be in column A, TOTAL_MACHINE_RATE in column N.
B22: Row 1 already has your 14 headers on it, in the shaded band. Leave that row alone.
B23: If your file has extra columns, or has them in a different order, tidy your copy first so
B24: the columns line up with row 1 here. Paste as many rows as you like, all countries
B25: included. Step 4 is what picks out the ones you want.
A27: STEP 2 | B27: Paste the material rates.
B28: Same again on the JLR Materials tab. Delete the example on row 2, then paste your
B29: rows into cell A2 . CODE goes in column A, CO2 in column G.
A31: STEP 3 | B31: Paste the labour rates, if you have them separately.
B32: On the card we have seen, labour is already inside the machine file, as
B33: TOTAL_LABOUR_RATE next to a LABOUR_CATEGORY. If that is true for you, skip this step.
B34: Go to JLR Labour , delete the example rows, and leave the tab empty. The sheet will
B35: find labour on the machine tab instead.
B36: If you do have a separate labour file, delete the examples and paste into A2 as before.
A38: STEP 4 | B38: Say which country and which period you want.
B39: Go to the Settings tab and fill in the four shaded cells in column B:
B40: B2 Country for example United Kingdom
B41: B3 Machine period for example 04042025 (copy it from PERIOD_CODE)
B42: B4 Material period for example 04-04-2025 (copy it from PERIOD)
B43: B5 MATERIAL_RECLAIM choose percent or per kg
B44: Type each one exactly as it appears in your file, spaces and dashes and all. Copying it
B45: straight out of the file is safer than typing it.
B46: There are two period boxes on purpose. The two files write the same quarter differently.
B47: Leave a box empty only if you have already cut that file down to one country and one period.
B48: About B5: if MATERIAL_RECLAIM is a percentage of the material rate, leave it on percent.
B49: If it is already a price per kilo, choose per kg. Please check which one it is with whoever
B50: looks after the rate card. Getting it the wrong way round changes the scrap credit a lot.
A52: STEP 5 | B52: Say which of your codes is which CostVision rate. You only do this once.
B53: Go to the Mapping tab. It lists every rate CostVision uses, with a plain description of
B54: each one in column B, such as "1045 / C45 (Medium-Carbon Steel) — UK".
B55: In column C, type your own CODE next to the ones you have. Leave the rest empty.
B56: Column D then shows the name you hold against that code. Read it. If it is not the thing
B57: you meant, the code is wrong. If it turns red and says NOT FOUND, that code is not in the
B58: data you pasted.
B59: For labour, the code is the LABOUR_CATEGORY, such as CB. It is not a machine number.
B60: Every description ends with the region it belongs to, such as "— UK" or "— CN". Put a UK
B61: rate card against the UK rows. A UK rate put on a Chinese row will load quite happily and
B62: be wrong, and nothing further down can tell.
B63: You do not have to fill in all of them. Map the twenty materials you actually buy and the
B64: other three hundred keep the values CostVision ships with. That is a normal way to use this.
A66: STEP 6 | B66: Recalculate and save.
B67: Press F9. Saving does it too. Then use File → Save As and put the quarter in the name,
B68: such as CostVision-rates-2025-Q2.xlsx. Keep it as .xlsx.
A70: STEP 7 | B70: Check it, then upload it.
B71: Go to the Check tab. Every line that should be zero turns green when it is, and red when
B72: it is not. It also tells you how many rates were picked up. If that is zero all the way
B73: down, something in step 4 or step 5 has not matched.
B74: When it looks right: open CostVision, sign in as an admin, and go to Edit Rates.
B75: Choose Upload company rates, and pick the file you just saved. It will tell you how many
B76: rows it read. From then on, every costing uses your rates.
A78: AN EXAMPLE, ALL THE WAY THROUGH
B79: Say your machine card has this row on it:
B80: 712008 | 100t Hydraulic Injection Moulding MC | United Kingdom | 04042025 | CB |
B81: 40.97 | 1.75 | 1.06 | 1.97 | 0.18 | 0.64 | 4.45 | 0.00 | 10.06
B82: You paste it into JLR Machines. On Settings you put United Kingdom and 04042025.
B83: On Mapping you find imm-100t, "100T Injection Moulding Machine — UK", and type 712008
B84: next to it. Column D comes back with "100t Hydraulic Injection Moulding MC", so you know
B85: you picked the right row.
B86: Press F9. CostVision now costs that machine at 10.06 an hour, which is exactly the
B87: TOTAL_MACHINE_RATE on your card, and it keeps the split you gave it:
B88: maintenance 1.97/hr, energy 4.45/hr, floor space 1.06/hr, finance 0.64/hr,
B89: indirect 0.18/hr, depreciation 1.76/hr.
B90: And because CB sits on that row at 40.97, mapping lab-uk-skilled to CB gives you the
... B92: The tab called How it converts shows every formula behind this, line by line.
A94: NEXT QUARTER
B95: Open this same file. Delete the old rows on the JLR tabs and paste the new ones. Change
B96: the two period boxes on Settings. Press F9, save, upload. Your column C on the Mapping
B97: tab is still filled in, because codes do not change from quarter to quarter.
A99: IF SOMETHING LOOKS WRONG
B100: Nothing was picked up at all.
B101: The country or the period on Settings does not match the file exactly. Copy the value
B102: out of your export and paste it in, rather than typing it.
B103: Column D on Mapping says NOT FOUND.
B104: That code is not in the data you pasted. Check the code, and check the paste landed.
B105: Check says a code matched more than one row.
B106: Your paste has the same code twice, usually two countries or two periods. Narrow it on
B107: Settings. Until you do, that row keeps the CostVision value on purpose.
B108: A rate looks far too big or far too small.
B109: Look at B5 on Settings. percent and per kg give very different answers.
B110: CostVision would not accept the file.
B111: It will name the tab and the row. It is usually a number that pasted in as text.
A113: A FEW RULES THAT MATTER
A114: • | B114: Do not change column A on the Materials, Machines or Labour tabs. Those ids are what the
...

Sheet How it converts
A1: How it converts
A2: Every rule this workbook applies, in plain words, with the formula that does it. Nothing here is hidden in code.
A4: The short version
B5: Your rate card and CostVision hold the same numbers in different shapes.
B6: A machine rate on your card is seven costs per hour that add up to TOTAL_MACHINE_RATE.
B7: CostVision holds the same seven as yearly costs, and divides by hours x utilisation to get back to an hourly rate.
B8: So this sheet multiplies each of your hourly figures by that machine’s hours x utilisation. CostVision divides it straight back out.
B9: The rate lands on your published number, and the split survives, so a report can still show what the rate is made of.
B10: Materials and labour are simpler: the price and the hourly rate go straight across.
A12: The machine rate, line by line
A13: Each of your seven hourly figures becomes one yearly figure. 3,200 in the formula below is that machine’s own 4,000 hours x 80% utilisation — the same number CostVision divides by afterwards, so it cancels.
B14: From your file | C14: Becomes, in CostVision | D14: What happens to it | E14: The formula, as it is in the sheet
B15: DEPRECIATION | C15: annualDepreciation | D15: Depreciation x hours x utilisation, plus the penny the seven elements round by, so the rebuilt rate equals TOTAL_MACHINE_RATE exactly. | E15: IF($X2>0,IF($Y2>0,MAX(0,$Q2+$X2-$Y2)*3200,$X2*3200),40480)
B16: MRO | C16: maintenance | D16: MRO x hours x utilisation. | E16: IF($X2>0,IF($Y2>0,$S2*3200,0),22211)
B17: UTILITIES | C17: energy | D17: Utilities x hours x utilisation. | E17: IF($X2>0,IF($Y2>0,$V2*3200,0),23304)
B18: FLOORSPACE | C18: floorSpace | D18: Floorspace x hours x utilisation. | E18: IF($X2>0,IF($Y2>0,$R2*3200,0),8077)
B19: INSURANCE + CONSUMABLES | C19: indirectSupport | D19: Insurance and consumables together — CostVision has one line where the card has two. | E19: IF($X2>0,IF($Y2>0,($T2+$W2)*3200,0),22158)
B20: INTEREST | C20: financeCost | D20: Interest x hours x utilisation. | E20: IF($X2>0,IF($Y2>0,$U2*3200,0),16000)
B21: TOTAL_MACHINE_RATE | C21: nothing directly | D21: Used as the switch — if there is a rate for this machine, take your figures; if not, keep ours. Also used to check the answer. | E21: IF($X2<=0,0,ROUND((D2+E2+F2+G2+H2+I2)/3200-$X2,4))
B22: If a row has only a TOTAL_MACHINE_RATE and no breakdown, the whole total goes on the depreciation line and the source note says so, rather than pretending to be a breakdown.
A25: Materials
B26: From your file | C26: Becomes, in CostVision | D26: What happens to it | E26: The formula, as it is in the sheet
B27: MATERIAL_RATE | C27: pricePerKg | D27: Your price per kilo, or ours when you have not mapped this one. | E27: IF($M2>0,$M2,3.56)
B28: MATERIAL_RECLAIM | C28: scrapRecoveryPricePerKg | D28: The scrap credit, worked out in column O from whichever basis Settings says. | E28: IF($O2>0,$O2,0.54)
B29: MATERIAL_RECLAIM | C29: working: scrap £/kg | D29: Percent of the rate, or a price per kilo already. Settings B5 decides. | E29: IF($N2=0,0,IF(Settings!$B$5="percent",$M2*$N2/100,$N2))
B30: CO2 | C30: nothing | D30: Brought onto the Materials tab so you can see it. CostVision has no carbon field in this file, so it is ignored on upload. | E30: (no formula — the column is carried across only)
A33: Labour
B34: From your file | C34: Becomes, in CostVision | D34: What happens to it | E34: The formula, as it is in the sheet
B35: TOTAL_LABOUR_RATE | C35: fullyLoadedRatePerHr | D35: Your hourly rate for that labour category, or ours when it is not mapped. | E35: IF($L2>0,$L2,26.19)
B36: TOTAL_LABOUR_RATE on JLR Machines | C36: working: from the machine tab | D36: If there is no separate labour file, read the category off the machine rows instead. | E36: IF($H2="",0,IFERROR(AVERAGEIFS('JLR Machines'!$F$2:$F$20001,'JLR Machines'!$E$2:$E$20001,$H2,'JLR Machines'!$C$2:$C$20001,IF(Settings!$B$2="","<>",Settings!$B$2),'JLR Machines'!$D$2:$D$20001,IF(Settings!$B$3="","<>",Settings!$B$3)),0))
A39: The three rules underneath all of it
B40: From your file | C40: Becomes, in CostVision | D40: What happens to it | E40: The formula, as it is in the sheet
B41: Mapping column C | C41: which code to use | D41: Finds the code you typed on the Mapping tab for this row. Empty means "not mapped", and the row keeps our value. | E41: IFERROR(INDEX(Mapping!$C$2:$C$549,MATCH($A2,Mapping!$A$2:$A$549,0)),"")
B42: COUNTRY + PERIOD | C42: how many rows match | D42: Counts the pasted rows with this code, in the country and period you asked for on Settings. Only a count of exactly 1 is used. Two means the filter has not narrowed it, and a made-up average would be a rate nobody published. | E42: IF($K2="",0,COUNTIFS('JLR Materials'!$A$2:$A$20001,$K2,'JLR Materials'!$C$2:$C$20001,IF(Settings!$B$2="","<>",Settings!$B$2),'JLR Materials'!$D$2:$D$20001,IF(Settings!$B$4="","<>",Settings!$B$4)))
B43: the matched row | C43: the number itself | D43: Reads one column off that single matching row. Zero when there is no clean single match, which every formula above reads as "keep what CostVision already had". | E43: IF($L2<>1,0,SUMIFS('JLR Materials'!$E$2:$E$20001,'JLR Materials'!$A$2:$A$20001,$K2,'JLR Materials'!$C$2:$C$20001,IF(Settings!$B$2="","<>",Settings!$B$2),'JLR Materials'!$D$2:$D$20001,IF(Settings!$B$4="","<>",Settings!$B$4)))
A46: Where to find the working in the sheet
B47: From your file | C47: Becomes, in CostVision | D47: What happens to it | E47: The formula, as it is in the sheet
B48: Materials | C48: K to P are the working columns. Q and R hold our own note and date, for when yours is not used.
B49: Machines | C49: O to Z are the working columns. AA and AB hold our own note and date.
B50: Labour | C50: H to L are the working columns. M holds our own note.
B51: Mapping | C51: C is yours to fill in. D is the sheet reading your code back to you.

Sheet Settings
A1: Setting | B1: Value | C1: What it does
A2: Country | C2: Type it exactly as your file writes it, e.g. United Kingdom. Leave empty to take any.
A3: Machine period | C3: The PERIOD_CODE on your machine and labour files, e.g. 04042025.
A4: Material period | C4: The PERIOD on your material file, e.g. 04-04-2025. The two files write it differently.
A5: MATERIAL_RECLAIM is | B5: percent | C5: Is it a percentage of the material rate, or already a price per kilo? Please check.
B8: The shaded boxes are the only things to fill in on this tab.
B9: Leave a box empty only if you have already cut that file down to one country and one period.
B10: If a code ends up matching two rows, the Check tab will tell you, and CostVision keeps its
B11: own value for that row rather than guessing which of the two you meant.

Sheet JLR Machines
A1: MACHINE_CODE | B1: MACHINE_NAME | C1: COUNTRY_NAME | D1: PERIOD_CODE | E1: LABOUR_CATEGORY | F1: TOTAL_LABOUR_RATE | G1: DEPRECIATION | H1: FLOORSPACE | I1: MRO | J1: INSURANCE | K1: INTEREST | L1: UTILITIES | M1: CONSUMABLES | N1: TOTAL_MACHINE_RATE
A2: EXAMPLE | B2: EXAMPLE ROW, DELETE IT — your machine export goes here, from cell A2 down | C2: United Kingdom | D2: 04042025 | E2: CB | F2: 40.97 | G2: 1.75 | H2: 1.06 | I2: 1.97 | J2: 0.18 | K2: 0.64 | L2: 4.45 | M2: 0 | N2: 10.06

Sheet JLR Materials
A1: CODE | B1: MATERIAL | C1: COUNTRY | D1: PERIOD | E1: MATERIAL_RATE | F1: MATERIAL_RECLAIM | G1: CO2
A2: EXAMPLE | B2: EXAMPLE ROW, DELETE IT — your material export goes here, from cell A2 down | C2: United Kingdom | D2: 04-04-2025 | E2: 0.72 | F2: 40.48 | G2: 2.19

Sheet JLR Labour
A1: LABOUR_CATEGORY | B1: DESCRIPTION | C1: COUNTRY_NAME | D1: PERIOD_CODE | E1: TOTAL_LABOUR_RATE
A2: EXAMPLE | B2: EXAMPLE ROW, DELETE IT — or leave this whole tab empty, and the sheet will read TOTAL_LABOUR_RATE off the JLR Machines tab by LABOUR_CATEGORY instead | C2: United Kingdom | D2: 04042025 | E2: 40.97

Sheet Mapping
A1: tool id | B1: what it is (do not edit) | C1: JLR code | D1: JLR name for that code | E1: category
A2: mat-al6061 | B2: 6061-T6 — Aluminium — UK | D2: =IF($C2="","",IFERROR(IF($E2="machine",INDEX('JLR Machines'!$B$2:$B$20001,MATCH($C2,'JLR Machines'!$A$2:$A$20001,0)),IF($E2="material",INDEX('JLR Materials'!$B$2:$B$20001,MATCH($C2,'JLR Materials'!$A$2:$A$20001,0)),IF($E2="labour",IFERROR(INDEX('JLR Labour'!$B$2:$B$20001,MATCH($C2,'JLR Labour'!$A$2:$A$20001,0)),"labour category "&$C2&" — from the machine tab"),""))),"NOT FOUND — check the code")) | E2: material
A3: mat-steel1045 | B3: 1045 / C45 / 080M46 (Medium-Carbon Steel) — Carbon Steel — UK | D3: =IF($C3="","",IFERROR(IF($E3="machine",INDEX('JLR Machines'!$B$2:$B$20001,MATCH($C3,'JLR Machines'!$A$2:$A$20001,0)),IF($E3="material",INDEX('JLR Materials'!$B$2:$B$20001,MATCH($C3,'JLR Materials'!$A$2:$A$20001,0)),IF($E3="labour",IFERROR(INDEX('JLR Labour'!$B$2:$B$20001,MATCH($C3,'JLR Labour'!$A$2:$A$20001,0)),"labour category "&$C3&" — from the machine tab"),""))),"NOT FOUND — check the code")) | E3: material
A4: mat-ss316l | B4: 316L — Stainless Steel — UK | D4: =IF($C4="","",IFERROR(IF($E4="machine",INDEX('JLR Machines'!$B$2:$B$20001,MATCH($C4,'JLR Machines'!$A$2:$A$20001,0)),IF($E4="material",INDEX('JLR Materials'!$B$2:$B$20001,MATCH($C4,'JLR Materials'!$A$2:$A$20001,0)),IF($E4="labour",IFERROR(INDEX('JLR Labour'!$B$2:$B$20001,MATCH($C4,'JLR Labour'!$A$2:$A$20001,0)),"labour category "&$C4&" — from the machine tab"),""))),"NOT FOUND — check the code")) | E4: material
A5: mat-steel4140 | B5: 4140 / 42CrMo4 / EN19 (Chromoly Alloy Steel) — Alloy Steel — UK | D5: =IF($C5="","",IFERROR(IF($E5="machine",INDEX('JLR Machines'!$B$2:$B$20001,MATCH($C5,'JLR Machines'!$A$2:$A$20001,0)),IF($E5="material",INDEX('JLR Materials'!$B$2:$B$20001,MATCH($C5,'JLR Materials'!$A$2:$A$20001,0)),IF($E5="labour",IFERROR(INDEX('JLR Labour'!$B$2:$B$20001,MATCH($C5,'JLR Labour'!$A$2:$A$20001,0)),"labour category "&$C5&" — from the machine tab"),""))),"NOT FOUND — check the code")) | E5: material
A6: mat-ti6al4v | B6: Ti-6Al-4V — Titanium — UK | D6: =IF($C6="","",IFERROR(IF($E6="machine",INDEX('JLR Machines'!$B$2:$B$20001,MATCH($C6,'JLR Machines'!$A$2:$A$20001,0)),IF($E6="material",INDEX('JLR Materials'!$B$2:$B$20001,MATCH($C6,'JLR Materials'!$A$2:$A$20001,0)),IF($E6="labour",IFERROR(INDEX('JLR Labour'!$B$2:$B$20001,MATCH($C6,'JLR Labour'!$A$2:$A$20001,0)),"labour category "&$C6&" — from the machine tab"),""))),"NOT FOUND — check the code")) | E6: material
A7: mat-virtual | B7: Virtual / Pass-through — Virtual — UK | D7: =IF($C7="","",IFERROR(IF($E7="machine",INDEX('JLR Machines'!$B$2:$B$20001,MATCH($C7,'JLR Machines'!$A$2:$A$20001,0)),IF($E7="material",INDEX('JLR Materials'!$B$2:$B$20001,MATCH($C7,'JLR Materials'!$A$2:$A$20001,0)),IF($E7="labour",IFERROR(INDEX('JLR Labour'!$B$2:$B$20001,MATCH($C7,'JLR Labour'!$A$2:$A$20001,0)),"labour category "&$C7&" — from the machine tab"),""))),"NOT FOUND — check the code")) | E7: material
A8: mat-en8 | B8: EN8 / 080M40 (Medium Carbon) — Carbon Steel — UK | D8: =IF($C8="","",IFERROR(IF($E8="machine",INDEX('JLR Machines'!$B$2:$B$20001,MATCH($C8,'JLR Machines'!$A$2:$A$20001,0)),IF($E8="material",INDEX('JLR Materials'!$B$2:$B$20001,MATCH($C8,'JLR Materials'!$A$2:$A$20001,0)),IF($E8="labour",IFERROR(INDEX('JLR Labour'!$B$2:$B$20001,MATCH($C8,'JLR Labour'!$A$2:$A$20001,0)),"labour category "&$C8&" — from the machine tab"),""))),"NOT FOUND — check the code")) | E8: material
A9: mat-ss304-bar | B9: 304 Stainless Bar — Stainless Steel — UK | D9: =IF($C9="","",IFERROR(IF($E9="machine",INDEX('JLR Machines'!$B$2:$B$20001,MATCH($C9,'JLR Machines'!$A$2:$A$20001,0)),IF($E9="material",INDEX('JLR Materials'!$B$2:$B$20001,MATCH($C9,'JLR Materials'!$A$2:$A$20001,0)),IF($E9="labour",IFERROR(INDEX('JLR Labour'!$B$2:$B$20001,MATCH($C9,'JLR Labour'!$A$2:$A$20001,0)),"labour category "&$C9&" — from the machine tab"),""))),"NOT FOUND — check the code")) | E9: material
A10: mat-ss303 | B10: 303 Free-Machining Stainless Bar — Stainless Steel — UK | D10: =IF($C10="","",IFERROR(IF($E10="machine",INDEX('JLR Machines'!$B$2:$B$20001,MATCH($C10,'JLR Machines'!$A$2:$A$20001,0)),IF($E10="material",INDEX('JLR Materials'!$B$2:$B$20001,MATCH($C10,'JLR Materials'!$A$2:$A$20001,0)),IF($E10="labour",IFERROR(INDEX('JLR Labour'!$B$2:$B$20001,MATCH($C10,'JLR Labour'!$A$2:$A$20001,0)),"labour category "&$C10&" — from the machine tab"),""))),"NOT FOUND — check the code")) | E10: material
A11: mat-al6082-bar | B11: 6082-T6 Aluminium Bar — Aluminium — UK | D11: =IF($C11="","",IFERROR(IF($E11="machine",INDEX('JLR Machines'!$B$2:$B$20001,MATCH($C11,'JLR Machines'!$A$2:$A$20001,0)),IF($E11="material",INDEX('JLR Materials'!$B$2:$B$20001,MATCH($C11,'JLR Materials'!$A$2:$A$20001,0)),IF($E11="labour",IFERROR(INDEX('JLR Labour'!$B$2:$B$20001,MATCH($C11,'JLR Labour'!$A$2:$A$20001,0)),"labour category "&$C11&" — from the machine tab"),""))),"NOT FOUND — check the code")) | E11: material
A12: mat-al2011 | B12: 2011-T3 Free-Machining Al Bar — Aluminium — UK | D12: =IF($C12="","",IFERROR(IF($E12="machine",INDEX('JLR Machines'!$B$2:$B$20001,MATCH($C12,'JLR Machines'!$A$2:$A$20001,0)),IF($E12="material",INDEX('JLR Materials'!$B$2:$B$20001,MATCH($C12,'JLR Materials'!$A$2:$A$20001,0)),IF($E12="labour",IFERROR(INDEX('JLR Labour'!$B$2:$B$20001,MATCH($C12,'JLR Labour'!$A$2:$A$20001,0)),"labour category "&$C12&" — from the machine tab"),""))),"NOT FOUND — check the code")) | E12: material
A13: mat-brass-cz121 | B13: CZ121 / CW614N Free-Machining Brass — Copper Alloy — UK | D13: =IF($C13="","",IFERROR(IF($E13="machine",INDEX('JLR Machines'!$B$2:$B$20001,MATCH($C13,'JLR Machines'!$A$2:$A$20001,0)),IF($E13="material",INDEX('JLR Materials'!$B$2:$B$20001,MATCH($C13,'JLR Materials'!$A$2:$A$20001,0)),IF($E13="labour",IFERROR(INDEX('JLR Labour'!$B$2:$B$20001,MATCH($C13,'JLR Labour'!$A$2:$A$20001,0)),"labour category "&$C13&" — from the machine tab"),""))),"NOT FOUND — check the code")) | E13: material
... A549: lab-ro-semiskilled | B549: Semi-skilled Operator — Romania | D549: =IF($C549="","",IFERROR(IF($E549="machine",INDEX('JLR Machines'!$B$2:$B$20001,MATCH($C549,'JLR Machines'!$A$2:$A$20001,0)),IF($E549="material",INDEX('JLR Materials'!$B$2:$B$20001,MATCH($C549,'JLR Materials'!$A$2:$A$20001,0)),IF($E549="labour",IFERROR(INDEX('JLR Labour'!$B$2:$B$20001,MATCH($C549,'JLR Labour'!$A$2:$A$20001,0)),"labour category "&$C549&" — from the machine tab"),""))),"NOT FOUND — check the code")) | E549: labour

Sheet Materials
A1: id | B1: grade | C1: category | D1: pricePerKg | E1: scrapRecoveryPricePerKg | F1: densityKgPerM3 | G1: region | H1: effectiveDate | I1: sourceNote | J1: confidence | K1: JLR code | L1: rows matched | M1: MATERIAL_RATE | N1: MATERIAL_RECLAIM | O1: scrap £/kg | P1: CO2 (not used) | Q1: built-in source note | R1: built-in date
A2: mat-al6061 | B2: 6061-T6 | C2: Aluminium | D2: =IF($M2>0,$M2,3.56) -> 3.56 | E2: =IF($O2>0,$O2,0.54) -> 0.54 | F2: 2700 | G2: UK | H2: =IF($M2>0,IF($L2<>1,$R2,IFERROR(INDEX('JLR Materials'!$D$2:$D$20001,MATCH($K2,'JLR Materials'!$A$2:$A$20001,0)),$R2)),$R2) -> 2026-09 | I2: =IF($M2>0,"JLR rate card — material code "&$K2,$Q2) -> LME + UK processor premium, Jun 2026. Index-anchored 2026-07 refresh. | Refresh 2026-09: −£0.060/kg from 0.97kg al £2.910→£2.849/kg; premiums held | J2: Medium | K2: =IFERROR(INDEX(Mapping!$C$2:$C$549,MATCH($A2,Mapping!$A$2:$A$549,0)),"") | L2: =IF($K2="",0,COUNTIFS('JLR Materials'!$A$2:$A$20001,$K2,'JLR Materials'!$C$2:$C$20001,IF(Settings!$B$2="","<>",Settings!$B$2),'JLR Materials'!$D$2:$D$20001,IF(Settings!$B$4="","<>",Settings!$B$4))) -> 0 | M2: =IF($L2<>1,0,SUMIFS('JLR Materials'!$E$2:$E$20001,'JLR Materials'!$A$2:$A$20001,$K2,'JLR Materials'!$C$2:$C$20001,IF(Settings!$B$2="","<>",Settings!$B$2),'JLR Materials'!$D$2:$D$20001,IF(Settings!$B$4="","<>",Settings!$B$4))) -> 0 | N2: =IF($L2<>1,0,SUMIFS('JLR Materials'!$F$2:$F$20001,'JLR Materials'!$A$2:$A$20001,$K2,'JLR Materials'!$C$2:$C$20001,IF(Settings!$B$2="","<>",Settings!$B$2),'JLR Materials'!$D$2:$D$20001,IF(Settings!$B$4="","<>",Settings!$B$4))) -> 0 | O2: =IF($N2=0,0,IF(Settings!$B$5="percent",$M2*$N2/100,$N2)) -> 0 | P2: =IF($L2<>1,0,SUMIFS('JLR Materials'!$G$2:$G$20001,'JLR Materials'!$A$2:$A$20001,$K2,'JLR Materials'!$C$2:$C$20001,IF(Settings!$B$2="","<>",Settings!$B$2),'JLR Materials'!$D$2:$D$20001,IF(Settings!$B$4="","<>",Settings!$B$4))) -> 0 | Q2: LME + UK processor premium, Jun 2026. Index-anchored 2026-07 refresh. | Refresh 2026-09: −£0.060/kg from 0.97kg al £2.910→£2.849/kg; premiums held | R2: 2026-09
A3: mat-steel1045 | B3: 1045 / C45 / 080M46 (Medium-Carbon Steel) | C3: Carbon Steel | D3: =IF($M3>0,$M3,0.95) -> 0.95 | E3: =IF($O3>0,$O3,0.22) -> 0.22 | F3: 7850 | G3: UK | H3: =IF($M3>0,IF($L3<>1,$R3,IFERROR(INDEX('JLR Materials'!$D$2:$D$20001,MATCH($K3,'JLR Materials'!$A$2:$A$20001,0)),$R3)),$R3) -> 2026-09 | I3: =IF($M3>0,"JLR rate card — material code "&$K3,$Q3) -> UK steel stockholder, Jun 2026. Index-anchored 2026-07 refresh. | Refresh 2026-09: INDEX FLAT — Index flat: Kallanish N-Europe wire rod ’stable’ (Jun 2026), ’decrease slightly’ (Jul), ’remain stable’ / ’flat’ (Sep 2026) — carbon and alloy bar unchanged. | J3: Medium | K3: =IFERROR(INDEX(Mapping!$C$2:$C$549,MATCH($A3,Mapping!$A$2:$A$549,0)),"") | L3: =IF($K3="",0,COUNTIFS('JLR Materials'!$A$2:$A$20001,$K3,'JLR Materials'!$C$2:$C$20001,IF(Settings!$B$2="","<>",Settings!$B$2),'JLR Materials'!$D$2:$D$20001,IF(Settings!$B$4="","<>",Settings!$B$4))) -> 0 | M3: =IF($L3<>1,0,SUMIFS('JLR Materials'!$E$2:$E$20001,'JLR Materials'!$A$2:$A$20001,$K3,'JLR Materials'!$C$2:$C$20001,IF(Settings!$B$2="","<>",Settings!$B$2),'JLR Materials'!$D$2:$D$20001,IF(Settings!$B$4="","<>",Settings!$B$4))) -> 0 | N3: =IF($L3<>1,0,SUMIFS('JLR Materials'!$F$2:$F$20001,'JLR Materials'!$A$2:$A$20001,$K3,'JLR Materials'!$C$2:$C$20001,IF(Settings!$B$2="","<>",Settings!$B$2),'JLR Materials'!$D$2:$D$20001,IF(Settings!$B$4="","<>",Settings!$B$4))) -> 0 | O3: =IF($N3=0,0,IF(Settings!$B$5="percent",$M3*$N3/100,$N3)) -> 0 | P3: =IF($L3<>1,0,SUMIFS('JLR Materials'!$G$2:$G$20001,'JLR Materials'!$A$2:$A$20001,$K3,'JLR Materials'!$C$2:$C$20001,IF(Settings!$B$2="","<>",Settings!$B$2),'JLR Materials'!$D$2:$D$20001,IF(Settings!$B$4="","<>",Settings!$B$4))) -> 0 | Q3: UK steel stockholder, Jun 2026. Index-anchored 2026-07 refresh. | Refresh 2026-09: INDEX FLAT — Index flat: Kallanish N-Europe wire rod ’stable’ (Jun 2026), ’decrease slightly’ (Jul), ’remain stable’ / ’flat’ (Sep 2026) — carbon and alloy bar unchanged. | R3: 2026-09
A4: mat-ss316l | B4: 316L | C4: Stainless Steel | D4: =IF($M4>0,$M4,3.95) -> 3.95 | E4: =IF($O4>0,$O4,0.88) -> 0.88 | F4: 7990 | G4: UK | H4: =IF($M4>0,IF($L4<>1,$R4,IFERROR(INDEX('JLR Materials'!$D$2:$D$20001,MATCH($K4,'JLR Materials'!$A$2:$A$20001,0)),$R4)),$R4) -> 2026-09 | I4: =IF($M4>0,"JLR rate card — material code "&$K4,$Q4) -> UK stainless distributor, Jun 2026. Index-anchored 2026-07 refresh. | Refresh 2026-09: +£0.129/kg from 1kg ss_sur £2.037→£2.164/kg, 0.03kg ni £12.302→£12.378/kg; premiums held | J4: Medium | K4: =IFERROR(INDEX(Mapping!$C$2:$C$549,MATCH($A4,Mapping!$A$2:$A$549,0)),"") | L4: =IF($K4="",0,COUNTIFS('JLR Materials'!$A$2:$A$20001,$K4,'JLR Materials'!$C$2:$C$20001,IF(Settings!$B$2="","<>",Settings!$B$2),'JLR Materials'!$D$2:$D$20001,IF(Settings!$B$4="","<>",Settings!$B$4))) -> 0 | M4: =IF($L4<>1,0,SUMIFS('JLR Materials'!$E$2:$E$20001,'JLR Materials'!$A$2:$A$20001,$K4,'JLR Materials'!$C$2:$C$20001,IF(Settings!$B$2="","<>",Settings!$B$2),'JLR Materials'!$D$2:$D$20001,IF(Settings!$B$4="","<>",Settings!$B$4))) -> 0 | N4: =IF($L4<>1,0,SUMIFS('JLR Materials'!$F$2:$F$20001,'JLR Materials'!$A$2:$A$20001,$K4,'JLR Materials'!$C$2:$C$20001,IF(Settings!$B$2="","<>",Settings!$B$2),'JLR Materials'!$D$2:$D$20001,IF(Settings!$B$4="","<>",Settings!$B$4))) -> 0 | O4: =IF($N4=0,0,IF(Settings!$B$5="percent",$M4*$N4/100,$N4)) -> 0 | P4: =IF($L4<>1,0,SUMIFS('JLR Materials'!$G$2:$G$20001,'JLR Materials'!$A$2:$A$20001,$K4,'JLR Materials'!$C$2:$C$20001,IF(Settings!$B$2="","<>",Settings!$B$2),'JLR Materials'!$D$2:$D$20001,IF(Settings!$B$4="","<>",Settings!$B$4))) -> 0 | Q4: UK stainless distributor, Jun 2026. Index-anchored 2026-07 refresh. | Refresh 2026-09: +£0.129/kg from 1kg ss_sur £2.037→£2.164/kg, 0.03kg ni £12.302→£12.378/kg; premiums held | R4: 2026-09
A5: mat-steel4140 | B5: 4140 / 42CrMo4 / EN19 (Chromoly Alloy Steel) | C5: Alloy Steel | D5: =IF($M5>0,$M5,1.21) -> 1.21 | E5: =IF($O5>0,$O5,0.22) -> 0.22 | F5: 7850 | G5: UK | H5: =IF($M5>0,IF($L5<>1,$R5,IFERROR(INDEX('JLR Materials'!$D$2:$D$20001,MATCH($K5,'JLR Materials'!$A$2:$A$20001,0)),$R5)),$R5) -> 2026-09 | I5: =IF($M5>0,"JLR rate card — material code "&$K5,$Q5) -> UK steel stockholder, Jun 2026. Index-anchored 2026-07 refresh. | Refresh 2026-09: INDEX FLAT — Index flat: Kallanish N-Europe wire rod ’stable’ (Jun 2026), ’decrease slightly’ (Jul), ’remain stable’ / ’flat’ (Sep 2026) — carbon and alloy bar unchanged. | J5: Medium | K5: =IFERROR(INDEX(Mapping!$C$2:$C$549,MATCH($A5,Mapping!$A$2:$A$549,0)),"") | L5: =IF($K5="",0,COUNTIFS('JLR Materials'!$A$2:$A$20001,$K5,'JLR Materials'!$C$2:$C$20001,IF(Settings!$B$2="","<>",Settings!$B$2),'JLR Materials'!$D$2:$D$20001,IF(Settings!$B$4="","<>",Settings!$B$4))) -> 0 | M5: =IF($L5<>1,0,SUMIFS('JLR Materials'!$E$2:$E$20001,'JLR Materials'!$A$2:$A$20001,$K5,'JLR Materials'!$C$2:$C$20001,IF(Settings!$B$2="","<>",Settings!$B$2),'JLR Materials'!$D$2:$D$20001,IF(Settings!$B$4="","<>",Settings!$B$4))) -> 0 | N5: =IF($L5<>1,0,SUMIFS('JLR Materials'!$F$2:$F$20001,'JLR Materials'!$A$2:$A$20001,$K5,'JLR Materials'!$C$2:$C$20001,IF(Settings!$B$2="","<>",Settings!$B$2),'JLR Materials'!$D$2:$D$20001,IF(Settings!$B$4="","<>",Settings!$B$4))) -> 0 | O5: =IF($N5=0,0,IF(Settings!$B$5="percent",$M5*$N5/100,$N5)) -> 0 | P5: =IF($L5<>1,0,SUMIFS('JLR Materials'!$G$2:$G$20001,'JLR Materials'!$A$2:$A$20001,$K5,'JLR Materials'!$C$2:$C$20001,IF(Settings!$B$2="","<>",Settings!$B$2),'JLR Materials'!$D$2:$D$20001,IF(Settings!$B$4="","<>",Settings!$B$4))) -> 0 | Q5: UK steel stockholder, Jun 2026. Index-anchored 2026-07 refresh. | Refresh 2026-09: INDEX FLAT — Index flat: Kallanish N-Europe wire rod ’stable’ (Jun 2026), ’decrease slightly’ (Jul), ’remain stable’ / ’flat’ (Sep 2026) — carbon and alloy bar unchanged. | R5: 2026-09
A6: mat-ti6al4v | B6: Ti-6Al-4V | C6: Titanium | D6: =IF($M6>0,$M6,47.13) -> 47.13 | E6: =IF($O6>0,$O6,15.88) -> 15.88 | F6: 4430 | G6: UK | H6: =IF($M6>0,IF($L6<>1,$R6,IFERROR(INDEX('JLR Materials'!$D$2:$D$20001,MATCH($K6,'JLR Materials'!$A$2:$A$20001,0)),$R6)),$R6) -> 2026-09 | I6: =IF($M6>0,"JLR rate card — material code "&$K6,$Q6) -> Titanium distributor UK, Jun 2026. Index-anchored 2026-07 refresh. | Refresh 2026-09: −£0.367/kg from 0.9kg ti £5.398→£4.989/kg; premiums held | J6: Low | K6: =IFERROR(INDEX(Mapping!$C$2:$C$549,MATCH($A6,Mapping!$A$2:$A$549,0)),"") | L6: =IF($K6="",0,COUNTIFS('JLR Materials'!$A$2:$A$20001,$K6,'JLR Materials'!$C$2:$C$20001,IF(Settings!$B$2="","<>",Settings!$B$2),'JLR Materials'!$D$2:$D$20001,IF(Settings!$B$4="","<>",Settings!$B$4))) -> 0 | M6: =IF($L6<>1,0,SUMIFS('JLR Materials'!$E$2:$E$20001,'JLR Materials'!$A$2:$A$20001,$K6,'JLR Materials'!$C$2:$C$20001,IF(Settings!$B$2="","<>",Settings!$B$2),'JLR Materials'!$D$2:$D$20001,IF(Settings!$B$4="","<>",Settings!$B$4))) -> 0 | N6: =IF($L6<>1,0,SUMIFS('JLR Materials'!$F$2:$F$20001,'JLR Materials'!$A$2:$A$20001,$K6,'JLR Materials'!$C$2:$C$20001,IF(Settings!$B$2="","<>",Settings!$B$2),'JLR Materials'!$D$2:$D$20001,IF(Settings!$B$4="","<>",Settings!$B$4))) -> 0 | O6: =IF($N6=0,0,IF(Settings!$B$5="percent",$M6*$N6/100,$N6)) -> 0 | P6: =IF($L6<>1,0,SUMIFS('JLR Materials'!$G$2:$G$20001,'JLR Materials'!$A$2:$A$20001,$K6,'JLR Materials'!$C$2:$C$20001,IF(Settings!$B$2="","<>",Settings!$B$2),'JLR Materials'!$D$2:$D$20001,IF(Settings!$B$4="","<>",Settings!$B$4))) -> 0 | Q6: Titanium distributor UK, Jun 2026. Index-anchored 2026-07 refresh. | Refresh 2026-09: −£0.367/kg from 0.9kg ti £5.398→£4.989/kg; premiums held | R6: 2026-09
A7: mat-virtual | B7: Virtual / Pass-through | C7: Virtual | D7: =IF($M7>0,$M7,1) -> 1 | E7: =IF($O7>0,$O7,0) -> 0 | F7: 1000 | G7: UK | H7: =IF($M7>0,IF($L7<>1,$R7,IFERROR(INDEX('JLR Materials'!$D$2:$D$20001,MATCH($K7,'JLR Materials'!$A$2:$A$20001,0)),$R7)),$R7) -> 2026-06-14 | I7: =IF($M7>0,"JLR rate card — material code "&$K7,$Q7) -> Placeholder for directCost modules (painting, BIW, PCB, PCBA). Price is irrelevant — directCost overrides. | J7: Medium | K7: =IFERROR(INDEX(Mapping!$C$2:$C$549,MATCH($A7,Mapping!$A$2:$A$549,0)),"") | L7: =IF($K7="",0,COUNTIFS('JLR Materials'!$A$2:$A$20001,$K7,'JLR Materials'!$C$2:$C$20001,IF(Settings!$B$2="","<>",Settings!$B$2),'JLR Materials'!$D$2:$D$20001,IF(Settings!$B$4="","<>",Settings!$B$4))) -> 0 | M7: =IF($L7<>1,0,SUMIFS('JLR Materials'!$E$2:$E$20001,'JLR Materials'!$A$2:$A$20001,$K7,'JLR Materials'!$C$2:$C$20001,IF(Settings!$B$2="","<>",Settings!$B$2),'JLR Materials'!$D$2:$D$20001,IF(Settings!$B$4="","<>",Settings!$B$4))) -> 0 | N7: =IF($L7<>1,0,SUMIFS('JLR Materials'!$F$2:$F$20001,'JLR Materials'!$A$2:$A$20001,$K7,'JLR Materials'!$C$2:$C$20001,IF(Settings!$B$2="","<>",Settings!$B$2),'JLR Materials'!$D$2:$D$20001,IF(Settings!$B$4="","<>",Settings!$B$4))) -> 0 | O7: =IF($N7=0,0,IF(Settings!$B$5="percent",$M7*$N7/100,$N7)) -> 0 | P7: =IF($L7<>1,0,SUMIFS('JLR Materials'!$G$2:$G$20001,'JLR Materials'!$A$2:$A$20001,$K7,'JLR Materials'!$C$2:$C$20001,IF(Settings!$B$2="","<>",Settings!$B$2),'JLR Materials'!$D$2:$D$20001,IF(Settings!$B$4="","<>",Settings!$B$4))) -> 0 | Q7: Placeholder for directCost modules (painting, BIW, PCB, PCBA). Price is irrelevant — directCost overrides. | R7: 2026-06-14
A8: mat-en8 | B8: EN8 / 080M40 (Medium Carbon) | C8: Carbon Steel | D8: =IF($M8>0,$M8,0.98) -> 0.98 | E8: =IF($O8>0,$O8,0.22) -> 0.22 | F8: 7850 | G8: UK | H8: =IF($M8>0,IF($L8<>1,$R8,IFERROR(INDEX('JLR Materials'!$D$2:$D$20001,MATCH($K8,'JLR Materials'!$A$2:$A$20001,0)),$R8)),$R8) -> 2026-09 | I8: =IF($M8>0,"JLR rate card — material code "&$K8,$Q8) -> Index-anchored 2026-07 refresh. General medium-carbon machining bar — shafts, studs, general engineering. | Refresh 2026-09: INDEX FLAT — Index flat: Kallanish N-Europe wire rod ’stable’ (Jun 2026), ’decrease slightly’ (Jul), ’remain stable’ / ’flat’ (Sep 2026) — carbon and alloy bar unchanged. | J8: Medium | K8: =IFERROR(INDEX(Mapping!$C$2:$C$549,MATCH($A8,Mapping!$A$2:$A$549,0)),"") | L8: =IF($K8="",0,COUNTIFS('JLR Materials'!$A$2:$A$20001,$K8,'JLR Materials'!$C$2:$C$20001,IF(Settings!$B$2="","<>",Settings!$B$2),'JLR Materials'!$D$2:$D$20001,IF(Settings!$B$4="","<>",Settings!$B$4))) -> 0 | M8: =IF($L8<>1,0,SUMIFS('JLR Materials'!$E$2:$E$20001,'JLR Materials'!$A$2:$A$20001,$K8,'JLR Materials'!$C$2:$C$20001,IF(Settings!$B$2="","<>",Settings!$B$2),'JLR Materials'!$D$2:$D$20001,IF(Settings!$B$4="","<>",Settings!$B$4))) -> 0 | N8: =IF($L8<>1,0,SUMIFS('JLR Materials'!$F$2:$F$20001,'JLR Materials'!$A$2:$A$20001,$K8,'JLR Materials'!$C$2:$C$20001,IF(Settings!$B$2="","<>",Settings!$B$2),'JLR Materials'!$D$2:$D$20001,IF(Settings!$B$4="","<>",Settings!$B$4))) -> 0 | O8: =IF($N8=0,0,IF(Settings!$B$5="percent",$M8*$N8/100,$N8)) -> 0 | P8: =IF($L8<>1,0,SUMIFS('JLR Materials'!$G$2:$G$20001,'JLR Materials'!$A$2:$A$20001,$K8,'JLR Materials'!$C$2:$C$20001,IF(Settings!$B$2="","<>",Settings!$B$2),'JLR Materials'!$D$2:$D$20001,IF(Settings!$B$4="","<>",Settings!$B$4))) -> 0 | Q8: Index-anchored 2026-07 refresh. General medium-carbon machining bar — shafts, studs, general engineering. | Refresh 2026-09: INDEX FLAT — Index flat: Kallanish N-Europe wire rod ’stable’ (Jun 2026), ’decrease slightly’ (Jul), ’remain stable’ / ’flat’ (Sep 2026) — carbon and alloy bar unchanged. | R8: 2026-09
A9: mat-ss304-bar | B9: 304 Stainless Bar | C9: Stainless Steel | D9: =IF($M9>0,$M9,3.53) -> 3.53 | E9: =IF($O9>0,$O9,0.83) -> 0.83 | F9: 8000 | G9: UK | H9: =IF($M9>0,IF($L9<>1,$R9,IFERROR(INDEX('JLR Materials'!$D$2:$D$20001,MATCH($K9,'JLR Materials'!$A$2:$A$20001,0)),$R9)),$R9) -> 2026-09 | I9: =IF($M9>0,"JLR rate card — material code "&$K9,$Q9) -> Index-anchored 2026-07 refresh. General austenitic machining bar — fittings, shafts, food/chemical. | Refresh 2026-09: +£0.127/kg from 1kg ss_sur £2.037→£2.164/kg; premiums held | J9: Medium | K9: =IFERROR(INDEX(Mapping!$C$2:$C$549,MATCH($A9,Mapping!$A$2:$A$549,0)),"") | L9: =IF($K9="",0,COUNTIFS('JLR Materials'!$A$2:$A$20001,$K9,'JLR Materials'!$C$2:$C$20001,IF(Settings!$B$2="","<>",Settings!$B$2),'JLR Materials'!$D$2:$D$20001,IF(Settings!$B$4="","<>",Settings!$B$4))) -> 0 | M9: =IF($L9<>1,0,SUMIFS('JLR Materials'!$E$2:$E$20001,'JLR Materials'!$A$2:$A$20001,$K9,'JLR Materials'!$C$2:$C$20001,IF(Settings!$B$2="","<>",Settings!$B$2),'JLR Materials'!$D$2:$D$20001,IF(Settings!$B$4="","<>",Settings!$B$4))) -> 0 | N9: =IF($L9<>1,0,SUMIFS('JLR Materials'!$F$2:$F$20001,'JLR Materials'!$A$2:$A$20001,$K9,'JLR Materials'!$C$2:$C$20001,IF(Settings!$B$2="","<>",Settings!$B$2),'JLR Materials'!$D$2:$D$20001,IF(Settings!$B$4="","<>",Settings!$B$4))) -> 0 | O9: =IF($N9=0,0,IF(Settings!$B$5="percent",$M9*$N9/100,$N9)) -> 0 | P9: =IF($L9<>1,0,SUMIFS('JLR Materials'!$G$2:$G$20001,'JLR Materials'!$A$2:$A$20001,$K9,'JLR Materials'!$C$2:$C$20001,IF(Settings!$B$2="","<>",Settings!$B$2),'JLR Materials'!$D$2:$D$20001,IF(Settings!$B$4="","<>",Settings!$B$4))) -> 0 | Q9: Index-anchored 2026-07 refresh. General austenitic machining bar — fittings, shafts, food/chemical. | Refresh 2026-09: +£0.127/kg from 1kg ss_sur £2.037→£2.164/kg; premiums held | R9: 2026-09
A10: mat-ss303 | B10: 303 Free-Machining Stainless Bar | C10: Stainless Steel | D10: =IF($M10>0,$M10,3.83) -> 3.83 | E10: =IF($O10>0,$O10,0.83) -> 0.83 | F10: 8000 | G10: UK | H10: =IF($M10>0,IF($L10<>1,$R10,IFERROR(INDEX('JLR Materials'!$D$2:$D$20001,MATCH($K10,'JLR Materials'!$A$2:$A$20001,0)),$R10)),$R10) -> 2026-09 | I10: =IF($M10>0,"JLR rate card — material code "&$K10,$Q10) -> Index-anchored 2026-07 refresh. Sulphur-added free-machining austenitic — high-volume turned parts, fasteners. | Refresh 2026-09: +£0.127/kg from 1kg ss_sur £2.037→£2.164/kg; premiums held | J10: Medium | K10: =IFERROR(INDEX(Mapping!$C$2:$C$549,MATCH($A10,Mapping!$A$2:$A$549,0)),"") | L10: =IF($K10="",0,COUNTIFS('JLR Materials'!$A$2:$A$20001,$K10,'JLR Materials'!$C$2:$C$20001,IF(Settings!$B$2="","<>",Settings!$B$2),'JLR Materials'!$D$2:$D$20001,IF(Settings!$B$4="","<>",Settings!$B$4))) -> 0 | M10: =IF($L10<>1,0,SUMIFS('JLR Materials'!$E$2:$E$20001,'JLR Materials'!$A$2:$A$20001,$K10,'JLR Materials'!$C$2:$C$20001,IF(Settings!$B$2="","<>",Settings!$B$2),'JLR Materials'!$D$2:$D$20001,IF(Settings!$B$4="","<>",Settings!$B$4))) -> 0 | N10: =IF($L10<>1,0,SUMIFS('JLR Materials'!$F$2:$F$20001,'JLR Materials'!$A$2:$A$20001,$K10,'JLR Materials'!$C$2:$C$20001,IF(Settings!$B$2="","<>",Settings!$B$2),'JLR Materials'!$D$2:$D$20001,IF(Settings!$B$4="","<>",Settings!$B$4))) -> 0 | O10: =IF($N10=0,0,IF(Settings!$B$5="percent",$M10*$N10/100,$N10)) -> 0 | P10: =IF($L10<>1,0,SUMIFS('JLR Materials'!$G$2:$G$20001,'JLR Materials'!$A$2:$A$20001,$K10,'JLR Materials'!$C$2:$C$20001,IF(Settings!$B$2="","<>",Settings!$B$2),'JLR Materials'!$D$2:$D$20001,IF(Settings!$B$4="","<>",Settings!$B$4))) -> 0 | Q10: Index-anchored 2026-07 refresh. Sulphur-added free-machining austenitic — high-volume turned parts, fasteners. | Refresh 2026-09: +£0.127/kg from 1kg ss_sur £2.037→£2.164/kg; premiums held | R10: 2026-09
A11: mat-al6082-bar | B11: 6082-T6 Aluminium Bar | C11: Aluminium | D11: =IF($M11>0,$M11,3.49) -> 3.49 | E11: =IF($O11>0,$O11,0.54) -> 0.54 | F11: 2700 | G11: UK | H11: =IF($M11>0,IF($L11<>1,$R11,IFERROR(INDEX('JLR Materials'!$D$2:$D$20001,MATCH($K11,'JLR Materials'!$A$2:$A$20001,0)),$R11)),$R11) -> 2026-09 | I11: =IF($M11>0,"JLR rate card — material code "&$K11,$Q11) -> Index-anchored 2026-07 refresh. Structural 6xxx machining bar/plate — brackets, jigs, structural parts. | Refresh 2026-09: −£0.060/kg from 0.97kg al £2.910→£2.849/kg; premiums held | J11: Medium | K11: =IFERROR(INDEX(Mapping!$C$2:$C$549,MATCH($A11,Mapping!$A$2:$A$549,0)),"") | L11: =IF($K11="",0,COUNTIFS('JLR Materials'!$A$2:$A$20001,$K11,'JLR Materials'!$C$2:$C$20001,IF(Settings!$B$2="","<>",Settings!$B$2),'JLR Materials'!$D$2:$D$20001,IF(Settings!$B$4="","<>",Settings!$B$4))) -> 0 | M11: =IF($L11<>1,0,SUMIFS('JLR Materials'!$E$2:$E$20001,'JLR Materials'!$A$2:$A$20001,$K11,'JLR Materials'!$C$2:$C$20001,IF(Settings!$B$2="","<>",Settings!$B$2),'JLR Materials'!$D$2:$D$20001,IF(Settings!$B$4="","<>",Settings!$B$4))) -> 0 | N11: =IF($L11<>1,0,SUMIFS('JLR Materials'!$F$2:$F$20001,'JLR Materials'!$A$2:$A$20001,$K11,'JLR Materials'!$C$2:$C$20001,IF(Settings!$B$2="","<>",Settings!$B$2),'JLR Materials'!$D$2:$D$20001,IF(Settings!$B$4="","<>",Settings!$B$4))) -> 0 | O11: =IF($N11=0,0,IF(Settings!$B$5="percent",$M11*$N11/100,$N11)) -> 0 | P11: =IF($L11<>1,0,SUMIFS('JLR Materials'!$G$2:$G$20001,'JLR Materials'!$A$2:$A$20001,$K11,'JLR Materials'!$C$2:$C$20001,IF(Settings!$B$2="","<>",Settings!$B$2),'JLR Materials'!$D$2:$D$20001,IF(Settings!$B$4="","<>",Settings!$B$4))) -> 0 | Q11: Index-anchored 2026-07 refresh. Structural 6xxx machining bar/plate — brackets, jigs, structural parts. | Refresh 2026-09: −£0.060/kg from 0.97kg al £2.910→£2.849/kg; premiums held | R11: 2026-09
A12: mat-al2011 | B12: 2011-T3 Free-Machining Al Bar | C12: Aluminium | D12: =IF($M12>0,$M12,3.93) -> 3.93 | E12: =IF($O12>0,$O12,0.55) -> 0.55 | F12: 2830 | G12: UK | H12: =IF($M12>0,IF($L12<>1,$R12,IFERROR(INDEX('JLR Materials'!$D$2:$D$20001,MATCH($K12,'JLR Materials'!$A$2:$A$20001,0)),$R12)),$R12) -> 2026-09 | I12: =IF($M12>0,"JLR rate card — material code "&$K12,$Q12) -> Index-anchored 2026-07 refresh. Free-machining Al-Cu-Pb — high-speed screw-machine parts, fittings. | Refresh 2026-09: −£0.022/kg from 0.93kg al £2.910→£2.849/kg, 0.05kg cu £10.070→£10.768/kg; premiums held | J12: Low | K12: =IFERROR(INDEX(Mapping!$C$2:$C$549,MATCH($A12,Mapping!$A$2:$A$549,0)),"") | L12: =IF($K12="",0,COUNTIFS('JLR Materials'!$A$2:$A$20001,$K12,'JLR Materials'!$C$2:$C$20001,IF(Settings!$B$2="","<>",Settings!$B$2),'JLR Materials'!$D$2:$D$20001,IF(Settings!$B$4="","<>",Settings!$B$4))) -> 0 | M12: =IF($L12<>1,0,SUMIFS('JLR Materials'!$E$2:$E$20001,'JLR Materials'!$A$2:$A$20001,$K12,'JLR Materials'!$C$2:$C$20001,IF(Settings!$B$2="","<>",Settings!$B$2),'JLR Materials'!$D$2:$D$20001,IF(Settings!$B$4="","<>",Settings!$B$4))) -> 0 | N12: =IF($L12<>1,0,SUMIFS('JLR Materials'!$F$2:$F$20001,'JLR Materials'!$A$2:$A$20001,$K12,'JLR Materials'!$C$2:$C$20001,IF(Settings!$B$2="","<>",Settings!$B$2),'JLR Materials'!$D$2:$D$20001,IF(Settings!$B$4="","<>",Settings!$B$4))) -> 0 | O12: =IF($N12=0,0,IF(Settings!$B$5="percent",$M12*$N12/100,$N12)) -> 0 | P12: =IF($L12<>1,0,SUMIFS('JLR Materials'!$G$2:$G$20001,'JLR Materials'!$A$2:$A$20001,$K12,'JLR Materials'!$C$2:$C$20001,IF(Settings!$B$2="","<>",Settings!$B$2),'JLR Materials'!$D$2:$D$20001,IF(Settings!$B$4="","<>",Settings!$B$4))) -> 0 | Q12: Index-anchored 2026-07 refresh. Free-machining Al-Cu-Pb — high-speed screw-machine parts, fittings. | Refresh 2026-09: −£0.022/kg from 0.93kg al £2.910→£2.849/kg, 0.05kg cu £10.070→£10.768/kg; premiums held | R12: 2026-09
A13: mat-brass-cz121 | B13: CZ121 / CW614N Free-Machining Brass | C13: Copper Alloy | D13: =IF($M13>0,$M13,7.7) -> 7.7 | E13: =IF($O13>0,$O13,3.3) -> 3.3 | F13: 8490 | G13: UK | H13: =IF($M13>0,IF($L13<>1,$R13,IFERROR(INDEX('JLR Materials'!$D$2:$D$20001,MATCH($K13,'JLR Materials'!$A$2:$A$20001,0)),$R13)),$R13) -> 2026-09 | I13: =IF($M13>0,"JLR rate card — material code "&$K13,$Q13) -> Index-anchored 2026-07 refresh. Standard free-machining brass bar — fittings, valve parts, connectors. | Refresh 2026-09: +£0.697/kg from 0.58kg cu £10.070→£10.768/kg, 0.39kg zn £2.164→£2.913/kg, 0.03kg pb £1.442→£1.438/kg; premiums held | J13: Low | K13: =IFERROR(INDEX(Mapping!$C$2:$C$549,MATCH($A13,Mapping!$A$2:$A$549,0)),"") | L13: =IF($K13="",0,COUNTIFS('JLR Materials'!$A$2:$A$20001,$K13,'JLR Materials'!$C$2:$C$20001,IF(Settings!$B$2="","<>",Settings!$B$2),'JLR Materials'!$D$2:$D$20001,IF(Settings!$B$4="","<>",Settings!$B$4))) -> 0 | M13: =IF($L13<>1,0,SUMIFS('JLR Materials'!$E$2:$E$20001,'JLR Materials'!$A$2:$A$20001,$K13,'JLR Materials'!$C$2:$C$20001,IF(Settings!$B$2="","<>",Settings!$B$2),'JLR Materials'!$D$2:$D$20001,IF(Settings!$B$4="","<>",Settings!$B$4))) -> 0 | N13: =IF($L13<>1,0,SUMIFS('JLR Materials'!$F$2:$F$20001,'JLR Materials'!$A$2:$A$20001,$K13,'JLR Materials'!$C$2:$C$20001,IF(Settings!$B$2="","<>",Settings!$B$2),'JLR Materials'!$D$2:$D$20001,IF(Settings!$B$4="","<>",Settings!$B$4))) -> 0 | O13: =IF($N13=0,0,IF(Settings!$B$5="percent",$M13*$N13/100,$N13)) -> 0 | P13: =IF($L13<>1,0,SUMIFS('JLR Materials'!$G$2:$G$20001,'JLR Materials'!$A$2:$A$20001,$K13,'JLR Materials'!$C$2:$C$20001,IF(Settings!$B$2="","<>",Settings!$B$2),'JLR Materials'!$D$2:$D$20001,IF(Settings!$B$4="","<>",Settings!$B$4))) -> 0 | Q13: Index-anchored 2026-07 refresh. Standard free-machining brass bar — fittings, valve parts, connectors. | Refresh 2026-09: +£0.697/kg from 0.58kg cu £10.070→£10.768/kg, 0.39kg zn £2.164→£2.913/kg, 0.03kg pb £1.442→£1.438/kg; premiums held | R13: 2026-09
A14: mat-bronze-pb1 | B14: PB1 Phosphor Bronze Bar | C14: Copper Alloy | D14: =IF($M14>0,$M14,13.91) -> 13.91 | E14: =IF($O14>0,$O14,4.23) -> 4.23 | F14: 8800 | G14: UK | H14: =IF($M14>0,IF($L14<>1,$R14,IFERROR(INDEX('JLR Materials'!$D$2:$D$20001,MATCH($K14,'JLR Materials'!$A$2:$A$20001,0)),$R14)),$R14) -> 2026-09 | I14: =IF($M14>0,"JLR rate card — material code "&$K14,$Q14) -> Index-anchored 2026-07 refresh. Phosphor bronze bar — bearings, bushes, worm wheels, high-load sliding. | Refresh 2026-09: +£4.710/kg from 0.89kg cu £10.070→£10.768/kg, 0.105kg sn £38.211→£41.201/kg, floored at commodity content £13.91/kg (previous level was below the metal it contains); premiums held | J14: Low | K14: =IFERROR(INDEX(Mapping!$C$2:$C$549,MATCH($A14,Mapping!$A$2:$A$549,0)),"") | L14: =IF($K14="",0,COUNTIFS('JLR Materials'!$A$2:$A$20001,$K14,'JLR Materials'!$C$2:$C$20001,IF(Settings!$B$2="","<>",Settings!$B$2),'JLR Materials'!$D$2:$D$20001,IF(Settings!$B$4="","<>",Settings!$B$4))) -> 0 | M14: =IF($L14<>1,0,SUMIFS('JLR Materials'!$E$2:$E$20001,'JLR Materials'!$A$2:$A$20001,$K14,'JLR Materials'!$C$2:$C$20001,IF(Settings!$B$2="","<>",Settings!$B$2),'JLR Materials'!$D$2:$D$20001,IF(Settings!$B$4="","<>",Settings!$B$4))) -> 0 | N14: =IF($L14<>1,0,SUMIFS('JLR Materials'!$F$2:$F$20001,'JLR Materials'!$A$2:$A$20001,$K14,'JLR Materials'!$C$2:$C$20001,IF(Settings!$B$2="","<>",Settings!$B$2),'JLR Materials'!$D$2:$D$20001,IF(Settings!$B$4="","<>",Settings!$B$4))) -> 0 | O14: =IF($N14=0,0,IF(Settings!$B$5="percent",$M14*$N14/100,$N14)) -> 0 | P14: =IF($L14<>1,0,SUMIFS('JLR Materials'!$G$2:$G$20001,'JLR Materials'!$A$2:$A$20001,$K14,'JLR Materials'!$C$2:$C$20001,IF(Settings!$B$2="","<>",Settings!$B$2),'JLR Materials'!$D$2:$D$20001,IF(Settings!$B$4="","<>",Settings!$B$4))) -> 0 | Q14: Index-anchored 2026-07 refresh. Phosphor bronze bar — bearings, bushes, worm wheels, high-load sliding. | Refresh 2026-09: +£4.710/kg from 0.89kg cu £10.070→£10.768/kg, 0.105kg sn £38.211→£41.201/kg, floored at commodity content £13.91/kg (previous level was below the metal it contains); premiums held | R14: 2026-09
A15: mat-pom-c | B15: POM-C (Acetal / Delrin Stock) | C15: Engineering Plastic (Stock) | D15: =IF($M15>0,$M15,3.1) -> 3.1 | E15: =IF($O15>0,$O15,0.1) -> 0.1 | F15: 1410 | G15: UK | H15: =IF($M15>0,IF($L15<>1,$R15,IFERROR(INDEX('JLR Materials'!$D$2:$D$20001,MATCH($K15,'JLR Materials'!$A$2:$A$20001,0)),$R15)),$R15) -> 2026-09 | I15: =IF($M15>0,"JLR rate card — material code "&$K15,$Q15) -> Index-anchored 2026-07. Acetal copolymer rod/sheet — precision gears, bushes, manifolds; excellent machinability. | Refresh 2026-09: NOT SOURCED — pom: Not sourced this period: engineering resin prices are paywalled (PIE/ICIS). Direction only: PC rising through Aug 2026, PA6 rebounding, PA66 under pressure, PET declining — no like-for-like June→Sep figures. Held at the June 2026 price. | J15: Medium | K15: =IFERROR(INDEX(Mapping!$C$2:$C$549,MATCH($A15,Mapping!$A$2:$A$549,0)),"") | L15: =IF($K15="",0,COUNTIFS('JLR Materials'!$A$2:$A$20001,$K15,'JLR Materials'!$C$2:$C$20001,IF(Settings!$B$2="","<>",Settings!$B$2),'JLR Materials'!$D$2:$D$20001,IF(Settings!$B$4="","<>",Settings!$B$4))) -> 0 | M15: =IF($L15<>1,0,SUMIFS('JLR Materials'!$E$2:$E$20001,'JLR Materials'!$A$2:$A$20001,$K15,'JLR Materials'!$C$2:$C$20001,IF(Settings!$B$2="","<>",Settings!$B$2),'JLR Materials'!$D$2:$D$20001,IF(Settings!$B$4="","<>",Settings!$B$4))) -> 0 | N15: =IF($L15<>1,0,SUMIFS('JLR Materials'!$F$2:$F$20001,'JLR Materials'!$A$2:$A$20001,$K15,'JLR Materials'!$C$2:$C$20001,IF(Settings!$B$2="","<>",Settings!$B$2),'JLR Materials'!$D$2:$D$20001,IF(Settings!$B$4="","<>",Settings!$B$4))) -> 0 | O15: =IF($N15=0,0,IF(Settings!$B$5="percent",$M15*$N15/100,$N15)) -> 0 | P15: =IF($L15<>1,0,SUMIFS('JLR Materials'!$G$2:$G$20001,'JLR Materials'!$A$2:$A$20001,$K15,'JLR Materials'!$C$2:$C$20001,IF(Settings!$B$2="","<>",Settings!$B$2),'JLR Materials'!$D$2:$D$20001,IF(Settings!$B$4="","<>",Settings!$B$4))) -> 0 | Q15: Index-anchored 2026-07. Acetal copolymer rod/sheet — precision gears, bushes, manifolds; excellent machinability. | Refresh 2026-09: NOT SOURCED — pom: Not sourced this period: engineering resin prices are paywalled (PIE/ICIS). Direction only: PC rising through Aug 2026, PA6 rebounding, PA66 under pressure, PET declining — no like-for-like June→Sep figures. Held at the June 2026 price. | R15: 2026-09
A16: mat-pa6-cast | B16: Nylon 6 (Cast PA6 Stock) | C16: Engineering Plastic (Stock) | D16: =IF($M16>0,$M16,4.2) -> 4.2 | E16: =IF($O16>0,$O16,0.1) -> 0.1 | F16: 1150 | G16: UK | H16: =IF($M16>0,IF($L16<>1,$R16,IFERROR(INDEX('JLR Materials'!$D$2:$D$20001,MATCH($K16,'JLR Materials'!$A$2:$A$20001,0)),$R16)),$R16) -> 2026-09 | I16: =IF($M16>0,"JLR rate card — material code "&$K16,$Q16) -> Index-anchored 2026-07. Cast nylon rod/slab — wear pads, sprockets, rollers, guide rails. | Refresh 2026-09: NOT SOURCED — pa6: Not sourced this period: engineering resin prices are paywalled (PIE/ICIS). Direction only: PC rising through Aug 2026, PA6 rebounding, PA66 under pressure, PET declining — no like-for-like June→Sep figures. Held at the June 2026 price. | J16: Medium | K16: =IFERROR(INDEX(Mapping!$C$2:$C$549,MATCH($A16,Mapping!$A$2:$A$549,0)),"") | L16: =IF($K16="",0,COUNTIFS('JLR Materials'!$A$2:$A$20001,$K16,'JLR Materials'!$C$2:$C$20001,IF(Settings!$B$2="","<>",Settings!$B$2),'JLR Materials'!$D$2:$D$20001,IF(Settings!$B$4="","<>",Settings!$B$4))) -> 0 | M16: =IF($L16<>1,0,SUMIFS('JLR Materials'!$E$2:$E$20001,'JLR Materials'!$A$2:$A$20001,$K16,'JLR Materials'!$C$2:$C$20001,IF(Settings!$B$2="","<>",Settings!$B$2),'JLR Materials'!$D$2:$D$20001,IF(Settings!$B$4="","<>",Settings!$B$4))) -> 0 | N16: =IF($L16<>1,0,SUMIFS('JLR Materials'!$F$2:$F$20001,'JLR Materials'!$A$2:$A$20001,$K16,'JLR Materials'!$C$2:$C$20001,IF(Settings!$B$2="","<>",Settings!$B$2),'JLR Materials'!$D$2:$D$20001,IF(Settings!$B$4="","<>",Settings!$B$4))) -> 0 | O16: =IF($N16=0,0,IF(Settings!$B$5="percent",$M16*$N16/100,$N16)) -> 0 | P16: =IF($L16<>1,0,SUMIFS('JLR Materials'!$G$2:$G$20001,'JLR Materials'!$A$2:$A$20001,$K16,'JLR Materials'!$C$2:$C$20001,IF(Settings!$B$2="","<>",Settings!$B$2),'JLR Materials'!$D$2:$D$20001,IF(Settings!$B$4="","<>",Settings!$B$4))) -> 0 | Q16: Index-anchored 2026-07. Cast nylon rod/slab — wear pads, sprockets, rollers, guide rails. | Refresh 2026-09: NOT SOURCED — pa6: Not sourced this period: engineering resin prices are paywalled (PIE/ICIS). Direction only: PC rising through Aug 2026, PA6 rebounding, PA66 under pressure, PET declining — no like-for-like June→Sep figures. Held at the June 2026 price. | R16: 2026-09
A17: mat-ptfe | B17: PTFE (Virgin Stock) | C17: Engineering Plastic (Stock) | D17: =IF($M17>0,$M17,12.5) -> 12.5 | E17: =IF($O17>0,$O17,0.2) -> 0.2 | F17: 2170 | G17: UK | H17: =IF($M17>0,IF($L17<>1,$R17,IFERROR(INDEX('JLR Materials'!$D$2:$D$20001,MATCH($K17,'JLR Materials'!$A$2:$A$20001,0)),$R17)),$R17) -> 2026-09 | I17: =IF($M17>0,"JLR rate card — material code "&$K17,$Q17) -> Index-anchored 2026-07. Virgin PTFE rod/sheet — seals, insulators, chemical/low-friction parts. | Refresh 2026-09: SPECIALTY — no public market index for this grade; held at the June 2026 price — refresh by supplier quote | J17: Low | K17: =IFERROR(INDEX(Mapping!$C$2:$C$549,MATCH($A17,Mapping!$A$2:$A$549,0)),"") | L17: =IF($K17="",0,COUNTIFS('JLR Materials'!$A$2:$A$20001,$K17,'JLR Materials'!$C$2:$C$20001,IF(Settings!$B$2="","<>",Settings!$B$2),'JLR Materials'!$D$2:$D$20001,IF(Settings!$B$4="","<>",Settings!$B$4))) -> 0 | M17: =IF($L17<>1,0,SUMIFS('JLR Materials'!$E$2:$E$20001,'JLR Materials'!$A$2:$A$20001,$K17,'JLR Materials'!$C$2:$C$20001,IF(Settings!$B$2="","<>",Settings!$B$2),'JLR Materials'!$D$2:$D$20001,IF(Settings!$B$4="","<>",Settings!$B$4))) -> 0 | N17: =IF($L17<>1,0,SUMIFS('JLR Materials'!$F$2:$F$20001,'JLR Materials'!$A$2:$A$20001,$K17,'JLR Materials'!$C$2:$C$20001,IF(Settings!$B$2="","<>",Settings!$B$2),'JLR Materials'!$D$2:$D$20001,IF(Settings!$B$4="","<>",Settings!$B$4))) -> 0 | O17: =IF($N17=0,0,IF(Settings!$B$5="percent",$M17*$N17/100,$N17)) -> 0 | P17: =IF($L17<>1,0,SUMIFS('JLR Materials'!$G$2:$G$20001,'JLR Materials'!$A$2:$A$20001,$K17,'JLR Materials'!$C$2:$C$20001,IF(Settings!$B$2="","<>",Settings!$B$2),'JLR Materials'!$D$2:$D$20001,IF(Settings!$B$4="","<>",Settings!$B$4))) -> 0 | Q17: Index-anchored 2026-07. Virgin PTFE rod/sheet — seals, insulators, chemical/low-friction parts. | Refresh 2026-09: SPECIALTY — no public market index for this grade; held at the June 2026 price — refresh by supplier quote | R17: 2026-09
A18: mat-peek-stock | B18: PEEK (Unfilled Stock) | C18: Engineering Plastic (Stock) | D18: =IF($M18>0,$M18,95) -> 95 | E18: =IF($O18>0,$O18,0.5) -> 0.5 | F18: 1300 | G18: UK | H18: =IF($M18>0,IF($L18<>1,$R18,IFERROR(INDEX('JLR Materials'!$D$2:$D$20001,MATCH($K18,'JLR Materials'!$A$2:$A$20001,0)),$R18)),$R18) -> 2026-09 | I18: =IF($M18>0,"JLR rate card — material code "&$K18,$Q18) -> Index-anchored 2026-07. Unfilled PEEK rod/plate — high-temp/chemical machined parts, medical, aerospace. | Refresh 2026-09: SPECIALTY — no public market index for this grade; held at the June 2026 price — refresh by supplier quote | J18: Low | K18: =IFERROR(INDEX(Mapping!$C$2:$C$549,MATCH($A18,Mapping!$A$2:$A$549,0)),"") | L18: =IF($K18="",0,COUNTIFS('JLR Materials'!$A$2:$A$20001,$K18,'JLR Materials'!$C$2:$C$20001,IF(Settings!$B$2="","<>",Settings!$B$2),'JLR Materials'!$D$2:$D$20001,IF(Settings!$B$4="","<>",Settings!$B$4))) -> 0 | M18: =IF($L18<>1,0,SUMIFS('JLR Materials'!$E$2:$E$20001,'JLR Materials'!$A$2:$A$20001,$K18,'JLR Materials'!$C$2:$C$20001,IF(Settings!$B$2="","<>",Settings!$B$2),'JLR Materials'!$D$2:$D$20001,IF(Settings!$B$4="","<>",Settings!$B$4))) -> 0 | N18: =IF($L18<>1,0,SUMIFS('JLR Materials'!$F$2:$F$20001,'JLR Materials'!$A$2:$A$20001,$K18,'JLR Materials'!$C$2:$C$20001,IF(Settings!$B$2="","<>",Settings!$B$2),'JLR Materials'!$D$2:$D$20001,IF(Settings!$B$4="","<>",Settings!$B$4))) -> 0 | O18: =IF($N18=0,0,IF(Settings!$B$5="percent",$M18*$N18/100,$N18)) -> 0 | P18: =IF($L18<>1,0,SUMIFS('JLR Materials'!$G$2:$G$20001,'JLR Materials'!$A$2:$A$20001,$K18,'JLR Materials'!$C$2:$C$20001,IF(Settings!$B$2="","<>",Settings!$B$2),'JLR Materials'!$D$2:$D$20001,IF(Settings!$B$4="","<>",Settings!$B$4))) -> 0 | Q18: Index-anchored 2026-07. Unfilled PEEK rod/plate — high-temp/chemical machined parts, medical, aerospace. | Refresh 2026-09: SPECIALTY — no public market index for this grade; held at the June 2026 price — refresh by supplier quote | R18: 2026-09
A19: mat-acrylic-cast | B19: Cast Acrylic (PMMA Stock) | C19: Engineering Plastic (Stock) | D19: =IF($M19>0,$M19,4.8) -> 4.8 | E19: =IF($O19>0,$O19,0.05) -> 0.05 | F19: 1190 | G19: UK | H19: =IF($M19>0,IF($L19<>1,$R19,IFERROR(INDEX('JLR Materials'!$D$2:$D$20001,MATCH($K19,'JLR Materials'!$A$2:$A$20001,0)),$R19)),$R19) -> 2026-09 | I19: =IF($M19>0,"JLR rate card — material code "&$K19,$Q19) -> Index-anchored 2026-07. Cast acrylic sheet/rod — optical, signage, machined transparent parts. | Refresh 2026-09: NOT SOURCED — pmma: Not sourced this period: engineering resin prices are paywalled (PIE/ICIS). Direction only: PC rising through Aug 2026, PA6 rebounding, PA66 under pressure, PET declining — no like-for-like June→Sep figures. Held at the June 2026 price. | J19: Low | K19: =IFERROR(INDEX(Mapping!$C$2:$C$549,MATCH($A19,Mapping!$A$2:$A$549,0)),"") | L19: =IF($K19="",0,COUNTIFS('JLR Materials'!$A$2:$A$20001,$K19,'JLR Materials'!$C$2:$C$20001,IF(Settings!$B$2="","<>",Settings!$B$2),'JLR Materials'!$D$2:$D$20001,IF(Settings!$B$4="","<>",Settings!$B$4))) -> 0 | M19: =IF($L19<>1,0,SUMIFS('JLR Materials'!$E$2:$E$20001,'JLR Materials'!$A$2:$A$20001,$K19,'JLR Materials'!$C$2:$C$20001,IF(Settings!$B$2="","<>",Settings!$B$2),'JLR Materials'!$D$2:$D$20001,IF(Settings!$B$4="","<>",Settings!$B$4))) -> 0 | N19: =IF($L19<>1,0,SUMIFS('JLR Materials'!$F$2:$F$20001,'JLR Materials'!$A$2:$A$20001,$K19,'JLR Materials'!$C$2:$C$20001,IF(Settings!$B$2="","<>",Settings!$B$2),'JLR Materials'!$D$2:$D$20001,IF(Settings!$B$4="","<>",Settings!$B$4))) -> 0 | O19: =IF($N19=0,0,IF(Settings!$B$5="percent",$M19*$N19/100,$N19)) -> 0 | P19: =IF($L19<>1,0,SUMIFS('JLR Materials'!$G$2:$G$20001,'JLR Materials'!$A$2:$A$20001,$K19,'JLR Materials'!$C$2:$C$20001,IF(Settings!$B$2="","<>",Settings!$B$2),'JLR Materials'!$D$2:$D$20001,IF(Settings!$B$4="","<>",Settings!$B$4))) -> 0 | Q19: Index-anchored 2026-07. Cast acrylic sheet/rod — optical, signage, machined transparent parts. | Refresh 2026-09: NOT SOURCED — pmma: Not sourced this period: engineering resin prices are paywalled (PIE/ICIS). Direction only: PC rising through Aug 2026, PA6 rebounding, PA66 under pressure, PET declining — no like-for-like June→Sep figures. Held at the June 2026 price. | R19: 2026-09
A20: mat-uhmwpe | B20: UHMW-PE (Stock) | C20: Engineering Plastic (Stock) | D20: =IF($M20>0,$M20,3.4) -> 3.4 | E20: =IF($O20>0,$O20,0.08) -> 0.08 | F20: 940 | G20: UK | H20: =IF($M20>0,IF($L20<>1,$R20,IFERROR(INDEX('JLR Materials'!$D$2:$D$20001,MATCH($K20,'JLR Materials'!$A$2:$A$20001,0)),$R20)),$R20) -> 2026-09 | I20: =IF($M20>0,"JLR rate card — material code "&$K20,$Q20) -> Index-anchored 2026-07. Ultra-high-molecular-weight PE sheet — wear strips, chute liners, guides. | Refresh 2026-09: SPECIALTY — no public market index for this grade; held at the June 2026 price — refresh by supplier quote | J20: Low | K20: =IFERROR(INDEX(Mapping!$C$2:$C$549,MATCH($A20,Mapping!$A$2:$A$549,0)),"") | L20: =IF($K20="",0,COUNTIFS('JLR Materials'!$A$2:$A$20001,$K20,'JLR Materials'!$C$2:$C$20001,IF(Settings!$B$2="","<>",Settings!$B$2),'JLR Materials'!$D$2:$D$20001,IF(Settings!$B$4="","<>",Settings!$B$4))) -> 0 | M20: =IF($L20<>1,0,SUMIFS('JLR Materials'!$E$2:$E$20001,'JLR Materials'!$A$2:$A$20001,$K20,'JLR Materials'!$C$2:$C$20001,IF(Settings!$B$2="","<>",Settings!$B$2),'JLR Materials'!$D$2:$D$20001,IF(Settings!$B$4="","<>",Settings!$B$4))) -> 0 | N20: =IF($L20<>1,0,SUMIFS('JLR Materials'!$F$2:$F$20001,'JLR Materials'!$A$2:$A$20001,$K20,'JLR Materials'!$C$2:$C$20001,IF(Settings!$B$2="","<>",Settings!$B$2),'JLR Materials'!$D$2:$D$20001,IF(Settings!$B$4="","<>",Settings!$B$4))) -> 0 | O20: =IF($N20=0,0,IF(Settings!$B$5="percent",$M20*$N20/100,$N20)) -> 0 | P20: =IF($L20<>1,0,SUMIFS('JLR Materials'!$G$2:$G$20001,'JLR Materials'!$A$2:$A$20001,$K20,'JLR Materials'!$C$2:$C$20001,IF(Settings!$B$2="","<>",Settings!$B$2),'JLR Materials'!$D$2:$D$20001,IF(Settings!$B$4="","<>",Settings!$B$4))) -> 0 | Q20: Index-anchored 2026-07. Ultra-high-molecular-weight PE sheet — wear strips, chute liners, guides. | Refresh 2026-09: SPECIALTY — no public market index for this grade; held at the June 2026 price — refresh by supplier quote | R20: 2026-09
A21: mat-dc01 | B21: DC01 | C21: Mild Steel Sheet | D21: =IF($M21>0,$M21,0.91) -> 0.91 | E21: =IF($O21>0,$O21,0.21) -> 0.21 | F21: 7850 | G21: UK | H21: =IF($M21>0,IF($L21<>1,$R21,IFERROR(INDEX('JLR Materials'!$D$2:$D$20001,MATCH($K21,'JLR Materials'!$A$2:$A$20001,0)),$R21)),$R21) -> 2026-09 | I21: =IF($M21>0,"JLR rate card — material code "&$K21,$Q21) -> UK CR mild sheet, delivered small-lot. Index-anchored: CRC €781/t → £0.67/kg mill + £0.19/kg stockholder premium. Basis: Fastmarkets EU HRC €691/t May-26 +€90 CRC, FX 0.855. Yield ~140 MPa. | Refresh 2026-09: +£0.049/kg from 1kg crc £0.668→£0.717/kg; premiums held | J21: Medium | K21: =IFERROR(INDEX(Mapping!$C$2:$C$549,MATCH($A21,Mapping!$A$2:$A$549,0)),"") | L21: =IF($K21="",0,COUNTIFS('JLR Materials'!$A$2:$A$20001,$K21,'JLR Materials'!$C$2:$C$20001,IF(Settings!$B$2="","<>",Settings!$B$2),'JLR Materials'!$D$2:$D$20001,IF(Settings!$B$4="","<>",Settings!$B$4))) -> 0 | M21: =IF($L21<>1,0,SUMIFS('JLR Materials'!$E$2:$E$20001,'JLR Materials'!$A$2:$A$20001,$K21,'JLR Materials'!$C$2:$C$20001,IF(Settings!$B$2="","<>",Settings!$B$2),'JLR Materials'!$D$2:$D$20001,IF(Settings!$B$4="","<>",Settings!$B$4))) -> 0 | N21: =IF($L21<>1,0,SUMIFS('JLR Materials'!$F$2:$F$20001,'JLR Materials'!$A$2:$A$20001,$K21,'JLR Materials'!$C$2:$C$20001,IF(Settings!$B$2="","<>",Settings!$B$2),'JLR Materials'!$D$2:$D$20001,IF(Settings!$B$4="","<>",Settings!$B$4))) -> 0 | O21: =IF($N21=0,0,IF(Settings!$B$5="percent",$M21*$N21/100,$N21)) -> 0 | P21: =IF($L21<>1,0,SUMIFS('JLR Materials'!$G$2:$G$20001,'JLR Materials'!$A$2:$A$20001,$K21,'JLR Materials'!$C$2:$C$20001,IF(Settings!$B$2="","<>",Settings!$B$2),'JLR Materials'!$D$2:$D$20001,IF(Settings!$B$4="","<>",Settings!$B$4))) -> 0 | Q21: UK CR mild sheet, delivered small-lot. Index-anchored: CRC €781/t → £0.67/kg mill + £0.19/kg stockholder premium. Basis: Fastmarkets EU HRC €691/t May-26 +€90 CRC, FX 0.855. Yield ~140 MPa. | Refresh 2026-09: +£0.049/kg from 1kg crc £0.668→£0.717/kg; premiums held | R21: 2026-09
A22: mat-dc01-gi | B22: DC01 GI (Hot-dip Galvanised) | C22: Galvanised Steel Sheet | D22: =IF($M22>0,$M22,1.11) -> 1.11 | E22: =IF($O22>0,$O22,0.21) -> 0.21 | F22: 7850 | G22: UK | H22: =IF($M22>0,IF($L22<>1,$R22,IFERROR(INDEX('JLR Materials'!$D$2:$D$20001,MATCH($K22,'JLR Materials'!$A$2:$A$20001,0)),$R22)),$R22) -> 2026-09 | I22: =IF($M22>0,"JLR rate card — material code "&$K22,$Q22) -> UK galv coil, BIW bodywork standard. Jun 2026 Index-anchored 2026-07 (see PRICING BASIS). | Refresh 2026-09: +£0.049/kg from 1kg hdg £0.668→£0.717/kg; premiums held | J22: Medium | K22: =IFERROR(INDEX(Mapping!$C$2:$C$549,MATCH($A22,Mapping!$A$2:$A$549,0)),"") | L22: =IF($K22="",0,COUNTIFS('JLR Materials'!$A$2:$A$20001,$K22,'JLR Materials'!$C$2:$C$20001,IF(Settings!$B$2="","<>",Settings!$B$2),'JLR Materials'!$D$2:$D$20001,IF(Settings!$B$4="","<>",Settings!$B$4))) -> 0 | M22: =IF($L22<>1,0,SUMIFS('JLR Materials'!$E$2:$E$20001,'JLR Materials'!$A$2:$A$20001,$K22,'JLR Materials'!$C$2:$C$20001,IF(Settings!$B$2="","<>",Settings!$B$2),'JLR Materials'!$D$2:$D$20001,IF(Settings!$B$4="","<>",Settings!$B$4))) -> 0 | N22: =IF($L22<>1,0,SUMIFS('JLR Materials'!$F$2:$F$20001,'JLR Materials'!$A$2:$A$20001,$K22,'JLR Materials'!$C$2:$C$20001,IF(Settings!$B$2="","<>",Settings!$B$2),'JLR Materials'!$D$2:$D$20001,IF(Settings!$B$4="","<>",Settings!$B$4))) -> 0 | O22: =IF($N22=0,0,IF(Settings!$B$5="percent",$M22*$N22/100,$N22)) -> 0 | P22: =IF($L22<>1,0,SUMIFS('JLR Materials'!$G$2:$G$20001,'JLR Materials'!$A$2:$A$20001,$K22,'JLR Materials'!$C$2:$C$20001,IF(Settings!$B$2="","<>",Settings!$B$2),'JLR Materials'!$D$2:$D$20001,IF(Settings!$B$4="","<>",Settings!$B$4))) -> 0 | Q22: UK galv coil, BIW bodywork standard. Jun 2026 Index-anchored 2026-07 (see PRICING BASIS). | Refresh 2026-09: +£0.049/kg from 1kg hdg £0.668→£0.717/kg; premiums held | R22: 2026-09
A23: mat-dc03-ga | B23: DC03 GA (Galvannealed) | C23: Galvanised Steel Sheet | D23: =IF($M23>0,$M23,1.15) -> 1.15 | E23: =IF($O23>0,$O23,0.21) -> 0.21 | F23: 7850 | G23: UK | H23: =IF($M23>0,IF($L23<>1,$R23,IFERROR(INDEX('JLR Materials'!$D$2:$D$20001,MATCH($K23,'JLR Materials'!$A$2:$A$20001,0)),$R23)),$R23) -> 2026-09 | I23: =IF($M23>0,"JLR rate card — material code "&$K23,$Q23) -> UK galvannealed coil, standard BIW inner panels. Jun 2026 Index-anchored 2026-07 (see PRICING BASIS). | Refresh 2026-09: +£0.049/kg from 1kg hdg £0.668→£0.717/kg; premiums held | J23: Medium | K23: =IFERROR(INDEX(Mapping!$C$2:$C$549,MATCH($A23,Mapping!$A$2:$A$549,0)),"") | L23: =IF($K23="",0,COUNTIFS('JLR Materials'!$A$2:$A$20001,$K23,'JLR Materials'!$C$2:$C$20001,IF(Settings!$B$2="","<>",Settings!$B$2),'JLR Materials'!$D$2:$D$20001,IF(Settings!$B$4="","<>",Settings!$B$4))) -> 0 | M23: =IF($L23<>1,0,SUMIFS('JLR Materials'!$E$2:$E$20001,'JLR Materials'!$A$2:$A$20001,$K23,'JLR Materials'!$C$2:$C$20001,IF(Settings!$B$2="","<>",Settings!$B$2),'JLR Materials'!$D$2:$D$20001,IF(Settings!$B$4="","<>",Settings!$B$4))) -> 0 | N23: =IF($L23<>1,0,SUMIFS('JLR Materials'!$F$2:$F$20001,'JLR Materials'!$A$2:$A$20001,$K23,'JLR Materials'!$C$2:$C$20001,IF(Settings!$B$2="","<>",Settings!$B$2),'JLR Materials'!$D$2:$D$20001,IF(Settings!$B$4="","<>",Settings!$B$4))) -> 0 | O23: =IF($N23=0,0,IF(Settings!$B$5="percent",$M23*$N23/100,$N23)) -> 0 | P23: =IF($L23<>1,0,SUMIFS('JLR Materials'!$G$2:$G$20001,'JLR Materials'!$A$2:$A$20001,$K23,'JLR Materials'!$C$2:$C$20001,IF(Settings!$B$2="","<>",Settings!$B$2),'JLR Materials'!$D$2:$D$20001,IF(Settings!$B$4="","<>",Settings!$B$4))) -> 0 | Q23: UK galvannealed coil, standard BIW inner panels. Jun 2026 Index-anchored 2026-07 (see PRICING BASIS). | Refresh 2026-09: +£0.049/kg from 1kg hdg £0.668→£0.717/kg; premiums held | R23: 2026-09
A24: mat-dp600 | B24: DP600 | C24: AHSS Sheet | D24: =IF($M24>0,$M24,1.3) -> 1.3 | E24: =IF($O24>0,$O24,0.23) -> 0.23 | F24: 7850 | G24: UK | H24: =IF($M24>0,IF($L24<>1,$R24,IFERROR(INDEX('JLR Materials'!$D$2:$D$20001,MATCH($K24,'JLR Materials'!$A$2:$A$20001,0)),$R24)),$R24) -> 2026-09 | I24: =IF($M24>0,"JLR rate card — material code "&$K24,$Q24) -> UK AHSS coil, Jun 2026 Index-anchored 2026-07 (see PRICING BASIS). | Refresh 2026-09: +£0.049/kg from 1kg crc £0.668→£0.717/kg; premiums held | J24: Medium | K24: =IFERROR(INDEX(Mapping!$C$2:$C$549,MATCH($A24,Mapping!$A$2:$A$549,0)),"") | L24: =IF($K24="",0,COUNTIFS('JLR Materials'!$A$2:$A$20001,$K24,'JLR Materials'!$C$2:$C$20001,IF(Settings!$B$2="","<>",Settings!$B$2),'JLR Materials'!$D$2:$D$20001,IF(Settings!$B$4="","<>",Settings!$B$4))) -> 0 | M24: =IF($L24<>1,0,SUMIFS('JLR Materials'!$E$2:$E$20001,'JLR Materials'!$A$2:$A$20001,$K24,'JLR Materials'!$C$2:$C$20001,IF(Settings!$B$2="","<>",Settings!$B$2),'JLR Materials'!$D$2:$D$20001,IF(Settings!$B$4="","<>",Settings!$B$4))) -> 0 | N24: =IF($L24<>1,0,SUMIFS('JLR Materials'!$F$2:$F$20001,'JLR Materials'!$A$2:$A$20001,$K24,'JLR Materials'!$C$2:$C$20001,IF(Settings!$B$2="","<>",Settings!$B$2),'JLR Materials'!$D$2:$D$20001,IF(Settings!$B$4="","<>",Settings!$B$4))) -> 0 | O24: =IF($N24=0,0,IF(Settings!$B$5="percent",$M24*$N24/100,$N24)) -> 0 | P24: =IF($L24<>1,0,SUMIFS('JLR Materials'!$G$2:$G$20001,'JLR Materials'!$A$2:$A$20001,$K24,'JLR Materials'!$C$2:$C$20001,IF(Settings!$B$2="","<>",Settings!$B$2),'JLR Materials'!$D$2:$D$20001,IF(Settings!$B$4="","<>",Settings!$B$4))) -> 0 | Q24: UK AHSS coil, Jun 2026 Index-anchored 2026-07 (see PRICING BASIS). | Refresh 2026-09: +£0.049/kg from 1kg crc £0.668→£0.717/kg; premiums held | R24: 2026-09
A25: mat-hsla340 | B25: HSLA 340 | C25: High Strength Steel Sheet | D25: =IF($M25>0,$M25,1.19) -> 1.19 | E25: =IF($O25>0,$O25,0.22) -> 0.22 | F25: 7850 | G25: UK | H25: =IF($M25>0,IF($L25<>1,$R25,IFERROR(INDEX('JLR Materials'!$D$2:$D$20001,MATCH($K25,'JLR Materials'!$A$2:$A$20001,0)),$R25)),$R25) -> 2026-09 | I25: =IF($M25>0,"JLR rate card — material code "&$K25,$Q25) -> UK HSLA coil, Jun 2026 Index-anchored 2026-07 (see PRICING BASIS). | Refresh 2026-09: +£0.049/kg from 1kg crc £0.668→£0.717/kg; premiums held | J25: Medium | K25: =IFERROR(INDEX(Mapping!$C$2:$C$549,MATCH($A25,Mapping!$A$2:$A$549,0)),"") | L25: =IF($K25="",0,COUNTIFS('JLR Materials'!$A$2:$A$20001,$K25,'JLR Materials'!$C$2:$C$20001,IF(Settings!$B$2="","<>",Settings!$B$2),'JLR Materials'!$D$2:$D$20001,IF(Settings!$B$4="","<>",Settings!$B$4))) -> 0 | M25: =IF($L25<>1,0,SUMIFS('JLR Materials'!$E$2:$E$20001,'JLR Materials'!$A$2:$A$20001,$K25,'JLR Materials'!$C$2:$C$20001,IF(Settings!$B$2="","<>",Settings!$B$2),'JLR Materials'!$D$2:$D$20001,IF(Settings!$B$4="","<>",Settings!$B$4))) -> 0 | N25: =IF($L25<>1,0,SUMIFS('JLR Materials'!$F$2:$F$20001,'JLR Materials'!$A$2:$A$20001,$K25,'JLR Materials'!$C$2:$C$20001,IF(Settings!$B$2="","<>",Settings!$B$2),'JLR Materials'!$D$2:$D$20001,IF(Settings!$B$4="","<>",Settings!$B$4))) -> 0 | O25: =IF($N25=0,0,IF(Settings!$B$5="percent",$M25*$N25/100,$N25)) -> 0 | P25: =IF($L25<>1,0,SUMIFS('JLR Materials'!$G$2:$G$20001,'JLR Materials'!$A$2:$A$20001,$K25,'JLR Materials'!$C$2:$C$20001,IF(Settings!$B$2="","<>",Settings!$B$2),'JLR Materials'!$D$2:$D$20001,IF(Settings!$B$4="","<>",Settings!$B$4))) -> 0 | Q25: UK HSLA coil, Jun 2026 Index-anchored 2026-07 (see PRICING BASIS). | Refresh 2026-09: +£0.049/kg from 1kg crc £0.668→£0.717/kg; premiums held | R25: 2026-09
A26: mat-22mnb5 | B26: 22MnB5 (Hot Press Forming / Boron Steel) | C26: Ultra-High Strength Steel | D26: =IF($M26>0,$M26,1.79) -> 1.79 | E26: =IF($O26>0,$O26,0.23) -> 0.23 | F26: 7850 | G26: UK | H26: =IF($M26>0,IF($L26<>1,$R26,IFERROR(INDEX('JLR Materials'!$D$2:$D$20001,MATCH($K26,'JLR Materials'!$A$2:$A$20001,0)),$R26)),$R26) -> 2026-09 | I26: =IF($M26>0,"JLR rate card — material code "&$K26,$Q26) -> UK PHS coil for hot stamping (A/B-pillar, roof rail). Jun 2026 Index-anchored 2026-07 (see PRICING BASIS). | Refresh 2026-09: +£0.049/kg from 1kg crc £0.668→£0.717/kg; premiums held | J26: Low | K26: =IFERROR(INDEX(Mapping!$C$2:$C$549,MATCH($A26,Mapping!$A$2:$A$549,0)),"") | L26: =IF($K26="",0,COUNTIFS('JLR Materials'!$A$2:$A$20001,$K26,'JLR Materials'!$C$2:$C$20001,IF(Settings!$B$2="","<>",Settings!$B$2),'JLR Materials'!$D$2:$D$20001,IF(Settings!$B$4="","<>",Settings!$B$4))) -> 0 | M26: =IF($L26<>1,0,SUMIFS('JLR Materials'!$E$2:$E$20001,'JLR Materials'!$A$2:$A$20001,$K26,'JLR Materials'!$C$2:$C$20001,IF(Settings!$B$2="","<>",Settings!$B$2),'JLR Materials'!$D$2:$D$20001,IF(Settings!$B$4="","<>",Settings!$B$4))) -> 0 | N26: =IF($L26<>1,0,SUMIFS('JLR Materials'!$F$2:$F$20001,'JLR Materials'!$A$2:$A$20001,$K26,'JLR Materials'!$C$2:$C$20001,IF(Settings!$B$2="","<>",Settings!$B$2),'JLR Materials'!$D$2:$D$20001,IF(Settings!$B$4="","<>",Settings!$B$4))) -> 0 | O26: =IF($N26=0,0,IF(Settings!$B$5="percent",$M26*$N26/100,$N26)) -> 0 | P26: =IF($L26<>1,0,SUMIFS('JLR Materials'!$G$2:$G$20001,'JLR Materials'!$A$2:$A$20001,$K26,'JLR Materials'!$C$2:$C$20001,IF(Settings!$B$2="","<>",Settings!$B$2),'JLR Materials'!$D$2:$D$20001,IF(Settings!$B$4="","<>",Settings!$B$4))) -> 0 | Q26: UK PHS coil for hot stamping (A/B-pillar, roof rail). Jun 2026 Index-anchored 2026-07 (see PRICING BASIS). | Refresh 2026-09: +£0.049/kg from 1kg crc £0.668→£0.717/kg; premiums held | R26: 2026-09
A27: mat-aa5182 | B27: AA5182 | C27: Aluminium Sheet | D27: =IF($M27>0,$M27,3.19) -> 3.19 | E27: =IF($O27>0,$O27,0.49) -> 0.49 | F27: 2700 | G27: UK | H27: =IF($M27>0,IF($L27<>1,$R27,IFERROR(INDEX('JLR Materials'!$D$2:$D$20001,MATCH($K27,'JLR Materials'!$A$2:$A$20001,0)),$R27)),$R27) -> 2026-09 | I27: =IF($M27>0,"JLR rate card — material code "&$K27,$Q27) -> UK Al sheet, Jun 2026 Index-anchored 2026-07 (see PRICING BASIS). | Refresh 2026-09: −£0.060/kg from 0.97kg al £2.910→£2.849/kg; premiums held | J27: Medium | K27: =IFERROR(INDEX(Mapping!$C$2:$C$549,MATCH($A27,Mapping!$A$2:$A$549,0)),"") | L27: =IF($K27="",0,COUNTIFS('JLR Materials'!$A$2:$A$20001,$K27,'JLR Materials'!$C$2:$C$20001,IF(Settings!$B$2="","<>",Settings!$B$2),'JLR Materials'!$D$2:$D$20001,IF(Settings!$B$4="","<>",Settings!$B$4))) -> 0 | M27: =IF($L27<>1,0,SUMIFS('JLR Materials'!$E$2:$E$20001,'JLR Materials'!$A$2:$A$20001,$K27,'JLR Materials'!$C$2:$C$20001,IF(Settings!$B$2="","<>",Settings!$B$2),'JLR Materials'!$D$2:$D$20001,IF(Settings!$B$4="","<>",Settings!$B$4))) -> 0 | N27: =IF($L27<>1,0,SUMIFS('JLR Materials'!$F$2:$F$20001,'JLR Materials'!$A$2:$A$20001,$K27,'JLR Materials'!$C$2:$C$20001,IF(Settings!$B$2="","<>",Settings!$B$2),'JLR Materials'!$D$2:$D$20001,IF(Settings!$B$4="","<>",Settings!$B$4))) -> 0 | O27: =IF($N27=0,0,IF(Settings!$B$5="percent",$M27*$N27/100,$N27)) -> 0 | P27: =IF($L27<>1,0,SUMIFS('JLR Materials'!$G$2:$G$20001,'JLR Materials'!$A$2:$A$20001,$K27,'JLR Materials'!$C$2:$C$20001,IF(Settings!$B$2="","<>",Settings!$B$2),'JLR Materials'!$D$2:$D$20001,IF(Settings!$B$4="","<>",Settings!$B$4))) -> 0 | Q27: UK Al sheet, Jun 2026 Index-anchored 2026-07 (see PRICING BASIS). | Refresh 2026-09: −£0.060/kg from 0.97kg al £2.910→£2.849/kg; premiums held | R27: 2026-09
A28: mat-ss304-sheet | B28: 304L Stainless Sheet | C28: Stainless Steel Sheet | D28: =IF($M28>0,$M28,3.49) -> 3.49 | E28: =IF($O28>0,$O28,0.83) -> 0.83 | F28: 7900 | G28: UK | H28: =IF($M28>0,IF($L28<>1,$R28,IFERROR(INDEX('JLR Materials'!$D$2:$D$20001,MATCH($K28,'JLR Materials'!$A$2:$A$20001,0)),$R28)),$R28) -> 2026-09 | I28: =IF($M28>0,"JLR rate card — material code "&$K28,$Q28) -> UK stainless coil, food/pharma stampings. Jun 2026 Index-anchored 2026-07 (see PRICING BASIS). | Refresh 2026-09: +£0.127/kg from 1kg ss_sur £2.037→£2.164/kg; premiums held | J28: Medium | K28: =IFERROR(INDEX(Mapping!$C$2:$C$549,MATCH($A28,Mapping!$A$2:$A$549,0)),"") | L28: =IF($K28="",0,COUNTIFS('JLR Materials'!$A$2:$A$20001,$K28,'JLR Materials'!$C$2:$C$20001,IF(Settings!$B$2="","<>",Settings!$B$2),'JLR Materials'!$D$2:$D$20001,IF(Settings!$B$4="","<>",Settings!$B$4))) -> 0 | M28: =IF($L28<>1,0,SUMIFS('JLR Materials'!$E$2:$E$20001,'JLR Materials'!$A$2:$A$20001,$K28,'JLR Materials'!$C$2:$C$20001,IF(Settings!$B$2="","<>",Settings!$B$2),'JLR Materials'!$D$2:$D$20001,IF(Settings!$B$4="","<>",Settings!$B$4))) -> 0 | N28: =IF($L28<>1,0,SUMIFS('JLR Materials'!$F$2:$F$20001,'JLR Materials'!$A$2:$A$20001,$K28,'JLR Materials'!$C$2:$C$20001,IF(Settings!$B$2="","<>",Settings!$B$2),'JLR Materials'!$D$2:$D$20001,IF(Settings!$B$4="","<>",Settings!$B$4))) -> 0 | O28: =IF($N28=0,0,IF(Settings!$B$5="percent",$M28*$N28/100,$N28)) -> 0 | P28: =IF($L28<>1,0,SUMIFS('JLR Materials'!$G$2:$G$20001,'JLR Materials'!$A$2:$A$20001,$K28,'JLR Materials'!$C$2:$C$20001,IF(Settings!$B$2="","<>",Settings!$B$2),'JLR Materials'!$D$2:$D$20001,IF(Settings!$B$4="","<>",Settings!$B$4))) -> 0 | Q28: UK stainless coil, food/pharma stampings. Jun 2026 Index-anchored 2026-07 (see PRICING BASIS). | Refresh 2026-09: +£0.127/kg from 1kg ss_sur £2.037→£2.164/kg; premiums held | R28: 2026-09
A29: mat-aa5052 | B29: AA5052-H32 Sheet | C29: Aluminium Sheet | D29: =IF($M29>0,$M29,3.19) -> 3.19 | E29: =IF($O29>0,$O29,0.49) -> 0.49 | F29: 2680 | G29: UK | H29: =IF($M29>0,IF($L29<>1,$R29,IFERROR(INDEX('JLR Materials'!$D$2:$D$20001,MATCH($K29,'JLR Materials'!$A$2:$A$20001,0)),$R29)),$R29) -> 2026-09 | I29: =IF($M29>0,"JLR rate card — material code "&$K29,$Q29) -> UK Al sheet stockholder Jun 2026. 5xxx series — marine/vehicle panels, excellent corrosion resistance. Yield 195 MPa. Index-anchored 2026-07 (see PRICING BASIS). | Refresh 2026-09: −£0.060/kg from 0.97kg al £2.910→£2.849/kg; premiums held | J29: Medium | K29: =IFERROR(INDEX(Mapping!$C$2:$C$549,MATCH($A29,Mapping!$A$2:$A$549,0)),"") | L29: =IF($K29="",0,COUNTIFS('JLR Materials'!$A$2:$A$20001,$K29,'JLR Materials'!$C$2:$C$20001,IF(Settings!$B$2="","<>",Settings!$B$2),'JLR Materials'!$D$2:$D$20001,IF(Settings!$B$4="","<>",Settings!$B$4))) -> 0 | M29: =IF($L29<>1,0,SUMIFS('JLR Materials'!$E$2:$E$20001,'JLR Materials'!$A$2:$A$20001,$K29,'JLR Materials'!$C$2:$C$20001,IF(Settings!$B$2="","<>",Settings!$B$2),'JLR Materials'!$D$2:$D$20001,IF(Settings!$B$4="","<>",Settings!$B$4))) -> 0 | N29: =IF($L29<>1,0,SUMIFS('JLR Materials'!$F$2:$F$20001,'JLR Materials'!$A$2:$A$20001,$K29,'JLR Materials'!$C$2:$C$20001,IF(Settings!$B$2="","<>",Settings!$B$2),'JLR Materials'!$D$2:$D$20001,IF(Settings!$B$4="","<>",Settings!$B$4))) -> 0 | O29: =IF($N29=0,0,IF(Settings!$B$5="percent",$M29*$N29/100,$N29)) -> 0 | P29: =IF($L29<>1,0,SUMIFS('JLR Materials'!$G$2:$G$20001,'JLR Materials'!$A$2:$A$20001,$K29,'JLR Materials'!$C$2:$C$20001,IF(Settings!$B$2="","<>",Settings!$B$2),'JLR Materials'!$D$2:$D$20001,IF(Settings!$B$4="","<>",Settings!$B$4))) -> 0 | Q29: UK Al sheet stockholder Jun 2026. 5xxx series — marine/vehicle panels, excellent corrosion resistance. Yield 195 MPa. Index-anchored 2026-07 (see PRICING BASIS). | Refresh 2026-09: −£0.060/kg from 0.97kg al £2.910→£2.849/kg; premiums held | R29: 2026-09
A30: mat-aa5083 | B30: AA5083-H111 Sheet | C30: Aluminium Sheet | D30: =IF($M30>0,$M30,3.4) -> 3.4 | E30: =IF($O30>0,$O30,0.49) -> 0.49 | F30: 2660 | G30: UK | H30: =IF($M30>0,IF($L30<>1,$R30,IFERROR(INDEX('JLR Materials'!$D$2:$D$20001,MATCH($K30,'JLR Materials'!$A$2:$A$20001,0)),$R30)),$R30) -> 2026-09 | I30: =IF($M30>0,"JLR rate card — material code "&$K30,$Q30) -> UK Al sheet stockholder Jun 2026. 5xxx series — marine structures, shipbuilding. Higher strength than 5052. Yield 228 MPa. Index-anchored 2026-07 (see PRICING BASIS). | Refresh 2026-09: −£0.060/kg from 0.97kg al £2.910→£2.849/kg; premiums held | J30: Medium | K30: =IFERROR(INDEX(Mapping!$C$2:$C$549,MATCH($A30,Mapping!$A$2:$A$549,0)),"") | L30: =IF($K30="",0,COUNTIFS('JLR Materials'!$A$2:$A$20001,$K30,'JLR Materials'!$C$2:$C$20001,IF(Settings!$B$2="","<>",Settings!$B$2),'JLR Materials'!$D$2:$D$20001,IF(Settings!$B$4="","<>",Settings!$B$4))) -> 0 | M30: =IF($L30<>1,0,SUMIFS('JLR Materials'!$E$2:$E$20001,'JLR Materials'!$A$2:$A$20001,$K30,'JLR Materials'!$C$2:$C$20001,IF(Settings!$B$2="","<>",Settings!$B$2),'JLR Materials'!$D$2:$D$20001,IF(Settings!$B$4="","<>",Settings!$B$4))) -> 0 | N30: =IF($L30<>1,0,SUMIFS('JLR Materials'!$F$2:$F$20001,'JLR Materials'!$A$2:$A$20001,$K30,'JLR Materials'!$C$2:$C$20001,IF(Settings!$B$2="","<>",Settings!$B$2),'JLR Materials'!$D$2:$D$20001,IF(Settings!$B$4="","<>",Settings!$B$4))) -> 0 | O30: =IF($N30=0,0,IF(Settings!$B$5="percent",$M30*$N30/100,$N30)) -> 0 | P30: =IF($L30<>1,0,SUMIFS('JLR Materials'!$G$2:$G$20001,'JLR Materials'!$A$2:$A$20001,$K30,'JLR Materials'!$C$2:$C$20001,IF(Settings!$B$2="","<>",Settings!$B$2),'JLR Materials'!$D$2:$D$20001,IF(Settings!$B$4="","<>",Settings!$B$4))) -> 0 | Q30: UK Al sheet stockholder Jun 2026. 5xxx series — marine structures, shipbuilding. Higher strength than 5052. Yield 228 MPa. Index-anchored 2026-07 (see PRICING BASIS). | Refresh 2026-09: −£0.060/kg from 0.97kg al £2.910→£2.849/kg; premiums held | R30: 2026-09
A31: mat-aa6082-sheet | B31: AA6082-T6 Sheet | C31: Aluminium Sheet | D31: =IF($M31>0,$M31,3.56) -> 3.56 | E31: =IF($O31>0,$O31,0.49) -> 0.49 | F31: 2700 | G31: UK | H31: =IF($M31>0,IF($L31<>1,$R31,IFERROR(INDEX('JLR Materials'!$D$2:$D$20001,MATCH($K31,'JLR Materials'!$A$2:$A$20001,0)),$R31)),$R31) -> 2026-09 | I31: =IF($M31>0,"JLR rate card — material code "&$K31,$Q31) -> UK Al sheet/plate stockholder Jun 2026. 6xxx series structural alloy — frames, structural parts. Yield 250 MPa. Index-anchored 2026-07 (see PRICING BASIS). | Refresh 2026-09: −£0.060/kg from 0.97kg al £2.910→£2.849/kg; premiums held | J31: Low | K31: =IFERROR(INDEX(Mapping!$C$2:$C$549,MATCH($A31,Mapping!$A$2:$A$549,0)),"") | L31: =IF($K31="",0,COUNTIFS('JLR Materials'!$A$2:$A$20001,$K31,'JLR Materials'!$C$2:$C$20001,IF(Settings!$B$2="","<>",Settings!$B$2),'JLR Materials'!$D$2:$D$20001,IF(Settings!$B$4="","<>",Settings!$B$4))) -> 0 | M31: =IF($L31<>1,0,SUMIFS('JLR Materials'!$E$2:$E$20001,'JLR Materials'!$A$2:$A$20001,$K31,'JLR Materials'!$C$2:$C$20001,IF(Settings!$B$2="","<>",Settings!$B$2),'JLR Materials'!$D$2:$D$20001,IF(Settings!$B$4="","<>",Settings!$B$4))) -> 0 | N31: =IF($L31<>1,0,SUMIFS('JLR Materials'!$F$2:$F$20001,'JLR Materials'!$A$2:$A$20001,$K31,'JLR Materials'!$C$2:$C$20001,IF(Settings!$B$2="","<>",Settings!$B$2),'JLR Materials'!$D$2:$D$20001,IF(Settings!$B$4="","<>",Settings!$B$4))) -> 0 | O31: =IF($N31=0,0,IF(Settings!$B$5="percent",$M31*$N31/100,$N31)) -> 0 | P31: =IF($L31<>1,0,SUMIFS('JLR Materials'!$G$2:$G$20001,'JLR Materials'!$A$2:$A$20001,$K31,'JLR Materials'!$C$2:$C$20001,IF(Settings!$B$2="","<>",Settings!$B$2),'JLR Materials'!$D$2:$D$20001,IF(Settings!$B$4="","<>",Settings!$B$4))) -> 0 | Q31: UK Al sheet/plate stockholder Jun 2026. 6xxx series structural alloy — frames, structural parts. Yield 250 MPa. Index-anchored 2026-07 (see PRICING BASIS). | Refresh 2026-09: −£0.060/kg from 0.97kg al £2.910→£2.849/kg; premiums held | R31: 2026-09
A32: mat-aisi430 | B32: AISI 430 Ferritic SS Sheet | C32: Stainless Steel Sheet | D32: =IF($M32>0,$M32,2.97) -> 2.97 | E32: =IF($O32>0,$O32,0.71) -> 0.71 | F32: 7700 | G32: UK | H32: =IF($M32>0,IF($L32<>1,$R32,IFERROR(INDEX('JLR Materials'!$D$2:$D$20001,MATCH($K32,'JLR Materials'!$A$2:$A$20001,0)),$R32)),$R32) -> 2026-09 | I32: =IF($M32>0,"JLR rate card — material code "&$K32,$Q32) -> UK SS stockholder Jun 2026. Ferritic (magnetic) stainless — appliance panels, automotive trim. Moderate corrosion resistance. Yield 250 MPa. Index-anchored 2026-07 (see PRICING BASIS). | Refresh 2026-09: +£0.034/kg from 0.7kg hrc £0.591→£0.639/kg; premiums held | J32: Low | K32: =IFERROR(INDEX(Mapping!$C$2:$C$549,MATCH($A32,Mapping!$A$2:$A$549,0)),"") | L32: =IF($K32="",0,COUNTIFS('JLR Materials'!$A$2:$A$20001,$K32,'JLR Materials'!$C$2:$C$20001,IF(Settings!$B$2="","<>",Settings!$B$2),'JLR Materials'!$D$2:$D$20001,IF(Settings!$B$4="","<>",Settings!$B$4))) -> 0 | M32: =IF($L32<>1,0,SUMIFS('JLR Materials'!$E$2:$E$20001,'JLR Materials'!$A$2:$A$20001,$K32,'JLR Materials'!$C$2:$C$20001,IF(Settings!$B$2="","<>",Settings!$B$2),'JLR Materials'!$D$2:$D$20001,IF(Settings!$B$4="","<>",Settings!$B$4))) -> 0 | N32: =IF($L32<>1,0,SUMIFS('JLR Materials'!$F$2:$F$20001,'JLR Materials'!$A$2:$A$20001,$K32,'JLR Materials'!$C$2:$C$20001,IF(Settings!$B$2="","<>",Settings!$B$2),'JLR Materials'!$D$2:$D$20001,IF(Settings!$B$4="","<>",Settings!$B$4))) -> 0 | O32: =IF($N32=0,0,IF(Settings!$B$5="percent",$M32*$N32/100,$N32)) -> 0 | P32: =IF($L32<>1,0,SUMIFS('JLR Materials'!$G$2:$G$20001,'JLR Materials'!$A$2:$A$20001,$K32,'JLR Materials'!$C$2:$C$20001,IF(Settings!$B$2="","<>",Settings!$B$2),'JLR Materials'!$D$2:$D$20001,IF(Settings!$B$4="","<>",Settings!$B$4))) -> 0 | Q32: UK SS stockholder Jun 2026. Ferritic (magnetic) stainless — appliance panels, automotive trim. Moderate corrosion resistance. Yield 250 MPa. Index-anchored 2026-07 (see PRICING BASIS). | Refresh 2026-09: +£0.034/kg from 0.7kg hrc £0.591→£0.639/kg; premiums held | R32: 2026-09
A33: mat-ss316-sheet | B33: AISI 316L Stainless Sheet | C33: Stainless Steel Sheet | D33: =IF($M33>0,$M33,4.54) -> 4.54 | E33: =IF($O33>0,$O33,0.93) -> 0.93 | F33: 7990 | G33: UK | H33: =IF($M33>0,IF($L33<>1,$R33,IFERROR(INDEX('JLR Materials'!$D$2:$D$20001,MATCH($K33,'JLR Materials'!$A$2:$A$20001,0)),$R33)),$R33) -> 2026-09 | I33: =IF($M33>0,"JLR rate card — material code "&$K33,$Q33) -> UK SS stockholder Jun 2026. 316L — food processing, medical, marine (Mo addition gives better chloride resistance than 304). Yield 170 MPa. Index-anchored 2026-07 (see PRICING BASIS). | Refresh 2026-09: +£0.129/kg from 1kg ss_sur £2.037→£2.164/kg, 0.03kg ni £12.302→£12.378/kg; premiums held | J33: Medium | K33: =IFERROR(INDEX(Mapping!$C$2:$C$549,MATCH($A33,Mapping!$A$2:$A$549,0)),"") | L33: =IF($K33="",0,COUNTIFS('JLR Materials'!$A$2:$A$20001,$K33,'JLR Materials'!$C$2:$C$20001,IF(Settings!$B$2="","<>",Settings!$B$2),'JLR Materials'!$D$2:$D$20001,IF(Settings!$B$4="","<>",Settings!$B$4))) -> 0 | M33: =IF($L33<>1,0,SUMIFS('JLR Materials'!$E$2:$E$20001,'JLR Materials'!$A$2:$A$20001,$K33,'JLR Materials'!$C$2:$C$20001,IF(Settings!$B$2="","<>",Settings!$B$2),'JLR Materials'!$D$2:$D$20001,IF(Settings!$B$4="","<>",Settings!$B$4))) -> 0 | N33: =IF($L33<>1,0,SUMIFS('JLR Materials'!$F$2:$F$20001,'JLR Materials'!$A$2:$A$20001,$K33,'JLR Materials'!$C$2:$C$20001,IF(Settings!$B$2="","<>",Settings!$B$2),'JLR Materials'!$D$2:$D$20001,IF(Settings!$B$4="","<>",Settings!$B$4))) -> 0 | O33: =IF($N33=0,0,IF(Settings!$B$5="percent",$M33*$N33/100,$N33)) -> 0 | P33: =IF($L33<>1,0,SUMIFS('JLR Materials'!$G$2:$G$20001,'JLR Materials'!$A$2:$A$20001,$K33,'JLR Materials'!$C$2:$C$20001,IF(Settings!$B$2="","<>",Settings!$B$2),'JLR Materials'!$D$2:$D$20001,IF(Settings!$B$4="","<>",Settings!$B$4))) -> 0 | Q33: UK SS stockholder Jun 2026. 316L — food processing, medical, marine (Mo addition gives better chloride resistance than 304). Yield 170 MPa. Index-anchored 2026-07 (see PRICING BASIS). | Refresh 2026-09: +£0.129/kg from 1kg ss_sur £2.037→£2.164/kg, 0.03kg ni £12.302→£12.378/kg; premiums held | R33: 2026-09
A34: mat-dc01-ze | B34: DC01+ZE (Electrogalvanised) | C34: Electrogalvanised Steel Sheet | D34: =IF($M34>0,$M34,0.98) -> 0.98 | E34: =IF($O34>0,$O34,0.21) -> 0.21 | F34: 7850 | G34: UK | H34: =IF($M34>0,IF($L34<>1,$R34,IFERROR(INDEX('JLR Materials'!$D$2:$D$20001,MATCH($K34,'JLR Materials'!$A$2:$A$20001,0)),$R34)),$R34) -> 2026-09 | I34: =IF($M34>0,"JLR rate card — material code "&$K34,$Q34) -> UK steel coil Jun 2026. Thin zinc coating — automotive body, appliance housings. Better paintability than hot-dip. Yield 140 MPa. Index-anchored 2026-07 (see PRICING BASIS). | Refresh 2026-09: +£0.049/kg from 1kg crc £0.668→£0.717/kg; premiums held | J34: Medium | K34: =IFERROR(INDEX(Mapping!$C$2:$C$549,MATCH($A34,Mapping!$A$2:$A$549,0)),"") | L34: =IF($K34="",0,COUNTIFS('JLR Materials'!$A$2:$A$20001,$K34,'JLR Materials'!$C$2:$C$20001,IF(Settings!$B$2="","<>",Settings!$B$2),'JLR Materials'!$D$2:$D$20001,IF(Settings!$B$4="","<>",Settings!$B$4))) -> 0 | M34: =IF($L34<>1,0,SUMIFS('JLR Materials'!$E$2:$E$20001,'JLR Materials'!$A$2:$A$20001,$K34,'JLR Materials'!$C$2:$C$20001,IF(Settings!$B$2="","<>",Settings!$B$2),'JLR Materials'!$D$2:$D$20001,IF(Settings!$B$4="","<>",Settings!$B$4))) -> 0 | N34: =IF($L34<>1,0,SUMIFS('JLR Materials'!$F$2:$F$20001,'JLR Materials'!$A$2:$A$20001,$K34,'JLR Materials'!$C$2:$C$20001,IF(Settings!$B$2="","<>",Settings!$B$2),'JLR Materials'!$D$2:$D$20001,IF(Settings!$B$4="","<>",Settings!$B$4))) -> 0 | O34: =IF($N34=0,0,IF(Settings!$B$5="percent",$M34*$N34/100,$N34)) -> 0 | P34: =IF($L34<>1,0,SUMIFS('JLR Materials'!$G$2:$G$20001,'JLR Materials'!$A$2:$A$20001,$K34,'JLR Materials'!$C$2:$C$20001,IF(Settings!$B$2="","<>",Settings!$B$2),'JLR Materials'!$D$2:$D$20001,IF(Settings!$B$4="","<>",Settings!$B$4))) -> 0 | Q34: UK steel coil Jun 2026. Thin zinc coating — automotive body, appliance housings. Better paintability than hot-dip. Yield 140 MPa. Index-anchored 2026-07 (see PRICING BASIS). | Refresh 2026-09: +£0.049/kg from 1kg crc £0.668→£0.717/kg; premiums held | R34: 2026-09
A35: mat-hsla420 | B35: HSLA 420 Sheet | C35: High Strength Steel Sheet | D35: =IF($M35>0,$M35,1.29) -> 1.29 | E35: =IF($O35>0,$O35,0.23) -> 0.23 | F35: 7850 | G35: UK | H35: =IF($M35>0,IF($L35<>1,$R35,IFERROR(INDEX('JLR Materials'!$D$2:$D$20001,MATCH($K35,'JLR Materials'!$A$2:$A$20001,0)),$R35)),$R35) -> 2026-09 | I35: =IF($M35>0,"JLR rate card — material code "&$K35,$Q35) -> UK HSLA coil Jun 2026. 420 MPa min yield — structural reinforcements, crash components. Higher strength premium over HSLA 340. Index-anchored 2026-07 (see PRICING BASIS). | Refresh 2026-09: +£0.049/kg from 1kg crc £0.668→£0.717/kg; premiums held | J35: Low | K35: =IFERROR(INDEX(Mapping!$C$2:$C$549,MATCH($A35,Mapping!$A$2:$A$549,0)),"") | L35: =IF($K35="",0,COUNTIFS('JLR Materials'!$A$2:$A$20001,$K35,'JLR Materials'!$C$2:$C$20001,IF(Settings!$B$2="","<>",Settings!$B$2),'JLR Materials'!$D$2:$D$20001,IF(Settings!$B$4="","<>",Settings!$B$4))) -> 0 | M35: =IF($L35<>1,0,SUMIFS('JLR Materials'!$E$2:$E$20001,'JLR Materials'!$A$2:$A$20001,$K35,'JLR Materials'!$C$2:$C$20001,IF(Settings!$B$2="","<>",Settings!$B$2),'JLR Materials'!$D$2:$D$20001,IF(Settings!$B$4="","<>",Settings!$B$4))) -> 0 | N35: =IF($L35<>1,0,SUMIFS('JLR Materials'!$F$2:$F$20001,'JLR Materials'!$A$2:$A$20001,$K35,'JLR Materials'!$C$2:$C$20001,IF(Settings!$B$2="","<>",Settings!$B$2),'JLR Materials'!$D$2:$D$20001,IF(Settings!$B$4="","<>",Settings!$B$4))) -> 0 | O35: =IF($N35=0,0,IF(Settings!$B$5="percent",$M35*$N35/100,$N35)) -> 0 | P35: =IF($L35<>1,0,SUMIFS('JLR Materials'!$G$2:$G$20001,'JLR Materials'!$A$2:$A$20001,$K35,'JLR Materials'!$C$2:$C$20001,IF(Settings!$B$2="","<>",Settings!$B$2),'JLR Materials'!$D$2:$D$20001,IF(Settings!$B$4="","<>",Settings!$B$4))) -> 0 | Q35: UK HSLA coil Jun 2026. 420 MPa min yield — structural reinforcements, crash components. Higher strength premium over HSLA 340. Index-anchored 2026-07 (see PRICING BASIS). | Refresh 2026-09: +£0.049/kg from 1kg crc £0.668→£0.717/kg; premiums held | R35: 2026-09
A36: mat-hrpo | B36: HRPO (Hot Rolled Pickled & Oiled) | C36: Mild Steel Sheet | D36: =IF($M36>0,$M36,0.77) -> 0.77 | E36: =IF($O36>0,$O36,0.19) -> 0.19 | F36: 7850 | G36: UK | H36: =IF($M36>0,IF($L36<>1,$R36,IFERROR(INDEX('JLR Materials'!$D$2:$D$20001,MATCH($K36,'JLR Materials'!$A$2:$A$20001,0)),$R36)),$R36) -> 2026-09 | I36: =IF($M36>0,"JLR rate card — material code "&$K36,$Q36) -> UK steel coil Jun 2026. Hot-rolled, pickled and oiled — structural fabrication, heavy-gauge brackets, lower cost than CR. Yield 250 MPa. Index-anchored 2026-07 (see PRICING BASIS). | Refresh 2026-09: +£0.049/kg from 1kg hrc £0.591→£0.639/kg; premiums held | J36: Medium | K36: =IFERROR(INDEX(Mapping!$C$2:$C$549,MATCH($A36,Mapping!$A$2:$A$549,0)),"") | L36: =IF($K36="",0,COUNTIFS('JLR Materials'!$A$2:$A$20001,$K36,'JLR Materials'!$C$2:$C$20001,IF(Settings!$B$2="","<>",Settings!$B$2),'JLR Materials'!$D$2:$D$20001,IF(Settings!$B$4="","<>",Settings!$B$4))) -> 0 | M36: =IF($L36<>1,0,SUMIFS('JLR Materials'!$E$2:$E$20001,'JLR Materials'!$A$2:$A$20001,$K36,'JLR Materials'!$C$2:$C$20001,IF(Settings!$B$2="","<>",Settings!$B$2),'JLR Materials'!$D$2:$D$20001,IF(Settings!$B$4="","<>",Settings!$B$4))) -> 0 | N36: =IF($L36<>1,0,SUMIFS('JLR Materials'!$F$2:$F$20001,'JLR Materials'!$A$2:$A$20001,$K36,'JLR Materials'!$C$2:$C$20001,IF(Settings!$B$2="","<>",Settings!$B$2),'JLR Materials'!$D$2:$D$20001,IF(Settings!$B$4="","<>",Settings!$B$4))) -> 0 | O36: =IF($N36=0,0,IF(Settings!$B$5="percent",$M36*$N36/100,$N36)) -> 0 | P36: =IF($L36<>1,0,SUMIFS('JLR Materials'!$G$2:$G$20001,'JLR Materials'!$A$2:$A$20001,$K36,'JLR Materials'!$C$2:$C$20001,IF(Settings!$B$2="","<>",Settings!$B$2),'JLR Materials'!$D$2:$D$20001,IF(Settings!$B$4="","<>",Settings!$B$4))) -> 0 | Q36: UK steel coil Jun 2026. Hot-rolled, pickled and oiled — structural fabrication, heavy-gauge brackets, lower cost than CR. Yield 250 MPa. Index-anchored 2026-07 (see PRICING BASIS). | Refresh 2026-09: +£0.049/kg from 1kg hrc £0.591→£0.639/kg; premiums held | R36: 2026-09
A37: mat-aa5754-sheet | B37: AA5754-H22 Sheet | C37: Aluminium Sheet | D37: =IF($M37>0,$M37,3.32) -> 3.32 | E37: =IF($O37>0,$O37,0.49) -> 0.49 | F37: 2660 | G37: UK | H37: =IF($M37>0,IF($L37<>1,$R37,IFERROR(INDEX('JLR Materials'!$D$2:$D$20001,MATCH($K37,'JLR Materials'!$A$2:$A$20001,0)),$R37)),$R37) -> 2026-09 | I37: =IF($M37>0,"JLR rate card — material code "&$K37,$Q37) -> UK Al sheet stockholder Jun 2026. 5754 H22 — automotive body closures, truck panels. Excellent formability. Yield 140 MPa. Index-anchored 2026-07 (see PRICING BASIS). | Refresh 2026-09: −£0.060/kg from 0.97kg al £2.910→£2.849/kg; premiums held | J37: Medium | K37: =IFERROR(INDEX(Mapping!$C$2:$C$549,MATCH($A37,Mapping!$A$2:$A$549,0)),"") | L37: =IF($K37="",0,COUNTIFS('JLR Materials'!$A$2:$A$20001,$K37,'JLR Materials'!$C$2:$C$20001,IF(Settings!$B$2="","<>",Settings!$B$2),'JLR Materials'!$D$2:$D$20001,IF(Settings!$B$4="","<>",Settings!$B$4))) -> 0 | M37: =IF($L37<>1,0,SUMIFS('JLR Materials'!$E$2:$E$20001,'JLR Materials'!$A$2:$A$20001,$K37,'JLR Materials'!$C$2:$C$20001,IF(Settings!$B$2="","<>",Settings!$B$2),'JLR Materials'!$D$2:$D$20001,IF(Settings!$B$4="","<>",Settings!$B$4))) -> 0 | N37: =IF($L37<>1,0,SUMIFS('JLR Materials'!$F$2:$F$20001,'JLR Materials'!$A$2:$A$20001,$K37,'JLR Materials'!$C$2:$C$20001,IF(Settings!$B$2="","<>",Settings!$B$2),'JLR Materials'!$D$2:$D$20001,IF(Settings!$B$4="","<>",Settings!$B$4))) -> 0 | O37: =IF($N37=0,0,IF(Settings!$B$5="percent",$M37*$N37/100,$N37)) -> 0 | P37: =IF($L37<>1,0,SUMIFS('JLR Materials'!$G$2:$G$20001,'JLR Materials'!$A$2:$A$20001,$K37,'JLR Materials'!$C$2:$C$20001,IF(Settings!$B$2="","<>",Settings!$B$2),'JLR Materials'!$D$2:$D$20001,IF(Settings!$B$4="","<>",Settings!$B$4))) -> 0 | Q37: UK Al sheet stockholder Jun 2026. 5754 H22 — automotive body closures, truck panels. Excellent formability. Yield 140 MPa. Index-anchored 2026-07 (see PRICING BASIS). | Refresh 2026-09: −£0.060/kg from 0.97kg al £2.910→£2.849/kg; premiums held | R37: 2026-09
A38: mat-aa6061-sheet | B38: AA6061-T6 Sheet/Plate | C38: Aluminium Sheet | D38: =IF($M38>0,$M38,3.66) -> 3.66 | E38: =IF($O38>0,$O38,0.49) -> 0.49 | F38: 2700 | G38: UK | H38: =IF($M38>0,IF($L38<>1,$R38,IFERROR(INDEX('JLR Materials'!$D$2:$D$20001,MATCH($K38,'JLR Materials'!$A$2:$A$20001,0)),$R38)),$R38) -> 2026-09 | I38: =IF($M38>0,"JLR rate card — material code "&$K38,$Q38) -> UK Al sheet stockholder Jun 2026. 6061 T6 — general structural, aerospace, vehicle frames. Yield 276 MPa. Good weldability. Index-anchored 2026-07 (see PRICING BASIS). | Refresh 2026-09: −£0.060/kg from 0.97kg al £2.910→£2.849/kg; premiums held | J38: Medium | K38: =IFERROR(INDEX(Mapping!$C$2:$C$549,MATCH($A38,Mapping!$A$2:$A$549,0)),"") | L38: =IF($K38="",0,COUNTIFS('JLR Materials'!$A$2:$A$20001,$K38,'JLR Materials'!$C$2:$C$20001,IF(Settings!$B$2="","<>",Settings!$B$2),'JLR Materials'!$D$2:$D$20001,IF(Settings!$B$4="","<>",Settings!$B$4))) -> 0 | M38: =IF($L38<>1,0,SUMIFS('JLR Materials'!$E$2:$E$20001,'JLR Materials'!$A$2:$A$20001,$K38,'JLR Materials'!$C$2:$C$20001,IF(Settings!$B$2="","<>",Settings!$B$2),'JLR Materials'!$D$2:$D$20001,IF(Settings!$B$4="","<>",Settings!$B$4))) -> 0 | N38: =IF($L38<>1,0,SUMIFS('JLR Materials'!$F$2:$F$20001,'JLR Materials'!$A$2:$A$20001,$K38,'JLR Materials'!$C$2:$C$20001,IF(Settings!$B$2="","<>",Settings!$B$2),'JLR Materials'!$D$2:$D$20001,IF(Settings!$B$4="","<>",Settings!$B$4))) -> 0 | O38: =IF($N38=0,0,IF(Settings!$B$5="percent",$M38*$N38/100,$N38)) -> 0 | P38: =IF($L38<>1,0,SUMIFS('JLR Materials'!$G$2:$G$20001,'JLR Materials'!$A$2:$A$20001,$K38,'JLR Materials'!$C$2:$C$20001,IF(Settings!$B$2="","<>",Settings!$B$2),'JLR Materials'!$D$2:$D$20001,IF(Settings!$B$4="","<>",Settings!$B$4))) -> 0 | Q38: UK Al sheet stockholder Jun 2026. 6061 T6 — general structural, aerospace, vehicle frames. Yield 276 MPa. Good weldability. Index-anchored 2026-07 (see PRICING BASIS). | Refresh 2026-09: −£0.060/kg from 0.97kg al £2.910→£2.849/kg; premiums held | R38: 2026-09
A39: mat-aa6063-sheet | B39: AA6063-T5 Sheet | C39: Aluminium Sheet | D39: =IF($M39>0,$M39,3.49) -> 3.49 | E39: =IF($O39>0,$O39,0.49) -> 0.49 | F39: 2690 | G39: UK | H39: =IF($M39>0,IF($L39<>1,$R39,IFERROR(INDEX('JLR Materials'!$D$2:$D$20001,MATCH($K39,'JLR Materials'!$A$2:$A$20001,0)),$R39)),$R39) -> 2026-09 | I39: =IF($M39>0,"JLR rate card — material code "&$K39,$Q39) -> UK Al sheet stockholder Jun 2026. 6063 T5 — architectural panels, window frames, radiators. Yield 145 MPa. Anodises well. Index-anchored 2026-07 (see PRICING BASIS). | Refresh 2026-09: −£0.060/kg from 0.97kg al £2.910→£2.849/kg; premiums held | J39: Low | K39: =IFERROR(INDEX(Mapping!$C$2:$C$549,MATCH($A39,Mapping!$A$2:$A$549,0)),"") | L39: =IF($K39="",0,COUNTIFS('JLR Materials'!$A$2:$A$20001,$K39,'JLR Materials'!$C$2:$C$20001,IF(Settings!$B$2="","<>",Settings!$B$2),'JLR Materials'!$D$2:$D$20001,IF(Settings!$B$4="","<>",Settings!$B$4))) -> 0 | M39: =IF($L39<>1,0,SUMIFS('JLR Materials'!$E$2:$E$20001,'JLR Materials'!$A$2:$A$20001,$K39,'JLR Materials'!$C$2:$C$20001,IF(Settings!$B$2="","<>",Settings!$B$2),'JLR Materials'!$D$2:$D$20001,IF(Settings!$B$4="","<>",Settings!$B$4))) -> 0 | N39: =IF($L39<>1,0,SUMIFS('JLR Materials'!$F$2:$F$20001,'JLR Materials'!$A$2:$A$20001,$K39,'JLR Materials'!$C$2:$C$20001,IF(Settings!$B$2="","<>",Settings!$B$2),'JLR Materials'!$D$2:$D$20001,IF(Settings!$B$4="","<>",Settings!$B$4))) -> 0 | O39: =IF($N39=0,0,IF(Settings!$B$5="percent",$M39*$N39/100,$N39)) -> 0 | P39: =IF($L39<>1,0,SUMIFS('JLR Materials'!$G$2:$G$20001,'JLR Materials'!$A$2:$A$20001,$K39,'JLR Materials'!$C$2:$C$20001,IF(Settings!$B$2="","<>",Settings!$B$2),'JLR Materials'!$D$2:$D$20001,IF(Settings!$B$4="","<>",Settings!$B$4))) -> 0 | Q39: UK Al sheet stockholder Jun 2026. 6063 T5 — architectural panels, window frames, radiators. Yield 145 MPa. Anodises well. Index-anchored 2026-07 (see PRICING BASIS). | Refresh 2026-09: −£0.060/kg from 0.97kg al £2.910→£2.849/kg; premiums held | R39: 2026-09
A40: mat-aa3003-sheet | B40: AA3003-H14 Sheet | C40: Aluminium Sheet | D40: =IF($M40>0,$M40,2.99) -> 2.99 | E40: =IF($O40>0,$O40,0.47) -> 0.47 | F40: 2730 | G40: UK | H40: =IF($M40>0,IF($L40<>1,$R40,IFERROR(INDEX('JLR Materials'!$D$2:$D$20001,MATCH($K40,'JLR Materials'!$A$2:$A$20001,0)),$R40)),$R40) -> 2026-09 | I40: =IF($M40>0,"JLR rate card — material code "&$K40,$Q40) -> UK Al sheet stockholder Jun 2026. 3003 H14 — heat exchangers, chemical equipment, fuel tanks, cookware. Best formability of common Al alloys. Yield 145 MPa. Index-anchored 2026-07 (see PRICING BASIS). | Refresh 2026-09: −£0.060/kg from 0.97kg al £2.910→£2.849/kg; premiums held | J40: Low | K40: =IFERROR(INDEX(Mapping!$C$2:$C$549,MATCH($A40,Mapping!$A$2:$A$549,0)),"") | L40: =IF($K40="",0,COUNTIFS('JLR Materials'!$A$2:$A$20001,$K40,'JLR Materials'!$C$2:$C$20001,IF(Settings!$B$2="","<>",Settings!$B$2),'JLR Materials'!$D$2:$D$20001,IF(Settings!$B$4="","<>",Settings!$B$4))) -> 0 | M40: =IF($L40<>1,0,SUMIFS('JLR Materials'!$E$2:$E$20001,'JLR Materials'!$A$2:$A$20001,$K40,'JLR Materials'!$C$2:$C$20001,IF(Settings!$B$2="","<>",Settings!$B$2),'JLR Materials'!$D$2:$D$20001,IF(Settings!$B$4="","<>",Settings!$B$4))) -> 0 | N40: =IF($L40<>1,0,SUMIFS('JLR Materials'!$F$2:$F$20001,'JLR Materials'!$A$2:$A$20001,$K40,'JLR Materials'!$C$2:$C$20001,IF(Settings!$B$2="","<>",Settings!$B$2),'JLR Materials'!$D$2:$D$20001,IF(Settings!$B$4="","<>",Settings!$B$4))) -> 0 | O40: =IF($N40=0,0,IF(Settings!$B$5="percent",$M40*$N40/100,$N40)) -> 0 | P40: =IF($L40<>1,0,SUMIFS('JLR Materials'!$G$2:$G$20001,'JLR Materials'!$A$2:$A$20001,$K40,'JLR Materials'!$C$2:$C$20001,IF(Settings!$B$2="","<>",Settings!$B$2),'JLR Materials'!$D$2:$D$20001,IF(Settings!$B$4="","<>",Settings!$B$4))) -> 0 | Q40: UK Al sheet stockholder Jun 2026. 3003 H14 — heat exchangers, chemical equipment, fuel tanks, cookware. Best formability of common Al alloys. Yield 145 MPa. Index-anchored 2026-07 (see PRICING BASIS). | Refresh 2026-09: −£0.060/kg from 0.97kg al £2.910→£2.849/kg; premiums held | R40: 2026-09
A41: mat-c110-copper | B41: C110 ETP Copper Sheet | C41: Copper & Brass Sheet | D41: =IF($M41>0,$M41,10.77) -> 10.77 | E41: =IF($O41>0,$O41,6.01) -> 6.01 | F41: 8940 | G41: UK | H41: =IF($M41>0,IF($L41<>1,$R41,IFERROR(INDEX('JLR Materials'!$D$2:$D$20001,MATCH($K41,'JLR Materials'!$A$2:$A$20001,0)),$R41)),$R41) -> 2026-09 | I41: =IF($M41>0,"JLR rate card — material code "&$K41,$Q41) -> UK copper stockholder Jun 2026. C110 ETP copper — busbars, electrical contacts, heat sinks, roofing. 99.9% Cu, 100% IACS. Yield 70 MPa. Index-anchored 2026-07 (see PRICING BASIS). | Refresh 2026-09: +£0.920/kg from 1kg cu £10.070→£10.768/kg, floored at commodity content £10.77/kg (previous level was below the metal it contains); premiums held | J41: Medium | K41: =IFERROR(INDEX(Mapping!$C$2:$C$549,MATCH($A41,Mapping!$A$2:$A$549,0)),"") | L41: =IF($K41="",0,COUNTIFS('JLR Materials'!$A$2:$A$20001,$K41,'JLR Materials'!$C$2:$C$20001,IF(Settings!$B$2="","<>",Settings!$B$2),'JLR Materials'!$D$2:$D$20001,IF(Settings!$B$4="","<>",Settings!$B$4))) -> 0 | M41: =IF($L41<>1,0,SUMIFS('JLR Materials'!$E$2:$E$20001,'JLR Materials'!$A$2:$A$20001,$K41,'JLR Materials'!$C$2:$C$20001,IF(Settings!$B$2="","<>",Settings!$B$2),'JLR Materials'!$D$2:$D$20001,IF(Settings!$B$4="","<>",Settings!$B$4))) -> 0 | N41: =IF($L41<>1,0,SUMIFS('JLR Materials'!$F$2:$F$20001,'JLR Materials'!$A$2:$A$20001,$K41,'JLR Materials'!$C$2:$C$20001,IF(Settings!$B$2="","<>",Settings!$B$2),'JLR Materials'!$D$2:$D$20001,IF(Settings!$B$4="","<>",Settings!$B$4))) -> 0 | O41: =IF($N41=0,0,IF(Settings!$B$5="percent",$M41*$N41/100,$N41)) -> 0 | P41: =IF($L41<>1,0,SUMIFS('JLR Materials'!$G$2:$G$20001,'JLR Materials'!$A$2:$A$20001,$K41,'JLR Materials'!$C$2:$C$20001,IF(Settings!$B$2="","<>",Settings!$B$2),'JLR Materials'!$D$2:$D$20001,IF(Settings!$B$4="","<>",Settings!$B$4))) -> 0 | Q41: UK copper stockholder Jun 2026. C110 ETP copper — busbars, electrical contacts, heat sinks, roofing. 99.9% Cu, 100% IACS. Yield 70 MPa. Index-anchored 2026-07 (see PRICING BASIS). | Refresh 2026-09: +£0.920/kg from 1kg cu £10.070→£10.768/kg, floored at commodity content £10.77/kg (previous level was below the metal it contains); premiums held | R41: 2026-09
A42: mat-cz108-brass | B42: CZ108 Brass Sheet (70/30) | C42: Copper & Brass Sheet | D42: =IF($M42>0,$M42,8.42) -> 8.42 | E42: =IF($O42>0,$O42,4.77) -> 4.77 | F42: 8530 | G42: UK | H42: =IF($M42>0,IF($L42<>1,$R42,IFERROR(INDEX('JLR Materials'!$D$2:$D$20001,MATCH($K42,'JLR Materials'!$A$2:$A$20001,0)),$R42)),$R42) -> 2026-09 | I42: =IF($M42>0,"JLR rate card — material code "&$K42,$Q42) -> UK brass stockholder Jun 2026. CZ108 70/30 cartridge brass — decorative panels, heat exchangers, plumbing fittings. Excellent cold formability. Yield 105 MPa. Index-anchored 2026-07 (see PRICING BASIS). | Refresh 2026-09: +£1.000/kg from 0.7kg cu £10.070→£10.768/kg, 0.3kg zn £2.164→£2.913/kg, floored at commodity content £8.41/kg (previous level was below the metal it contains); premiums held | J42: Medium | K42: =IFERROR(INDEX(Mapping!$C$2:$C$549,MATCH($A42,Mapping!$A$2:$A$549,0)),"") | L42: =IF($K42="",0,COUNTIFS('JLR Materials'!$A$2:$A$20001,$K42,'JLR Materials'!$C$2:$C$20001,IF(Settings!$B$2="","<>",Settings!$B$2),'JLR Materials'!$D$2:$D$20001,IF(Settings!$B$4="","<>",Settings!$B$4))) -> 0 | M42: =IF($L42<>1,0,SUMIFS('JLR Materials'!$E$2:$E$20001,'JLR Materials'!$A$2:$A$20001,$K42,'JLR Materials'!$C$2:$C$20001,IF(Settings!$B$2="","<>",Settings!$B$2),'JLR Materials'!$D$2:$D$20001,IF(Settings!$B$4="","<>",Settings!$B$4))) -> 0 | N42: =IF($L42<>1,0,SUMIFS('JLR Materials'!$F$2:$F$20001,'JLR Materials'!$A$2:$A$20001,$K42,'JLR Materials'!$C$2:$C$20001,IF(Settings!$B$2="","<>",Settings!$B$2),'JLR Materials'!$D$2:$D$20001,IF(Settings!$B$4="","<>",Settings!$B$4))) -> 0 | O42: =IF($N42=0,0,IF(Settings!$B$5="percent",$M42*$N42/100,$N42)) -> 0 | P42: =IF($L42<>1,0,SUMIFS('JLR Materials'!$G$2:$G$20001,'JLR Materials'!$A$2:$A$20001,$K42,'JLR Materials'!$C$2:$C$20001,IF(Settings!$B$2="","<>",Settings!$B$2),'JLR Materials'!$D$2:$D$20001,IF(Settings!$B$4="","<>",Settings!$B$4))) -> 0 | Q42: UK brass stockholder Jun 2026. CZ108 70/30 cartridge brass — decorative panels, heat exchangers, plumbing fittings. Excellent cold formability. Yield 105 MPa. Index-anchored 2026-07 (see PRICING BASIS). | Refresh 2026-09: +£1.000/kg from 0.7kg cu £10.070→£10.768/kg, 0.3kg zn £2.164→£2.913/kg, floored at commodity content £8.41/kg (previous level was below the metal it contains); premiums held | R42: 2026-09
A43: mat-dp780 | B43: DP780 | C43: AHSS Sheet | D43: =IF($M43>0,$M43,1.37) -> 1.37 | E43: =IF($O43>0,$O43,0.23) -> 0.23 | F43: 7850 | G43: UK | H43: =IF($M43>0,IF($L43<>1,$R43,IFERROR(INDEX('JLR Materials'!$D$2:$D$20001,MATCH($K43,'JLR Materials'!$A$2:$A$20001,0)),$R43)),$R43) -> 2026-09 | I43: =IF($M43>0,"JLR rate card — material code "&$K43,$Q43) -> UK AHSS coil Jul 2026. Dual-phase 780 MPa UTS — crash rails, seat structures. Needs ~1.6× press tonnage & extra restrike vs DP600; springback compensation in die. Yield ~450 MPa. | Refresh 2026-09: +£0.049/kg from 1kg crc £0.668→£0.717/kg; premiums held | J43: Low | K43: =IFERROR(INDEX(Mapping!$C$2:$C$549,MATCH($A43,Mapping!$A$2:$A$549,0)),"") | L43: =IF($K43="",0,COUNTIFS('JLR Materials'!$A$2:$A$20001,$K43,'JLR Materials'!$C$2:$C$20001,IF(Settings!$B$2="","<>",Settings!$B$2),'JLR Materials'!$D$2:$D$20001,IF(Settings!$B$4="","<>",Settings!$B$4))) -> 0 | M43: =IF($L43<>1,0,SUMIFS('JLR Materials'!$E$2:$E$20001,'JLR Materials'!$A$2:$A$20001,$K43,'JLR Materials'!$C$2:$C$20001,IF(Settings!$B$2="","<>",Settings!$B$2),'JLR Materials'!$D$2:$D$20001,IF(Settings!$B$4="","<>",Settings!$B$4))) -> 0 | N43: =IF($L43<>1,0,SUMIFS('JLR Materials'!$F$2:$F$20001,'JLR Materials'!$A$2:$A$20001,$K43,'JLR Materials'!$C$2:$C$20001,IF(Settings!$B$2="","<>",Settings!$B$2),'JLR Materials'!$D$2:$D$20001,IF(Settings!$B$4="","<>",Settings!$B$4))) -> 0 | O43: =IF($N43=0,0,IF(Settings!$B$5="percent",$M43*$N43/100,$N43)) -> 0 | P43: =IF($L43<>1,0,SUMIFS('JLR Materials'!$G$2:$G$20001,'JLR Materials'!$A$2:$A$20001,$K43,'JLR Materials'!$C$2:$C$20001,IF(Settings!$B$2="","<>",Settings!$B$2),'JLR Materials'!$D$2:$D$20001,IF(Settings!$B$4="","<>",Settings!$B$4))) -> 0 | Q43: UK AHSS coil Jul 2026. Dual-phase 780 MPa UTS — crash rails, seat structures. Needs ~1.6× press tonnage & extra restrike vs DP600; springback compensation in die. Yield ~450 MPa. | Refresh 2026-09: +£0.049/kg from 1kg crc £0.668→£0.717/kg; premiums held | R43: 2026-09
A44: mat-dp980 | B44: DP980 | C44: AHSS Sheet | D44: =IF($M44>0,$M44,1.5) -> 1.5 | E44: =IF($O44>0,$O44,0.23) -> 0.23 | F44: 7850 | G44: UK | H44: =IF($M44>0,IF($L44<>1,$R44,IFERROR(INDEX('JLR Materials'!$D$2:$D$20001,MATCH($K44,'JLR Materials'!$A$2:$A$20001,0)),$R44)),$R44) -> 2026-09 | I44: =IF($M44>0,"JLR rate card — material code "&$K44,$Q44) -> UK AHSS coil Jul 2026. Dual-phase 980 MPa UTS — B-pillar reinforcements, longitudinals. High die wear, significant springback, limited formability. Yield ~600 MPa. | Refresh 2026-09: +£0.049/kg from 1kg crc £0.668→£0.717/kg; premiums held | J44: Low | K44: =IFERROR(INDEX(Mapping!$C$2:$C$549,MATCH($A44,Mapping!$A$2:$A$549,0)),"") | L44: =IF($K44="",0,COUNTIFS('JLR Materials'!$A$2:$A$20001,$K44,'JLR Materials'!$C$2:$C$20001,IF(Settings!$B$2="","<>",Settings!$B$2),'JLR Materials'!$D$2:$D$20001,IF(Settings!$B$4="","<>",Settings!$B$4))) -> 0 | M44: =IF($L44<>1,0,SUMIFS('JLR Materials'!$E$2:$E$20001,'JLR Materials'!$A$2:$A$20001,$K44,'JLR Materials'!$C$2:$C$20001,IF(Settings!$B$2="","<>",Settings!$B$2),'JLR Materials'!$D$2:$D$20001,IF(Settings!$B$4="","<>",Settings!$B$4))) -> 0 | N44: =IF($L44<>1,0,SUMIFS('JLR Materials'!$F$2:$F$20001,'JLR Materials'!$A$2:$A$20001,$K44,'JLR Materials'!$C$2:$C$20001,IF(Settings!$B$2="","<>",Settings!$B$2),'JLR Materials'!$D$2:$D$20001,IF(Settings!$B$4="","<>",Settings!$B$4))) -> 0 | O44: =IF($N44=0,0,IF(Settings!$B$5="percent",$M44*$N44/100,$N44)) -> 0 | P44: =IF($L44<>1,0,SUMIFS('JLR Materials'!$G$2:$G$20001,'JLR Materials'!$A$2:$A$20001,$K44,'JLR Materials'!$C$2:$C$20001,IF(Settings!$B$2="","<>",Settings!$B$2),'JLR Materials'!$D$2:$D$20001,IF(Settings!$B$4="","<>",Settings!$B$4))) -> 0 | Q44: UK AHSS coil Jul 2026. Dual-phase 980 MPa UTS — B-pillar reinforcements, longitudinals. High die wear, significant springback, limited formability. Yield ~600 MPa. | Refresh 2026-09: +£0.049/kg from 1kg crc £0.668→£0.717/kg; premiums held | R44: 2026-09
A45: mat-dp1000 | B45: DP1000 | C45: AHSS Sheet | D45: =IF($M45>0,$M45,1.57) -> 1.57 | E45: =IF($O45>0,$O45,0.23) -> 0.23 | F45: 7850 | G45: UK | H45: =IF($M45>0,IF($L45<>1,$R45,IFERROR(INDEX('JLR Materials'!$D$2:$D$20001,MATCH($K45,'JLR Materials'!$A$2:$A$20001,0)),$R45)),$R45) -> 2026-09 | I45: =IF($M45>0,"JLR rate card — material code "&$K45,$Q45) -> UK AHSS coil Jul 2026. Dual-phase 1000 MPa UTS — cold-formed crash structures. Yield ~700 MPa. | Refresh 2026-09: +£0.049/kg from 1kg crc £0.668→£0.717/kg; premiums held | J45: Low | K45: =IFERROR(INDEX(Mapping!$C$2:$C$549,MATCH($A45,Mapping!$A$2:$A$549,0)),"") | L45: =IF($K45="",0,COUNTIFS('JLR Materials'!$A$2:$A$20001,$K45,'JLR Materials'!$C$2:$C$20001,IF(Settings!$B$2="","<>",Settings!$B$2),'JLR Materials'!$D$2:$D$20001,IF(Settings!$B$4="","<>",Settings!$B$4))) -> 0 | M45: =IF($L45<>1,0,SUMIFS('JLR Materials'!$E$2:$E$20001,'JLR Materials'!$A$2:$A$20001,$K45,'JLR Materials'!$C$2:$C$20001,IF(Settings!$B$2="","<>",Settings!$B$2),'JLR Materials'!$D$2:$D$20001,IF(Settings!$B$4="","<>",Settings!$B$4))) -> 0 | N45: =IF($L45<>1,0,SUMIFS('JLR Materials'!$F$2:$F$20001,'JLR Materials'!$A$2:$A$20001,$K45,'JLR Materials'!$C$2:$C$20001,IF(Settings!$B$2="","<>",Settings!$B$2),'JLR Materials'!$D$2:$D$20001,IF(Settings!$B$4="","<>",Settings!$B$4))) -> 0 | O45: =IF($N45=0,0,IF(Settings!$B$5="percent",$M45*$N45/100,$N45)) -> 0 | P45: =IF($L45<>1,0,SUMIFS('JLR Materials'!$G$2:$G$20001,'JLR Materials'!$A$2:$A$20001,$K45,'JLR Materials'!$C$2:$C$20001,IF(Settings!$B$2="","<>",Settings!$B$2),'JLR Materials'!$D$2:$D$20001,IF(Settings!$B$4="","<>",Settings!$B$4))) -> 0 | Q45: UK AHSS coil Jul 2026. Dual-phase 1000 MPa UTS — cold-formed crash structures. Yield ~700 MPa. | Refresh 2026-09: +£0.049/kg from 1kg crc £0.668→£0.717/kg; premiums held | R45: 2026-09
A46: mat-trip780 | B46: TRIP780 | C46: AHSS Sheet | D46: =IF($M46>0,$M46,1.45) -> 1.45 | E46: =IF($O46>0,$O46,0.23) -> 0.23 | F46: 7850 | G46: UK | H46: =IF($M46>0,IF($L46<>1,$R46,IFERROR(INDEX('JLR Materials'!$D$2:$D$20001,MATCH($K46,'JLR Materials'!$A$2:$A$20001,0)),$R46)),$R46) -> 2026-09 | I46: =IF($M46>0,"JLR rate card — material code "&$K46,$Q46) -> UK AHSS coil Jul 2026. Transformation-induced plasticity 780 — best strength/formability balance, energy-absorbing members. Retained austenite. Yield ~440 MPa. | Refresh 2026-09: +£0.049/kg from 1kg crc £0.668→£0.717/kg; premiums held | J46: Low | K46: =IFERROR(INDEX(Mapping!$C$2:$C$549,MATCH($A46,Mapping!$A$2:$A$549,0)),"") | L46: =IF($K46="",0,COUNTIFS('JLR Materials'!$A$2:$A$20001,$K46,'JLR Materials'!$C$2:$C$20001,IF(Settings!$B$2="","<>",Settings!$B$2),'JLR Materials'!$D$2:$D$20001,IF(Settings!$B$4="","<>",Settings!$B$4))) -> 0 | M46: =IF($L46<>1,0,SUMIFS('JLR Materials'!$E$2:$E$20001,'JLR Materials'!$A$2:$A$20001,$K46,'JLR Materials'!$C$2:$C$20001,IF(Settings!$B$2="","<>",Settings!$B$2),'JLR Materials'!$D$2:$D$20001,IF(Settings!$B$4="","<>",Settings!$B$4))) -> 0 | N46: =IF($L46<>1,0,SUMIFS('JLR Materials'!$F$2:$F$20001,'JLR Materials'!$A$2:$A$20001,$K46,'JLR Materials'!$C$2:$C$20001,IF(Settings!$B$2="","<>",Settings!$B$2),'JLR Materials'!$D$2:$D$20001,IF(Settings!$B$4="","<>",Settings!$B$4))) -> 0 | O46: =IF($N46=0,0,IF(Settings!$B$5="percent",$M46*$N46/100,$N46)) -> 0 | P46: =IF($L46<>1,0,SUMIFS('JLR Materials'!$G$2:$G$20001,'JLR Materials'!$A$2:$A$20001,$K46,'JLR Materials'!$C$2:$C$20001,IF(Settings!$B$2="","<>",Settings!$B$2),'JLR Materials'!$D$2:$D$20001,IF(Settings!$B$4="","<>",Settings!$B$4))) -> 0 | Q46: UK AHSS coil Jul 2026. Transformation-induced plasticity 780 — best strength/formability balance, energy-absorbing members. Retained austenite. Yield ~440 MPa. | Refresh 2026-09: +£0.049/kg from 1kg crc £0.668→£0.717/kg; premiums held | R46: 2026-09
A47: mat-cp800 | B47: CP800 (Complex Phase) | C47: AHSS Sheet | D47: =IF($M47>0,$M47,1.43) -> 1.43 | E47: =IF($O47>0,$O47,0.23) -> 0.23 | F47: 7850 | G47: UK | H47: =IF($M47>0,IF($L47<>1,$R47,IFERROR(INDEX('JLR Materials'!$D$2:$D$20001,MATCH($K47,'JLR Materials'!$A$2:$A$20001,0)),$R47)),$R47) -> 2026-09 | I47: =IF($M47>0,"JLR rate card — material code "&$K47,$Q47) -> UK AHSS coil Jul 2026. Complex-phase 800 — high yield, good edge-stretch/hole expansion for chassis & suspension parts. Yield ~680 MPa. | Refresh 2026-09: +£0.049/kg from 1kg crc £0.668→£0.717/kg; premiums held | J47: Low | K47: =IFERROR(INDEX(Mapping!$C$2:$C$549,MATCH($A47,Mapping!$A$2:$A$549,0)),"") | L47: =IF($K47="",0,COUNTIFS('JLR Materials'!$A$2:$A$20001,$K47,'JLR Materials'!$C$2:$C$20001,IF(Settings!$B$2="","<>",Settings!$B$2),'JLR Materials'!$D$2:$D$20001,IF(Settings!$B$4="","<>",Settings!$B$4))) -> 0 | M47: =IF($L47<>1,0,SUMIFS('JLR Materials'!$E$2:$E$20001,'JLR Materials'!$A$2:$A$20001,$K47,'JLR Materials'!$C$2:$C$20001,IF(Settings!$B$2="","<>",Settings!$B$2),'JLR Materials'!$D$2:$D$20001,IF(Settings!$B$4="","<>",Settings!$B$4))) -> 0 | N47: =IF($L47<>1,0,SUMIFS('JLR Materials'!$F$2:$F$20001,'JLR Materials'!$A$2:$A$20001,$K47,'JLR Materials'!$C$2:$C$20001,IF(Settings!$B$2="","<>",Settings!$B$2),'JLR Materials'!$D$2:$D$20001,IF(Settings!$B$4="","<>",Settings!$B$4))) -> 0 | O47: =IF($N47=0,0,IF(Settings!$B$5="percent",$M47*$N47/100,$N47)) -> 0 | P47: =IF($L47<>1,0,SUMIFS('JLR Materials'!$G$2:$G$20001,'JLR Materials'!$A$2:$A$20001,$K47,'JLR Materials'!$C$2:$C$20001,IF(Settings!$B$2="","<>",Settings!$B$2),'JLR Materials'!$D$2:$D$20001,IF(Settings!$B$4="","<>",Settings!$B$4))) -> 0 | Q47: UK AHSS coil Jul 2026. Complex-phase 800 — high yield, good edge-stretch/hole expansion for chassis & suspension parts. Yield ~680 MPa. | Refresh 2026-09: +£0.049/kg from 1kg crc £0.668→£0.717/kg; premiums held | R47: 2026-09
A48: mat-ms1200 | B48: MS1200 (Martensitic) | C48: Ultra-High Strength Steel | D48: =IF($M48>0,$M48,1.6) -> 1.6 | E48: =IF($O48>0,$O48,0.23) -> 0.23 | F48: 7850 | G48: UK | H48: =IF($M48>0,IF($L48<>1,$R48,IFERROR(INDEX('JLR Materials'!$D$2:$D$20001,MATCH($K48,'JLR Materials'!$A$2:$A$20001,0)),$R48)),$R48) -> 2026-09 | I48: =IF($M48>0,"JLR rate card — material code "&$K48,$Q48) -> UK UHSS coil Jul 2026. Martensitic 1200 MPa — roll-formed bumper beams, door beams. Very low formability, roll-form only. Yield ~950 MPa. | Refresh 2026-09: +£0.049/kg from 1kg crc £0.668→£0.717/kg; premiums held | J48: Low | K48: =IFERROR(INDEX(Mapping!$C$2:$C$549,MATCH($A48,Mapping!$A$2:$A$549,0)),"") | L48: =IF($K48="",0,COUNTIFS('JLR Materials'!$A$2:$A$20001,$K48,'JLR Materials'!$C$2:$C$20001,IF(Settings!$B$2="","<>",Settings!$B$2),'JLR Materials'!$D$2:$D$20001,IF(Settings!$B$4="","<>",Settings!$B$4))) -> 0 | M48: =IF($L48<>1,0,SUMIFS('JLR Materials'!$E$2:$E$20001,'JLR Materials'!$A$2:$A$20001,$K48,'JLR Materials'!$C$2:$C$20001,IF(Settings!$B$2="","<>",Settings!$B$2),'JLR Materials'!$D$2:$D$20001,IF(Settings!$B$4="","<>",Settings!$B$4))) -> 0 | N48: =IF($L48<>1,0,SUMIFS('JLR Materials'!$F$2:$F$20001,'JLR Materials'!$A$2:$A$20001,$K48,'JLR Materials'!$C$2:$C$20001,IF(Settings!$B$2="","<>",Settings!$B$2),'JLR Materials'!$D$2:$D$20001,IF(Settings!$B$4="","<>",Settings!$B$4))) -> 0 | O48: =IF($N48=0,0,IF(Settings!$B$5="percent",$M48*$N48/100,$N48)) -> 0 | P48: =IF($L48<>1,0,SUMIFS('JLR Materials'!$G$2:$G$20001,'JLR Materials'!$A$2:$A$20001,$K48,'JLR Materials'!$C$2:$C$20001,IF(Settings!$B$2="","<>",Settings!$B$2),'JLR Materials'!$D$2:$D$20001,IF(Settings!$B$4="","<>",Settings!$B$4))) -> 0 | Q48: UK UHSS coil Jul 2026. Martensitic 1200 MPa — roll-formed bumper beams, door beams. Very low formability, roll-form only. Yield ~950 MPa. | Refresh 2026-09: +£0.049/kg from 1kg crc £0.668→£0.717/kg; premiums held | R48: 2026-09
A49: mat-ms1500 | B49: MS1500 (Martensitic) | C49: Ultra-High Strength Steel | D49: =IF($M49>0,$M49,1.77) -> 1.77 | E49: =IF($O49>0,$O49,0.23) -> 0.23 | F49: 7850 | G49: UK | H49: =IF($M49>0,IF($L49<>1,$R49,IFERROR(INDEX('JLR Materials'!$D$2:$D$20001,MATCH($K49,'JLR Materials'!$A$2:$A$20001,0)),$R49)),$R49) -> 2026-09 | I49: =IF($M49>0,"JLR rate card — material code "&$K49,$Q49) -> UK UHSS coil Jul 2026. Martensitic 1500 MPa — bumper beams, intrusion beams. Roll-forming or hot forming only. Yield ~1200 MPa. | Refresh 2026-09: +£0.049/kg from 1kg crc £0.668→£0.717/kg; premiums held | J49: Low | K49: =IFERROR(INDEX(Mapping!$C$2:$C$549,MATCH($A49,Mapping!$A$2:$A$549,0)),"") | L49: =IF($K49="",0,COUNTIFS('JLR Materials'!$A$2:$A$20001,$K49,'JLR Materials'!$C$2:$C$20001,IF(Settings!$B$2="","<>",Settings!$B$2),'JLR Materials'!$D$2:$D$20001,IF(Settings!$B$4="","<>",Settings!$B$4))) -> 0 | M49: =IF($L49<>1,0,SUMIFS('JLR Materials'!$E$2:$E$20001,'JLR Materials'!$A$2:$A$20001,$K49,'JLR Materials'!$C$2:$C$20001,IF(Settings!$B$2="","<>",Settings!$B$2),'JLR Materials'!$D$2:$D$20001,IF(Settings!$B$4="","<>",Settings!$B$4))) -> 0 | N49: =IF($L49<>1,0,SUMIFS('JLR Materials'!$F$2:$F$20001,'JLR Materials'!$A$2:$A$20001,$K49,'JLR Materials'!$C$2:$C$20001,IF(Settings!$B$2="","<>",Settings!$B$2),'JLR Materials'!$D$2:$D$20001,IF(Settings!$B$4="","<>",Settings!$B$4))) -> 0 | O49: =IF($N49=0,0,IF(Settings!$B$5="percent",$M49*$N49/100,$N49)) -> 0 | P49: =IF($L49<>1,0,SUMIFS('JLR Materials'!$G$2:$G$20001,'JLR Materials'!$A$2:$A$20001,$K49,'JLR Materials'!$C$2:$C$20001,IF(Settings!$B$2="","<>",Settings!$B$2),'JLR Materials'!$D$2:$D$20001,IF(Settings!$B$4="","<>",Settings!$B$4))) -> 0 | Q49: UK UHSS coil Jul 2026. Martensitic 1500 MPa — bumper beams, intrusion beams. Roll-forming or hot forming only. Yield ~1200 MPa. | Refresh 2026-09: +£0.049/kg from 1kg crc £0.668→£0.717/kg; premiums held | R49: 2026-09
A50: mat-usibor1500 | B50: Usibor 1500 (AlSi-coated 22MnB5) | C50: Press-Hardening Steel | D50: =IF($M50>0,$M50,2) -> 2 | E50: =IF($O50>0,$O50,0.23) -> 0.23 | F50: 7850 | G50: UK | H50: =IF($M50>0,IF($L50<>1,$R50,IFERROR(INDEX('JLR Materials'!$D$2:$D$20001,MATCH($K50,'JLR Materials'!$A$2:$A$20001,0)),$R50)),$R50) -> 2026-09 | I50: =IF($M50>0,"JLR rate card — material code "&$K50,$Q50) -> UK PHS coil Jul 2026. AlSi-coated boron for hot stamping — A/B-pillar, rocker, roof rail. ~1500 MPa after press-hardening quench. Requires ~900°C furnace + water-cooled dies. Yield ~1100 MPa. | Refresh 2026-09: +£0.049/kg from 1kg crc £0.668→£0.717/kg; premiums held | J50: Low | K50: =IFERROR(INDEX(Mapping!$C$2:$C$549,MATCH($A50,Mapping!$A$2:$A$549,0)),"") | L50: =IF($K50="",0,COUNTIFS('JLR Materials'!$A$2:$A$20001,$K50,'JLR Materials'!$C$2:$C$20001,IF(Settings!$B$2="","<>",Settings!$B$2),'JLR Materials'!$D$2:$D$20001,IF(Settings!$B$4="","<>",Settings!$B$4))) -> 0 | M50: =IF($L50<>1,0,SUMIFS('JLR Materials'!$E$2:$E$20001,'JLR Materials'!$A$2:$A$20001,$K50,'JLR Materials'!$C$2:$C$20001,IF(Settings!$B$2="","<>",Settings!$B$2),'JLR Materials'!$D$2:$D$20001,IF(Settings!$B$4="","<>",Settings!$B$4))) -> 0 | N50: =IF($L50<>1,0,SUMIFS('JLR Materials'!$F$2:$F$20001,'JLR Materials'!$A$2:$A$20001,$K50,'JLR Materials'!$C$2:$C$20001,IF(Settings!$B$2="","<>",Settings!$B$2),'JLR Materials'!$D$2:$D$20001,IF(Settings!$B$4="","<>",Settings!$B$4))) -> 0 | O50: =IF($N50=0,0,IF(Settings!$B$5="percent",$M50*$N50/100,$N50)) -> 0 | P50: =IF($L50<>1,0,SUMIFS('JLR Materials'!$G$2:$G$20001,'JLR Materials'!$A$2:$A$20001,$K50,'JLR Materials'!$C$2:$C$20001,IF(Settings!$B$2="","<>",Settings!$B$2),'JLR Materials'!$D$2:$D$20001,IF(Settings!$B$4="","<>",Settings!$B$4))) -> 0 | Q50: UK PHS coil Jul 2026. AlSi-coated boron for hot stamping — A/B-pillar, rocker, roof rail. ~1500 MPa after press-hardening quench. Requires ~900°C furnace + water-cooled dies. Yield ~1100 MPa. | Refresh 2026-09: +£0.049/kg from 1kg crc £0.668→£0.717/kg; premiums held | R50: 2026-09
A51: mat-usibor2000 | B51: Usibor 2000 | C51: Press-Hardening Steel | D51: =IF($M51>0,$M51,2.4) -> 2.4 | E51: =IF($O51>0,$O51,0.22) -> 0.22 | F51: 7850 | G51: UK | H51: =IF($M51>0,IF($L51<>1,$R51,IFERROR(INDEX('JLR Materials'!$D$2:$D$20001,MATCH($K51,'JLR Materials'!$A$2:$A$20001,0)),$R51)),$R51) -> 2026-09 | I51: =IF($M51>0,"JLR rate card — material code "&$K51,$Q51) -> UK PHS coil Jul 2026. Next-gen ~2000 MPa press-hardening steel for lightweight safety cage. Highest strength hot-stamping grade. Yield ~1400 MPa. | Refresh 2026-09: +£0.049/kg from 1kg crc £0.668→£0.717/kg; premiums held | J51: Low | K51: =IFERROR(INDEX(Mapping!$C$2:$C$549,MATCH($A51,Mapping!$A$2:$A$549,0)),"") | L51: =IF($K51="",0,COUNTIFS('JLR Materials'!$A$2:$A$20001,$K51,'JLR Materials'!$C$2:$C$20001,IF(Settings!$B$2="","<>",Settings!$B$2),'JLR Materials'!$D$2:$D$20001,IF(Settings!$B$4="","<>",Settings!$B$4))) -> 0 | M51: =IF($L51<>1,0,SUMIFS('JLR Materials'!$E$2:$E$20001,'JLR Materials'!$A$2:$A$20001,$K51,'JLR Materials'!$C$2:$C$20001,IF(Settings!$B$2="","<>",Settings!$B$2),'JLR Materials'!$D$2:$D$20001,IF(Settings!$B$4="","<>",Settings!$B$4))) -> 0 | N51: =IF($L51<>1,0,SUMIFS('JLR Materials'!$F$2:$F$20001,'JLR Materials'!$A$2:$A$20001,$K51,'JLR Materials'!$C$2:$C$20001,IF(Settings!$B$2="","<>",Settings!$B$2),'JLR Materials'!$D$2:$D$20001,IF(Settings!$B$4="","<>",Settings!$B$4))) -> 0 | O51: =IF($N51=0,0,IF(Settings!$B$5="percent",$M51*$N51/100,$N51)) -> 0 | P51: =IF($L51<>1,0,SUMIFS('JLR Materials'!$G$2:$G$20001,'JLR Materials'!$A$2:$A$20001,$K51,'JLR Materials'!$C$2:$C$20001,IF(Settings!$B$2="","<>",Settings!$B$2),'JLR Materials'!$D$2:$D$20001,IF(Settings!$B$4="","<>",Settings!$B$4))) -> 0 | Q51: UK PHS coil Jul 2026. Next-gen ~2000 MPa press-hardening steel for lightweight safety cage. Highest strength hot-stamping grade. Yield ~1400 MPa. | Refresh 2026-09: +£0.049/kg from 1kg crc £0.668→£0.717/kg; premiums held | R51: 2026-09
A52: mat-ms1300 | B52: MS1300 (Martensitic) | C52: Ultra-High Strength Steel | D52: =IF($M52>0,$M52,1.67) -> 1.67 | E52: =IF($O52>0,$O52,0.23) -> 0.23 | F52: 7850 | G52: UK | H52: =IF($M52>0,IF($L52<>1,$R52,IFERROR(INDEX('JLR Materials'!$D$2:$D$20001,MATCH($K52,'JLR Materials'!$A$2:$A$20001,0)),$R52)),$R52) -> 2026-09 | I52: =IF($M52>0,"JLR rate card — material code "&$K52,$Q52) -> UK UHSS coil Jul 2026. Martensitic 1300 MPa — roll-formed reinforcements. Yield ~1050 MPa. | Refresh 2026-09: +£0.049/kg from 1kg crc £0.668→£0.717/kg; premiums held | J52: Low | K52: =IFERROR(INDEX(Mapping!$C$2:$C$549,MATCH($A52,Mapping!$A$2:$A$549,0)),"") | L52: =IF($K52="",0,COUNTIFS('JLR Materials'!$A$2:$A$20001,$K52,'JLR Materials'!$C$2:$C$20001,IF(Settings!$B$2="","<>",Settings!$B$2),'JLR Materials'!$D$2:$D$20001,IF(Settings!$B$4="","<>",Settings!$B$4))) -> 0 | M52: =IF($L52<>1,0,SUMIFS('JLR Materials'!$E$2:$E$20001,'JLR Materials'!$A$2:$A$20001,$K52,'JLR Materials'!$C$2:$C$20001,IF(Settings!$B$2="","<>",Settings!$B$2),'JLR Materials'!$D$2:$D$20001,IF(Settings!$B$4="","<>",Settings!$B$4))) -> 0 | N52: =IF($L52<>1,0,SUMIFS('JLR Materials'!$F$2:$F$20001,'JLR Materials'!$A$2:$A$20001,$K52,'JLR Materials'!$C$2:$C$20001,IF(Settings!$B$2="","<>",Settings!$B$2),'JLR Materials'!$D$2:$D$20001,IF(Settings!$B$4="","<>",Settings!$B$4))) -> 0 | O52: =IF($N52=0,0,IF(Settings!$B$5="percent",$M52*$N52/100,$N52)) -> 0 | P52: =IF($L52<>1,0,SUMIFS('JLR Materials'!$G$2:$G$20001,'JLR Materials'!$A$2:$A$20001,$K52,'JLR Materials'!$C$2:$C$20001,IF(Settings!$B$2="","<>",Settings!$B$2),'JLR Materials'!$D$2:$D$20001,IF(Settings!$B$4="","<>",Settings!$B$4))) -> 0 | Q52: UK UHSS coil Jul 2026. Martensitic 1300 MPa — roll-formed reinforcements. Yield ~1050 MPa. | Refresh 2026-09: +£0.049/kg from 1kg crc £0.668→£0.717/kg; premiums held | R52: 2026-09
A53: mat-qp980 | B53: QP980 (Quench & Partition) | C53: AHSS Sheet (3rd Gen) | D53: =IF($M53>0,$M53,1.73) -> 1.73 | E53: =IF($O53>0,$O53,0.23) -> 0.23 | F53: 7850 | G53: UK | H53: =IF($M53>0,IF($L53<>1,$R53,IFERROR(INDEX('JLR Materials'!$D$2:$D$20001,MATCH($K53,'JLR Materials'!$A$2:$A$20001,0)),$R53)),$R53) -> 2026-09 | I53: =IF($M53>0,"JLR rate card — material code "&$K53,$Q53) -> UK AHSS coil Jul 2026. 3rd-gen quench-and-partition 980 — cold-formable at 980 MPa, high elongation. Structural + formable geometry. Yield ~700 MPa. | Refresh 2026-09: +£0.049/kg from 1kg crc £0.668→£0.717/kg; premiums held | J53: Low | K53: =IFERROR(INDEX(Mapping!$C$2:$C$549,MATCH($A53,Mapping!$A$2:$A$549,0)),"") | L53: =IF($K53="",0,COUNTIFS('JLR Materials'!$A$2:$A$20001,$K53,'JLR Materials'!$C$2:$C$20001,IF(Settings!$B$2="","<>",Settings!$B$2),'JLR Materials'!$D$2:$D$20001,IF(Settings!$B$4="","<>",Settings!$B$4))) -> 0 | M53: =IF($L53<>1,0,SUMIFS('JLR Materials'!$E$2:$E$20001,'JLR Materials'!$A$2:$A$20001,$K53,'JLR Materials'!$C$2:$C$20001,IF(Settings!$B$2="","<>",Settings!$B$2),'JLR Materials'!$D$2:$D$20001,IF(Settings!$B$4="","<>",Settings!$B$4))) -> 0 | N53: =IF($L53<>1,0,SUMIFS('JLR Materials'!$F$2:$F$20001,'JLR Materials'!$A$2:$A$20001,$K53,'JLR Materials'!$C$2:$C$20001,IF(Settings!$B$2="","<>",Settings!$B$2),'JLR Materials'!$D$2:$D$20001,IF(Settings!$B$4="","<>",Settings!$B$4))) -> 0 | O53: =IF($N53=0,0,IF(Settings!$B$5="percent",$M53*$N53/100,$N53)) -> 0 | P53: =IF($L53<>1,0,SUMIFS('JLR Materials'!$G$2:$G$20001,'JLR Materials'!$A$2:$A$20001,$K53,'JLR Materials'!$C$2:$C$20001,IF(Settings!$B$2="","<>",Settings!$B$2),'JLR Materials'!$D$2:$D$20001,IF(Settings!$B$4="","<>",Settings!$B$4))) -> 0 | Q53: UK AHSS coil Jul 2026. 3rd-gen quench-and-partition 980 — cold-formable at 980 MPa, high elongation. Structural + formable geometry. Yield ~700 MPa. | Refresh 2026-09: +£0.049/kg from 1kg crc £0.668→£0.717/kg; premiums held | R53: 2026-09
A54: mat-medmn1180 | B54: Medium-Mn 1180 | C54: AHSS Sheet (3rd Gen) | D54: =IF($M54>0,$M54,1.8) -> 1.8 | E54: =IF($O54>0,$O54,0.23) -> 0.23 | F54: 7850 | G54: UK | H54: =IF($M54>0,IF($L54<>1,$R54,IFERROR(INDEX('JLR Materials'!$D$2:$D$20001,MATCH($K54,'JLR Materials'!$A$2:$A$20001,0)),$R54)),$R54) -> 2026-09 | I54: =IF($M54>0,"JLR rate card — material code "&$K54,$Q54) -> UK AHSS coil Jul 2026. 3rd-gen medium-manganese 1180 — high strength + ductility for cold-formed safety parts. Yield ~850 MPa. | Refresh 2026-09: +£0.049/kg from 1kg crc £0.668→£0.717/kg; premiums held | J54: Low | K54: =IFERROR(INDEX(Mapping!$C$2:$C$549,MATCH($A54,Mapping!$A$2:$A$549,0)),"") | L54: =IF($K54="",0,COUNTIFS('JLR Materials'!$A$2:$A$20001,$K54,'JLR Materials'!$C$2:$C$20001,IF(Settings!$B$2="","<>",Settings!$B$2),'JLR Materials'!$D$2:$D$20001,IF(Settings!$B$4="","<>",Settings!$B$4))) -> 0 | M54: =IF($L54<>1,0,SUMIFS('JLR Materials'!$E$2:$E$20001,'JLR Materials'!$A$2:$A$20001,$K54,'JLR Materials'!$C$2:$C$20001,IF(Settings!$B$2="","<>",Settings!$B$2),'JLR Materials'!$D$2:$D$20001,IF(Settings!$B$4="","<>",Settings!$B$4))) -> 0 | N54: =IF($L54<>1,0,SUMIFS('JLR Materials'!$F$2:$F$20001,'JLR Materials'!$A$2:$A$20001,$K54,'JLR Materials'!$C$2:$C$20001,IF(Settings!$B$2="","<>",Settings!$B$2),'JLR Materials'!$D$2:$D$20001,IF(Settings!$B$4="","<>",Settings!$B$4))) -> 0 | O54: =IF($N54=0,0,IF(Settings!$B$5="percent",$M54*$N54/100,$N54)) -> 0 | P54: =IF($L54<>1,0,SUMIFS('JLR Materials'!$G$2:$G$20001,'JLR Materials'!$A$2:$A$20001,$K54,'JLR Materials'!$C$2:$C$20001,IF(Settings!$B$2="","<>",Settings!$B$2),'JLR Materials'!$D$2:$D$20001,IF(Settings!$B$4="","<>",Settings!$B$4))) -> 0 | Q54: UK AHSS coil Jul 2026. 3rd-gen medium-manganese 1180 — high strength + ductility for cold-formed safety parts. Yield ~850 MPa. | Refresh 2026-09: +£0.049/kg from 1kg crc £0.668→£0.717/kg; premiums held | R54: 2026-09
A55: mat-hsla550 | B55: HSLA 550 | C55: High Strength Steel Sheet | D55: =IF($M55>0,$M55,1.39) -> 1.39 | E55: =IF($O55>0,$O55,0.23) -> 0.23 | F55: 7850 | G55: UK | H55: =IF($M55>0,IF($L55<>1,$R55,IFERROR(INDEX('JLR Materials'!$D$2:$D$20001,MATCH($K55,'JLR Materials'!$A$2:$A$20001,0)),$R55)),$R55) -> 2026-09 | I55: =IF($M55>0,"JLR rate card — material code "&$K55,$Q55) -> UK HSLA coil Jul 2026. 550 MPa min yield — chassis brackets, cross members, heavy reinforcements. Yield 550 MPa. | Refresh 2026-09: +£0.049/kg from 1kg crc £0.668→£0.717/kg; premiums held | J55: Low | K55: =IFERROR(INDEX(Mapping!$C$2:$C$549,MATCH($A55,Mapping!$A$2:$A$549,0)),"") | L55: =IF($K55="",0,COUNTIFS('JLR Materials'!$A$2:$A$20001,$K55,'JLR Materials'!$C$2:$C$20001,IF(Settings!$B$2="","<>",Settings!$B$2),'JLR Materials'!$D$2:$D$20001,IF(Settings!$B$4="","<>",Settings!$B$4))) -> 0 | M55: =IF($L55<>1,0,SUMIFS('JLR Materials'!$E$2:$E$20001,'JLR Materials'!$A$2:$A$20001,$K55,'JLR Materials'!$C$2:$C$20001,IF(Settings!$B$2="","<>",Settings!$B$2),'JLR Materials'!$D$2:$D$20001,IF(Settings!$B$4="","<>",Settings!$B$4))) -> 0 | N55: =IF($L55<>1,0,SUMIFS('JLR Materials'!$F$2:$F$20001,'JLR Materials'!$A$2:$A$20001,$K55,'JLR Materials'!$C$2:$C$20001,IF(Settings!$B$2="","<>",Settings!$B$2),'JLR Materials'!$D$2:$D$20001,IF(Settings!$B$4="","<>",Settings!$B$4))) -> 0 | O55: =IF($N55=0,0,IF(Settings!$B$5="percent",$M55*$N55/100,$N55)) -> 0 | P55: =IF($L55<>1,0,SUMIFS('JLR Materials'!$G$2:$G$20001,'JLR Materials'!$A$2:$A$20001,$K55,'JLR Materials'!$C$2:$C$20001,IF(Settings!$B$2="","<>",Settings!$B$2),'JLR Materials'!$D$2:$D$20001,IF(Settings!$B$4="","<>",Settings!$B$4))) -> 0 | Q55: UK HSLA coil Jul 2026. 550 MPa min yield — chassis brackets, cross members, heavy reinforcements. Yield 550 MPa. | Refresh 2026-09: +£0.049/kg from 1kg crc £0.668→£0.717/kg; premiums held | R55: 2026-09
A56: mat-bh260 | B56: BH260 (Bake-Hardening) | C56: Bake-Hardening Steel Sheet | D56: =IF($M56>0,$M56,1.1) -> 1.1 | E56: =IF($O56>0,$O56,0.22) -> 0.22 | F56: 7850 | G56: UK | H56: =IF($M56>0,IF($L56<>1,$R56,IFERROR(INDEX('JLR Materials'!$D$2:$D$20001,MATCH($K56,'JLR Materials'!$A$2:$A$20001,0)),$R56)),$R56) -> 2026-09 | I56: =IF($M56>0,"JLR rate card — material code "&$K56,$Q56) -> UK BH coil Jul 2026. Bake-hardening +260 — outer body panels; formable when stamped, gains strength & dent resistance after paint-bake. Yield ~180 MPa (pre-bake). | Refresh 2026-09: +£0.049/kg from 1kg crc £0.668→£0.717/kg; premiums held | J56: Low | K56: =IFERROR(INDEX(Mapping!$C$2:$C$549,MATCH($A56,Mapping!$A$2:$A$549,0)),"") | L56: =IF($K56="",0,COUNTIFS('JLR Materials'!$A$2:$A$20001,$K56,'JLR Materials'!$C$2:$C$20001,IF(Settings!$B$2="","<>",Settings!$B$2),'JLR Materials'!$D$2:$D$20001,IF(Settings!$B$4="","<>",Settings!$B$4))) -> 0 | M56: =IF($L56<>1,0,SUMIFS('JLR Materials'!$E$2:$E$20001,'JLR Materials'!$A$2:$A$20001,$K56,'JLR Materials'!$C$2:$C$20001,IF(Settings!$B$2="","<>",Settings!$B$2),'JLR Materials'!$D$2:$D$20001,IF(Settings!$B$4="","<>",Settings!$B$4))) -> 0 | N56: =IF($L56<>1,0,SUMIFS('JLR Materials'!$F$2:$F$20001,'JLR Materials'!$A$2:$A$20001,$K56,'JLR Materials'!$C$2:$C$20001,IF(Settings!$B$2="","<>",Settings!$B$2),'JLR Materials'!$D$2:$D$20001,IF(Settings!$B$4="","<>",Settings!$B$4))) -> 0 | O56: =IF($N56=0,0,IF(Settings!$B$5="percent",$M56*$N56/100,$N56)) -> 0 | P56: =IF($L56<>1,0,SUMIFS('JLR Materials'!$G$2:$G$20001,'JLR Materials'!$A$2:$A$20001,$K56,'JLR Materials'!$C$2:$C$20001,IF(Settings!$B$2="","<>",Settings!$B$2),'JLR Materials'!$D$2:$D$20001,IF(Settings!$B$4="","<>",Settings!$B$4))) -> 0 | Q56: UK BH coil Jul 2026. Bake-hardening +260 — outer body panels; formable when stamped, gains strength & dent resistance after paint-bake. Yield ~180 MPa (pre-bake). | Refresh 2026-09: +£0.049/kg from 1kg crc £0.668→£0.717/kg; premiums held | R56: 2026-09
A57: mat-if-dx56 | B57: DX56D IF (Interstitial-Free) | C57: IF Steel Sheet | D57: =IF($M57>0,$M57,1) -> 1 | E57: =IF($O57>0,$O57,0.21) -> 0.21 | F57: 7850 | G57: UK | H57: =IF($M57>0,IF($L57<>1,$R57,IFERROR(INDEX('JLR Materials'!$D$2:$D$20001,MATCH($K57,'JLR Materials'!$A$2:$A$20001,0)),$R57)),$R57) -> 2026-09 | I57: =IF($M57>0,"JLR rate card — material code "&$K57,$Q57) -> UK IF coil Jul 2026. Ultra-formable interstitial-free — deep-drawn complex outer/inner panels (fenders, doors). Highest r-value/drawability. Yield ~140 MPa. | Refresh 2026-09: +£0.049/kg from 1kg crc £0.668→£0.717/kg; premiums held | J57: Low | K57: =IFERROR(INDEX(Mapping!$C$2:$C$549,MATCH($A57,Mapping!$A$2:$A$549,0)),"") | L57: =IF($K57="",0,COUNTIFS('JLR Materials'!$A$2:$A$20001,$K57,'JLR Materials'!$C$2:$C$20001,IF(Settings!$B$2="","<>",Settings!$B$2),'JLR Materials'!$D$2:$D$20001,IF(Settings!$B$4="","<>",Settings!$B$4))) -> 0 | M57: =IF($L57<>1,0,SUMIFS('JLR Materials'!$E$2:$E$20001,'JLR Materials'!$A$2:$A$20001,$K57,'JLR Materials'!$C$2:$C$20001,IF(Settings!$B$2="","<>",Settings!$B$2),'JLR Materials'!$D$2:$D$20001,IF(Settings!$B$4="","<>",Settings!$B$4))) -> 0 | N57: =IF($L57<>1,0,SUMIFS('JLR Materials'!$F$2:$F$20001,'JLR Materials'!$A$2:$A$20001,$K57,'JLR Materials'!$C$2:$C$20001,IF(Settings!$B$2="","<>",Settings!$B$2),'JLR Materials'!$D$2:$D$20001,IF(Settings!$B$4="","<>",Settings!$B$4))) -> 0 | O57: =IF($N57=0,0,IF(Settings!$B$5="percent",$M57*$N57/100,$N57)) -> 0 | P57: =IF($L57<>1,0,SUMIFS('JLR Materials'!$G$2:$G$20001,'JLR Materials'!$A$2:$A$20001,$K57,'JLR Materials'!$C$2:$C$20001,IF(Settings!$B$2="","<>",Settings!$B$2),'JLR Materials'!$D$2:$D$20001,IF(Settings!$B$4="","<>",Settings!$B$4))) -> 0 | Q57: UK IF coil Jul 2026. Ultra-formable interstitial-free — deep-drawn complex outer/inner panels (fenders, doors). Highest r-value/drawability. Yield ~140 MPa. | Refresh 2026-09: +£0.049/kg from 1kg crc £0.668→£0.717/kg; premiums held | R57: 2026-09
A58: mat-if-hs260 | B58: IF-HS 260 (High-Strength IF) | C58: IF Steel Sheet | D58: =IF($M58>0,$M58,1.13) -> 1.13 | E58: =IF($O58>0,$O58,0.22) -> 0.22 | F58: 7850 | G58: UK | H58: =IF($M58>0,IF($L58<>1,$R58,IFERROR(INDEX('JLR Materials'!$D$2:$D$20001,MATCH($K58,'JLR Materials'!$A$2:$A$20001,0)),$R58)),$R58) -> 2026-09 | I58: =IF($M58>0,"JLR rate card — material code "&$K58,$Q58) -> UK IF-HS coil Jul 2026. High-strength interstitial-free 260 — formable structural panels needing more strength than plain IF. Yield 260 MPa. | Refresh 2026-09: +£0.049/kg from 1kg crc £0.668→£0.717/kg; premiums held | J58: Low | K58: =IFERROR(INDEX(Mapping!$C$2:$C$549,MATCH($A58,Mapping!$A$2:$A$549,0)),"") | L58: =IF($K58="",0,COUNTIFS('JLR Materials'!$A$2:$A$20001,$K58,'JLR Materials'!$C$2:$C$20001,IF(Settings!$B$2="","<>",Settings!$B$2),'JLR Materials'!$D$2:$D$20001,IF(Settings!$B$4="","<>",Settings!$B$4))) -> 0 | M58: =IF($L58<>1,0,SUMIFS('JLR Materials'!$E$2:$E$20001,'JLR Materials'!$A$2:$A$20001,$K58,'JLR Materials'!$C$2:$C$20001,IF(Settings!$B$2="","<>",Settings!$B$2),'JLR Materials'!$D$2:$D$20001,IF(Settings!$B$4="","<>",Settings!$B$4))) -> 0 | N58: =IF($L58<>1,0,SUMIFS('JLR Materials'!$F$2:$F$20001,'JLR Materials'!$A$2:$A$20001,$K58,'JLR Materials'!$C$2:$C$20001,IF(Settings!$B$2="","<>",Settings!$B$2),'JLR Materials'!$D$2:$D$20001,IF(Settings!$B$4="","<>",Settings!$B$4))) -> 0 | O58: =IF($N58=0,0,IF(Settings!$B$5="percent",$M58*$N58/100,$N58)) -> 0 | P58: =IF($L58<>1,0,SUMIFS('JLR Materials'!$G$2:$G$20001,'JLR Materials'!$A$2:$A$20001,$K58,'JLR Materials'!$C$2:$C$20001,IF(Settings!$B$2="","<>",Settings!$B$2),'JLR Materials'!$D$2:$D$20001,IF(Settings!$B$4="","<>",Settings!$B$4))) -> 0 | Q58: UK IF-HS coil Jul 2026. High-strength interstitial-free 260 — formable structural panels needing more strength than plain IF. Yield 260 MPa. | Refresh 2026-09: +£0.049/kg from 1kg crc £0.668→£0.717/kg; premiums held | R58: 2026-09
A59: mat-dc04 | B59: DC04 (CR4 Deep-Drawing) | C59: Mild Steel Sheet | D59: =IF($M59>0,$M59,0.77) -> 0.77 | E59: =IF($O59>0,$O59,0.2) -> 0.2 | F59: 7850 | G59: UK | H59: =IF($M59>0,IF($L59<>1,$R59,IFERROR(INDEX('JLR Materials'!$D$2:$D$20001,MATCH($K59,'JLR Materials'!$A$2:$A$20001,0)),$R59)),$R59) -> 2026-09 | I59: =IF($M59>0,"JLR rate card — material code "&$K59,$Q59) -> UK CR coil Jul 2026. Deep-drawing quality — enclosures, brackets, moderate draws. Better r-value than DC01. | Refresh 2026-09: +£0.049/kg from 1kg crc £0.668→£0.717/kg; premiums held | J59: Medium | K59: =IFERROR(INDEX(Mapping!$C$2:$C$549,MATCH($A59,Mapping!$A$2:$A$549,0)),"") | L59: =IF($K59="",0,COUNTIFS('JLR Materials'!$A$2:$A$20001,$K59,'JLR Materials'!$C$2:$C$20001,IF(Settings!$B$2="","<>",Settings!$B$2),'JLR Materials'!$D$2:$D$20001,IF(Settings!$B$4="","<>",Settings!$B$4))) -> 0 | M59: =IF($L59<>1,0,SUMIFS('JLR Materials'!$E$2:$E$20001,'JLR Materials'!$A$2:$A$20001,$K59,'JLR Materials'!$C$2:$C$20001,IF(Settings!$B$2="","<>",Settings!$B$2),'JLR Materials'!$D$2:$D$20001,IF(Settings!$B$4="","<>",Settings!$B$4))) -> 0 | N59: =IF($L59<>1,0,SUMIFS('JLR Materials'!$F$2:$F$20001,'JLR Materials'!$A$2:$A$20001,$K59,'JLR Materials'!$C$2:$C$20001,IF(Settings!$B$2="","<>",Settings!$B$2),'JLR Materials'!$D$2:$D$20001,IF(Settings!$B$4="","<>",Settings!$B$4))) -> 0 | O59: =IF($N59=0,0,IF(Settings!$B$5="percent",$M59*$N59/100,$N59)) -> 0 | P59: =IF($L59<>1,0,SUMIFS('JLR Materials'!$G$2:$G$20001,'JLR Materials'!$A$2:$A$20001,$K59,'JLR Materials'!$C$2:$C$20001,IF(Settings!$B$2="","<>",Settings!$B$2),'JLR Materials'!$D$2:$D$20001,IF(Settings!$B$4="","<>",Settings!$B$4))) -> 0 | Q59: UK CR coil Jul 2026. Deep-drawing quality — enclosures, brackets, moderate draws. Better r-value than DC01. | Refresh 2026-09: +£0.049/kg from 1kg crc £0.668→£0.717/kg; premiums held | R59: 2026-09
A60: mat-dc05 | B60: DC05 (Extra-Deep-Drawing) | C60: Mild Steel Sheet | D60: =IF($M60>0,$M60,0.8) -> 0.8 | E60: =IF($O60>0,$O60,0.2) -> 0.2 | F60: 7850 | G60: UK | H60: =IF($M60>0,IF($L60<>1,$R60,IFERROR(INDEX('JLR Materials'!$D$2:$D$20001,MATCH($K60,'JLR Materials'!$A$2:$A$20001,0)),$R60)),$R60) -> 2026-09 | I60: =IF($M60>0,"JLR rate card — material code "&$K60,$Q60) -> UK CR coil Jul 2026. Extra-deep-drawing — sinks, housings, deeper draws without splits. | Refresh 2026-09: +£0.049/kg from 1kg crc £0.668→£0.717/kg; premiums held | J60: Low | K60: =IFERROR(INDEX(Mapping!$C$2:$C$549,MATCH($A60,Mapping!$A$2:$A$549,0)),"") | L60: =IF($K60="",0,COUNTIFS('JLR Materials'!$A$2:$A$20001,$K60,'JLR Materials'!$C$2:$C$20001,IF(Settings!$B$2="","<>",Settings!$B$2),'JLR Materials'!$D$2:$D$20001,IF(Settings!$B$4="","<>",Settings!$B$4))) -> 0 | M60: =IF($L60<>1,0,SUMIFS('JLR Materials'!$E$2:$E$20001,'JLR Materials'!$A$2:$A$20001,$K60,'JLR Materials'!$C$2:$C$20001,IF(Settings!$B$2="","<>",Settings!$B$2),'JLR Materials'!$D$2:$D$20001,IF(Settings!$B$4="","<>",Settings!$B$4))) -> 0 | N60: =IF($L60<>1,0,SUMIFS('JLR Materials'!$F$2:$F$20001,'JLR Materials'!$A$2:$A$20001,$K60,'JLR Materials'!$C$2:$C$20001,IF(Settings!$B$2="","<>",Settings!$B$2),'JLR Materials'!$D$2:$D$20001,IF(Settings!$B$4="","<>",Settings!$B$4))) -> 0 | O60: =IF($N60=0,0,IF(Settings!$B$5="percent",$M60*$N60/100,$N60)) -> 0 | P60: =IF($L60<>1,0,SUMIFS('JLR Materials'!$G$2:$G$20001,'JLR Materials'!$A$2:$A$20001,$K60,'JLR Materials'!$C$2:$C$20001,IF(Settings!$B$2="","<>",Settings!$B$2),'JLR Materials'!$D$2:$D$20001,IF(Settings!$B$4="","<>",Settings!$B$4))) -> 0 | Q60: UK CR coil Jul 2026. Extra-deep-drawing — sinks, housings, deeper draws without splits. | Refresh 2026-09: +£0.049/kg from 1kg crc £0.668→£0.717/kg; premiums held | R60: 2026-09
A61: mat-dc06 | B61: DC06 (Super-Deep-Drawing IF) | C61: Mild Steel Sheet | D61: =IF($M61>0,$M61,0.85) -> 0.85 | E61: =IF($O61>0,$O61,0.2) -> 0.2 | F61: 7850 | G61: UK | H61: =IF($M61>0,IF($L61<>1,$R61,IFERROR(INDEX('JLR Materials'!$D$2:$D$20001,MATCH($K61,'JLR Materials'!$A$2:$A$20001,0)),$R61)),$R61) -> 2026-09 | I61: =IF($M61>0,"JLR rate card — material code "&$K61,$Q61) -> UK CR/IF coil Jul 2026. Super-deep-drawing IF grade — complex deep pressings, fuel-filler pockets, tanks. Highest formability CR grade. | Refresh 2026-09: +£0.049/kg from 1kg crc £0.668→£0.717/kg; premiums held | J61: Low | K61: =IFERROR(INDEX(Mapping!$C$2:$C$549,MATCH($A61,Mapping!$A$2:$A$549,0)),"") | L61: =IF($K61="",0,COUNTIFS('JLR Materials'!$A$2:$A$20001,$K61,'JLR Materials'!$C$2:$C$20001,IF(Settings!$B$2="","<>",Settings!$B$2),'JLR Materials'!$D$2:$D$20001,IF(Settings!$B$4="","<>",Settings!$B$4))) -> 0 | M61: =IF($L61<>1,0,SUMIFS('JLR Materials'!$E$2:$E$20001,'JLR Materials'!$A$2:$A$20001,$K61,'JLR Materials'!$C$2:$C$20001,IF(Settings!$B$2="","<>",Settings!$B$2),'JLR Materials'!$D$2:$D$20001,IF(Settings!$B$4="","<>",Settings!$B$4))) -> 0 | N61: =IF($L61<>1,0,SUMIFS('JLR Materials'!$F$2:$F$20001,'JLR Materials'!$A$2:$A$20001,$K61,'JLR Materials'!$C$2:$C$20001,IF(Settings!$B$2="","<>",Settings!$B$2),'JLR Materials'!$D$2:$D$20001,IF(Settings!$B$4="","<>",Settings!$B$4))) -> 0 | O61: =IF($N61=0,0,IF(Settings!$B$5="percent",$M61*$N61/100,$N61)) -> 0 | P61: =IF($L61<>1,0,SUMIFS('JLR Materials'!$G$2:$G$20001,'JLR Materials'!$A$2:$A$20001,$K61,'JLR Materials'!$C$2:$C$20001,IF(Settings!$B$2="","<>",Settings!$B$2),'JLR Materials'!$D$2:$D$20001,IF(Settings!$B$4="","<>",Settings!$B$4))) -> 0 | Q61: UK CR/IF coil Jul 2026. Super-deep-drawing IF grade — complex deep pressings, fuel-filler pockets, tanks. Highest formability CR grade. | Refresh 2026-09: +£0.049/kg from 1kg crc £0.668→£0.717/kg; premiums held | R61: 2026-09
A62: mat-nogo-m270-35a | B62: M270-35A Non-Oriented Electrical (0.35mm) | C62: Electrical Steel Sheet | D62: =IF($M62>0,$M62,1.59) -> 1.59 | E62: =IF($O62>0,$O62,0.26) -> 0.26 | F62: 7650 | G62: UK | H62: =IF($M62>0,IF($L62<>1,$R62,IFERROR(INDEX('JLR Materials'!$D$2:$D$20001,MATCH($K62,'JLR Materials'!$A$2:$A$20001,0)),$R62)),$R62) -> 2026-09 | I62: =IF($M62>0,"JLR rate card — material code "&$K62,$Q62) -> UK electrical steel Jul 2026. Low-loss non-oriented Si-steel — EV/industrial motor + generator laminations; thin gauge, low core loss (~2.7 W/kg @1.5T/50Hz). Blanked/notched at high SPM. | Refresh 2026-09: +£0.041/kg from 1kg crno £0.612→£0.653/kg; premiums held | J62: Low | K62: =IFERROR(INDEX(Mapping!$C$2:$C$549,MATCH($A62,Mapping!$A$2:$A$549,0)),"") | L62: =IF($K62="",0,COUNTIFS('JLR Materials'!$A$2:$A$20001,$K62,'JLR Materials'!$C$2:$C$20001,IF(Settings!$B$2="","<>",Settings!$B$2),'JLR Materials'!$D$2:$D$20001,IF(Settings!$B$4="","<>",Settings!$B$4))) -> 0 | M62: =IF($L62<>1,0,SUMIFS('JLR Materials'!$E$2:$E$20001,'JLR Materials'!$A$2:$A$20001,$K62,'JLR Materials'!$C$2:$C$20001,IF(Settings!$B$2="","<>",Settings!$B$2),'JLR Materials'!$D$2:$D$20001,IF(Settings!$B$4="","<>",Settings!$B$4))) -> 0 | N62: =IF($L62<>1,0,SUMIFS('JLR Materials'!$F$2:$F$20001,'JLR Materials'!$A$2:$A$20001,$K62,'JLR Materials'!$C$2:$C$20001,IF(Settings!$B$2="","<>",Settings!$B$2),'JLR Materials'!$D$2:$D$20001,IF(Settings!$B$4="","<>",Settings!$B$4))) -> 0 | O62: =IF($N62=0,0,IF(Settings!$B$5="percent",$M62*$N62/100,$N62)) -> 0 | P62: =IF($L62<>1,0,SUMIFS('JLR Materials'!$G$2:$G$20001,'JLR Materials'!$A$2:$A$20001,$K62,'JLR Materials'!$C$2:$C$20001,IF(Settings!$B$2="","<>",Settings!$B$2),'JLR Materials'!$D$2:$D$20001,IF(Settings!$B$4="","<>",Settings!$B$4))) -> 0 | Q62: UK electrical steel Jul 2026. Low-loss non-oriented Si-steel — EV/industrial motor + generator laminations; thin gauge, low core loss (~2.7 W/kg @1.5T/50Hz). Blanked/notched at high SPM. | Refresh 2026-09: +£0.041/kg from 1kg crno £0.612→£0.653/kg; premiums held | R62: 2026-09
A63: mat-nogo-m400-50a | B63: M400-50A Non-Oriented Electrical (0.50mm) | C63: Electrical Steel Sheet | D63: =IF($M63>0,$M63,1.29) -> 1.29 | E63: =IF($O63>0,$O63,0.26) -> 0.26 | F63: 7700 | G63: UK | H63: =IF($M63>0,IF($L63<>1,$R63,IFERROR(INDEX('JLR Materials'!$D$2:$D$20001,MATCH($K63,'JLR Materials'!$A$2:$A$20001,0)),$R63)),$R63) -> 2026-09 | I63: =IF($M63>0,"JLR rate card — material code "&$K63,$Q63) -> UK electrical steel Jul 2026. General non-oriented Si-steel — appliance/industrial motors, pumps; 0.50mm, moderate loss. Cost-effective lamination grade. | Refresh 2026-09: +£0.041/kg from 1kg crno £0.612→£0.653/kg; premiums held | J63: Low | K63: =IFERROR(INDEX(Mapping!$C$2:$C$549,MATCH($A63,Mapping!$A$2:$A$549,0)),"") | L63: =IF($K63="",0,COUNTIFS('JLR Materials'!$A$2:$A$20001,$K63,'JLR Materials'!$C$2:$C$20001,IF(Settings!$B$2="","<>",Settings!$B$2),'JLR Materials'!$D$2:$D$20001,IF(Settings!$B$4="","<>",Settings!$B$4))) -> 0 | M63: =IF($L63<>1,0,SUMIFS('JLR Materials'!$E$2:$E$20001,'JLR Materials'!$A$2:$A$20001,$K63,'JLR Materials'!$C$2:$C$20001,IF(Settings!$B$2="","<>",Settings!$B$2),'JLR Materials'!$D$2:$D$20001,IF(Settings!$B$4="","<>",Settings!$B$4))) -> 0 | N63: =IF($L63<>1,0,SUMIFS('JLR Materials'!$F$2:$F$20001,'JLR Materials'!$A$2:$A$20001,$K63,'JLR Materials'!$C$2:$C$20001,IF(Settings!$B$2="","<>",Settings!$B$2),'JLR Materials'!$D$2:$D$20001,IF(Settings!$B$4="","<>",Settings!$B$4))) -> 0 | O63: =IF($N63=0,0,IF(Settings!$B$5="percent",$M63*$N63/100,$N63)) -> 0 | P63: =IF($L63<>1,0,SUMIFS('JLR Materials'!$G$2:$G$20001,'JLR Materials'!$A$2:$A$20001,$K63,'JLR Materials'!$C$2:$C$20001,IF(Settings!$B$2="","<>",Settings!$B$2),'JLR Materials'!$D$2:$D$20001,IF(Settings!$B$4="","<>",Settings!$B$4))) -> 0 | Q63: UK electrical steel Jul 2026. General non-oriented Si-steel — appliance/industrial motors, pumps; 0.50mm, moderate loss. Cost-effective lamination grade. | Refresh 2026-09: +£0.041/kg from 1kg crno £0.612→£0.653/kg; premiums held | R63: 2026-09
A64: mat-go-m105-30p | B64: M105-30P Grain-Oriented Electrical (0.30mm) | C64: Electrical Steel Sheet | D64: =IF($M64>0,$M64,2.9) -> 2.9 | E64: =IF($O64>0,$O64,0.3) -> 0.3 | F64: 7650 | G64: UK | H64: =IF($M64>0,IF($L64<>1,$R64,IFERROR(INDEX('JLR Materials'!$D$2:$D$20001,MATCH($K64,'JLR Materials'!$A$2:$A$20001,0)),$R64)),$R64) -> 2026-09 | I64: =IF($M64>0,"JLR rate card — material code "&$K64,$Q64) -> UK electrical steel Jul 2026. High-permeability grain-oriented Si-steel — transformer cores (E/I laminations, wound cores); very low loss along rolling direction. Premium over NO. | Refresh 2026-09: SPECIALTY — no public market index for this grade; held at the June 2026 price — refresh by supplier quote | J64: Low | K64: =IFERROR(INDEX(Mapping!$C$2:$C$549,MATCH($A64,Mapping!$A$2:$A$549,0)),"") | L64: =IF($K64="",0,COUNTIFS('JLR Materials'!$A$2:$A$20001,$K64,'JLR Materials'!$C$2:$C$20001,IF(Settings!$B$2="","<>",Settings!$B$2),'JLR Materials'!$D$2:$D$20001,IF(Settings!$B$4="","<>",Settings!$B$4))) -> 0 | M64: =IF($L64<>1,0,SUMIFS('JLR Materials'!$E$2:$E$20001,'JLR Materials'!$A$2:$A$20001,$K64,'JLR Materials'!$C$2:$C$20001,IF(Settings!$B$2="","<>",Settings!$B$2),'JLR Materials'!$D$2:$D$20001,IF(Settings!$B$4="","<>",Settings!$B$4))) -> 0 | N64: =IF($L64<>1,0,SUMIFS('JLR Materials'!$F$2:$F$20001,'JLR Materials'!$A$2:$A$20001,$K64,'JLR Materials'!$C$2:$C$20001,IF(Settings!$B$2="","<>",Settings!$B$2),'JLR Materials'!$D$2:$D$20001,IF(Settings!$B$4="","<>",Settings!$B$4))) -> 0 | O64: =IF($N64=0,0,IF(Settings!$B$5="percent",$M64*$N64/100,$N64)) -> 0 | P64: =IF($L64<>1,0,SUMIFS('JLR Materials'!$G$2:$G$20001,'JLR Materials'!$A$2:$A$20001,$K64,'JLR Materials'!$C$2:$C$20001,IF(Settings!$B$2="","<>",Settings!$B$2),'JLR Materials'!$D$2:$D$20001,IF(Settings!$B$4="","<>",Settings!$B$4))) -> 0 | Q64: UK electrical steel Jul 2026. High-permeability grain-oriented Si-steel — transformer cores (E/I laminations, wound cores); very low loss along rolling direction. Premium over NO. | Refresh 2026-09: SPECIALTY — no public market index for this grade; held at the June 2026 price — refresh by supplier quote | R64: 2026-09
A65: mat-m235-35a | B65: M235-35A NO Electrical (0.35mm, premium low-loss) | C65: Electrical Steel Sheet | D65: =IF($M65>0,$M65,1.99) -> 1.99 | E65: =IF($O65>0,$O65,0.26) -> 0.26 | F65: 7650 | G65: UK | H65: =IF($M65>0,IF($L65<>1,$R65,IFERROR(INDEX('JLR Materials'!$D$2:$D$20001,MATCH($K65,'JLR Materials'!$A$2:$A$20001,0)),$R65)),$R65) -> 2026-09 | I65: =IF($M65>0,"JLR rate card — material code "&$K65,$Q65) -> UK electrical steel Jul 2026. Premium low-loss NO — high-efficiency EV/industrial traction motors; ~2.35 W/kg @1.5T/50Hz. High-Si, thin gauge. | Refresh 2026-09: +£0.041/kg from 1kg crno £0.612→£0.653/kg; premiums held | J65: Low | K65: =IFERROR(INDEX(Mapping!$C$2:$C$549,MATCH($A65,Mapping!$A$2:$A$549,0)),"") | L65: =IF($K65="",0,COUNTIFS('JLR Materials'!$A$2:$A$20001,$K65,'JLR Materials'!$C$2:$C$20001,IF(Settings!$B$2="","<>",Settings!$B$2),'JLR Materials'!$D$2:$D$20001,IF(Settings!$B$4="","<>",Settings!$B$4))) -> 0 | M65: =IF($L65<>1,0,SUMIFS('JLR Materials'!$E$2:$E$20001,'JLR Materials'!$A$2:$A$20001,$K65,'JLR Materials'!$C$2:$C$20001,IF(Settings!$B$2="","<>",Settings!$B$2),'JLR Materials'!$D$2:$D$20001,IF(Settings!$B$4="","<>",Settings!$B$4))) -> 0 | N65: =IF($L65<>1,0,SUMIFS('JLR Materials'!$F$2:$F$20001,'JLR Materials'!$A$2:$A$20001,$K65,'JLR Materials'!$C$2:$C$20001,IF(Settings!$B$2="","<>",Settings!$B$2),'JLR Materials'!$D$2:$D$20001,IF(Settings!$B$4="","<>",Settings!$B$4))) -> 0 | O65: =IF($N65=0,0,IF(Settings!$B$5="percent",$M65*$N65/100,$N65)) -> 0 | P65: =IF($L65<>1,0,SUMIFS('JLR Materials'!$G$2:$G$20001,'JLR Materials'!$A$2:$A$20001,$K65,'JLR Materials'!$C$2:$C$20001,IF(Settings!$B$2="","<>",Settings!$B$2),'JLR Materials'!$D$2:$D$20001,IF(Settings!$B$4="","<>",Settings!$B$4))) -> 0 | Q65: UK electrical steel Jul 2026. Premium low-loss NO — high-efficiency EV/industrial traction motors; ~2.35 W/kg @1.5T/50Hz. High-Si, thin gauge. | Refresh 2026-09: +£0.041/kg from 1kg crno £0.612→£0.653/kg; premiums held | R65: 2026-09
A66: mat-m330-35a | B66: M330-35A NO Electrical (0.35mm) | C66: Electrical Steel Sheet | D66: =IF($M66>0,$M66,1.74) -> 1.74 | E66: =IF($O66>0,$O66,0.26) -> 0.26 | F66: 7650 | G66: UK | H66: =IF($M66>0,IF($L66<>1,$R66,IFERROR(INDEX('JLR Materials'!$D$2:$D$20001,MATCH($K66,'JLR Materials'!$A$2:$A$20001,0)),$R66)),$R66) -> 2026-09 | I66: =IF($M66>0,"JLR rate card — material code "&$K66,$Q66) -> UK electrical steel Jul 2026. Mid-grade 0.35mm NO — general traction/servo motors; good loss/cost balance. | Refresh 2026-09: +£0.041/kg from 1kg crno £0.612→£0.653/kg; premiums held | J66: Low | K66: =IFERROR(INDEX(Mapping!$C$2:$C$549,MATCH($A66,Mapping!$A$2:$A$549,0)),"") | L66: =IF($K66="",0,COUNTIFS('JLR Materials'!$A$2:$A$20001,$K66,'JLR Materials'!$C$2:$C$20001,IF(Settings!$B$2="","<>",Settings!$B$2),'JLR Materials'!$D$2:$D$20001,IF(Settings!$B$4="","<>",Settings!$B$4))) -> 0 | M66: =IF($L66<>1,0,SUMIFS('JLR Materials'!$E$2:$E$20001,'JLR Materials'!$A$2:$A$20001,$K66,'JLR Materials'!$C$2:$C$20001,IF(Settings!$B$2="","<>",Settings!$B$2),'JLR Materials'!$D$2:$D$20001,IF(Settings!$B$4="","<>",Settings!$B$4))) -> 0 | N66: =IF($L66<>1,0,SUMIFS('JLR Materials'!$F$2:$F$20001,'JLR Materials'!$A$2:$A$20001,$K66,'JLR Materials'!$C$2:$C$20001,IF(Settings!$B$2="","<>",Settings!$B$2),'JLR Materials'!$D$2:$D$20001,IF(Settings!$B$4="","<>",Settings!$B$4))) -> 0 | O66: =IF($N66=0,0,IF(Settings!$B$5="percent",$M66*$N66/100,$N66)) -> 0 | P66: =IF($L66<>1,0,SUMIFS('JLR Materials'!$G$2:$G$20001,'JLR Materials'!$A$2:$A$20001,$K66,'JLR Materials'!$C$2:$C$20001,IF(Settings!$B$2="","<>",Settings!$B$2),'JLR Materials'!$D$2:$D$20001,IF(Settings!$B$4="","<>",Settings!$B$4))) -> 0 | Q66: UK electrical steel Jul 2026. Mid-grade 0.35mm NO — general traction/servo motors; good loss/cost balance. | Refresh 2026-09: +£0.041/kg from 1kg crno £0.612→£0.653/kg; premiums held | R66: 2026-09
A67: mat-m250-50a | B67: M250-50A NO Electrical (0.50mm, low-loss) | C67: Electrical Steel Sheet | D67: =IF($M67>0,$M67,1.46) -> 1.46 | E67: =IF($O67>0,$O67,0.26) -> 0.26 | F67: 7650 | G67: UK | H67: =IF($M67>0,IF($L67<>1,$R67,IFERROR(INDEX('JLR Materials'!$D$2:$D$20001,MATCH($K67,'JLR Materials'!$A$2:$A$20001,0)),$R67)),$R67) -> 2026-09 | I67: =IF($M67>0,"JLR rate card — material code "&$K67,$Q67) -> UK electrical steel Jul 2026. Low-loss 0.50mm NO — efficient industrial motors, generators. | Refresh 2026-09: +£0.041/kg from 1kg crno £0.612→£0.653/kg; premiums held | J67: Low | K67: =IFERROR(INDEX(Mapping!$C$2:$C$549,MATCH($A67,Mapping!$A$2:$A$549,0)),"") | L67: =IF($K67="",0,COUNTIFS('JLR Materials'!$A$2:$A$20001,$K67,'JLR Materials'!$C$2:$C$20001,IF(Settings!$B$2="","<>",Settings!$B$2),'JLR Materials'!$D$2:$D$20001,IF(Settings!$B$4="","<>",Settings!$B$4))) -> 0 | M67: =IF($L67<>1,0,SUMIFS('JLR Materials'!$E$2:$E$20001,'JLR Materials'!$A$2:$A$20001,$K67,'JLR Materials'!$C$2:$C$20001,IF(Settings!$B$2="","<>",Settings!$B$2),'JLR Materials'!$D$2:$D$20001,IF(Settings!$B$4="","<>",Settings!$B$4))) -> 0 | N67: =IF($L67<>1,0,SUMIFS('JLR Materials'!$F$2:$F$20001,'JLR Materials'!$A$2:$A$20001,$K67,'JLR Materials'!$C$2:$C$20001,IF(Settings!$B$2="","<>",Settings!$B$2),'JLR Materials'!$D$2:$D$20001,IF(Settings!$B$4="","<>",Settings!$B$4))) -> 0 | O67: =IF($N67=0,0,IF(Settings!$B$5="percent",$M67*$N67/100,$N67)) -> 0 | P67: =IF($L67<>1,0,SUMIFS('JLR Materials'!$G$2:$G$20001,'JLR Materials'!$A$2:$A$20001,$K67,'JLR Materials'!$C$2:$C$20001,IF(Settings!$B$2="","<>",Settings!$B$2),'JLR Materials'!$D$2:$D$20001,IF(Settings!$B$4="","<>",Settings!$B$4))) -> 0 | Q67: UK electrical steel Jul 2026. Low-loss 0.50mm NO — efficient industrial motors, generators. | Refresh 2026-09: +£0.041/kg from 1kg crno £0.612→£0.653/kg; premiums held | R67: 2026-09
A68: mat-m470-50a | B68: M470-50A NO Electrical (0.50mm) | C68: Electrical Steel Sheet | D68: =IF($M68>0,$M68,1.24) -> 1.24 | E68: =IF($O68>0,$O68,0.26) -> 0.26 | F68: 7700 | G68: UK | H68: =IF($M68>0,IF($L68<>1,$R68,IFERROR(INDEX('JLR Materials'!$D$2:$D$20001,MATCH($K68,'JLR Materials'!$A$2:$A$20001,0)),$R68)),$R68) -> 2026-09 | I68: =IF($M68>0,"JLR rate card — material code "&$K68,$Q68) -> UK electrical steel Jul 2026. Standard 0.50mm NO — mains-frequency industrial motors, pumps. Workhorse economy grade. | Refresh 2026-09: +£0.041/kg from 1kg crno £0.612→£0.653/kg; premiums held | J68: Medium | K68: =IFERROR(INDEX(Mapping!$C$2:$C$549,MATCH($A68,Mapping!$A$2:$A$549,0)),"") | L68: =IF($K68="",0,COUNTIFS('JLR Materials'!$A$2:$A$20001,$K68,'JLR Materials'!$C$2:$C$20001,IF(Settings!$B$2="","<>",Settings!$B$2),'JLR Materials'!$D$2:$D$20001,IF(Settings!$B$4="","<>",Settings!$B$4))) -> 0 | M68: =IF($L68<>1,0,SUMIFS('JLR Materials'!$E$2:$E$20001,'JLR Materials'!$A$2:$A$20001,$K68,'JLR Materials'!$C$2:$C$20001,IF(Settings!$B$2="","<>",Settings!$B$2),'JLR Materials'!$D$2:$D$20001,IF(Settings!$B$4="","<>",Settings!$B$4))) -> 0 | N68: =IF($L68<>1,0,SUMIFS('JLR Materials'!$F$2:$F$20001,'JLR Materials'!$A$2:$A$20001,$K68,'JLR Materials'!$C$2:$C$20001,IF(Settings!$B$2="","<>",Settings!$B$2),'JLR Materials'!$D$2:$D$20001,IF(Settings!$B$4="","<>",Settings!$B$4))) -> 0 | O68: =IF($N68=0,0,IF(Settings!$B$5="percent",$M68*$N68/100,$N68)) -> 0 | P68: =IF($L68<>1,0,SUMIFS('JLR Materials'!$G$2:$G$20001,'JLR Materials'!$A$2:$A$20001,$K68,'JLR Materials'!$C$2:$C$20001,IF(Settings!$B$2="","<>",Settings!$B$2),'JLR Materials'!$D$2:$D$20001,IF(Settings!$B$4="","<>",Settings!$B$4))) -> 0 | Q68: UK electrical steel Jul 2026. Standard 0.50mm NO — mains-frequency industrial motors, pumps. Workhorse economy grade. | Refresh 2026-09: +£0.041/kg from 1kg crno £0.612→£0.653/kg; premiums held | R68: 2026-09
A69: mat-m600-50a | B69: M600-50A NO Electrical (0.50mm, economy) | C69: Electrical Steel Sheet | D69: =IF($M69>0,$M69,1.19) -> 1.19 | E69: =IF($O69>0,$O69,0.26) -> 0.26 | F69: 7750 | G69: UK | H69: =IF($M69>0,IF($L69<>1,$R69,IFERROR(INDEX('JLR Materials'!$D$2:$D$20001,MATCH($K69,'JLR Materials'!$A$2:$A$20001,0)),$R69)),$R69) -> 2026-09 | I69: =IF($M69>0,"JLR rate card — material code "&$K69,$Q69) -> UK electrical steel Jul 2026. Economy 0.50mm NO — small appliance/fan motors, low duty cycle. | Refresh 2026-09: +£0.041/kg from 1kg crno £0.612→£0.653/kg; premiums held | J69: Medium | K69: =IFERROR(INDEX(Mapping!$C$2:$C$549,MATCH($A69,Mapping!$A$2:$A$549,0)),"") | L69: =IF($K69="",0,COUNTIFS('JLR Materials'!$A$2:$A$20001,$K69,'JLR Materials'!$C$2:$C$20001,IF(Settings!$B$2="","<>",Settings!$B$2),'JLR Materials'!$D$2:$D$20001,IF(Settings!$B$4="","<>",Settings!$B$4))) -> 0 | M69: =IF($L69<>1,0,SUMIFS('JLR Materials'!$E$2:$E$20001,'JLR Materials'!$A$2:$A$20001,$K69,'JLR Materials'!$C$2:$C$20001,IF(Settings!$B$2="","<>",Settings!$B$2),'JLR Materials'!$D$2:$D$20001,IF(Settings!$B$4="","<>",Settings!$B$4))) -> 0 | N69: =IF($L69<>1,0,SUMIFS('JLR Materials'!$F$2:$F$20001,'JLR Materials'!$A$2:$A$20001,$K69,'JLR Materials'!$C$2:$C$20001,IF(Settings!$B$2="","<>",Settings!$B$2),'JLR Materials'!$D$2:$D$20001,IF(Settings!$B$4="","<>",Settings!$B$4))) -> 0 | O69: =IF($N69=0,0,IF(Settings!$B$5="percent",$M69*$N69/100,$N69)) -> 0 | P69: =IF($L69<>1,0,SUMIFS('JLR Materials'!$G$2:$G$20001,'JLR Materials'!$A$2:$A$20001,$K69,'JLR Materials'!$C$2:$C$20001,IF(Settings!$B$2="","<>",Settings!$B$2),'JLR Materials'!$D$2:$D$20001,IF(Settings!$B$4="","<>",Settings!$B$4))) -> 0 | Q69: UK electrical steel Jul 2026. Economy 0.50mm NO — small appliance/fan motors, low duty cycle. | Refresh 2026-09: +£0.041/kg from 1kg crno £0.612→£0.653/kg; premiums held | R69: 2026-09
A70: mat-m700-65a | B70: M700-65A NO Electrical (0.65mm, mains) | C70: Electrical Steel Sheet | D70: =IF($M70>0,$M70,1.14) -> 1.14 | E70: =IF($O70>0,$O70,0.26) -> 0.26 | F70: 7800 | G70: UK | H70: =IF($M70>0,IF($L70<>1,$R70,IFERROR(INDEX('JLR Materials'!$D$2:$D$20001,MATCH($K70,'JLR Materials'!$A$2:$A$20001,0)),$R70)),$R70) -> 2026-09 | I70: =IF($M70>0,"JLR rate card — material code "&$K70,$Q70) -> UK electrical steel Jul 2026. Thick 0.65mm NO — low-cost mains motors, ballasts; higher loss, cheapest lamination grade. | Refresh 2026-09: +£0.041/kg from 1kg crno £0.612→£0.653/kg; premiums held | J70: Low | K70: =IFERROR(INDEX(Mapping!$C$2:$C$549,MATCH($A70,Mapping!$A$2:$A$549,0)),"") | L70: =IF($K70="",0,COUNTIFS('JLR Materials'!$A$2:$A$20001,$K70,'JLR Materials'!$C$2:$C$20001,IF(Settings!$B$2="","<>",Settings!$B$2),'JLR Materials'!$D$2:$D$20001,IF(Settings!$B$4="","<>",Settings!$B$4))) -> 0 | M70: =IF($L70<>1,0,SUMIFS('JLR Materials'!$E$2:$E$20001,'JLR Materials'!$A$2:$A$20001,$K70,'JLR Materials'!$C$2:$C$20001,IF(Settings!$B$2="","<>",Settings!$B$2),'JLR Materials'!$D$2:$D$20001,IF(Settings!$B$4="","<>",Settings!$B$4))) -> 0 | N70: =IF($L70<>1,0,SUMIFS('JLR Materials'!$F$2:$F$20001,'JLR Materials'!$A$2:$A$20001,$K70,'JLR Materials'!$C$2:$C$20001,IF(Settings!$B$2="","<>",Settings!$B$2),'JLR Materials'!$D$2:$D$20001,IF(Settings!$B$4="","<>",Settings!$B$4))) -> 0 | O70: =IF($N70=0,0,IF(Settings!$B$5="percent",$M70*$N70/100,$N70)) -> 0 | P70: =IF($L70<>1,0,SUMIFS('JLR Materials'!$G$2:$G$20001,'JLR Materials'!$A$2:$A$20001,$K70,'JLR Materials'!$C$2:$C$20001,IF(Settings!$B$2="","<>",Settings!$B$2),'JLR Materials'!$D$2:$D$20001,IF(Settings!$B$4="","<>",Settings!$B$4))) -> 0 | Q70: UK electrical steel Jul 2026. Thick 0.65mm NO — low-cost mains motors, ballasts; higher loss, cheapest lamination grade. | Refresh 2026-09: +£0.041/kg from 1kg crno £0.612→£0.653/kg; premiums held | R70: 2026-09
A71: mat-no27-27a | B71: NO27 (0.27mm EV Traction) | C71: Electrical Steel Sheet | D71: =IF($M71>0,$M71,2.44) -> 2.44 | E71: =IF($O71>0,$O71,0.28) -> 0.28 | F71: 7600 | G71: UK | H71: =IF($M71>0,IF($L71<>1,$R71,IFERROR(INDEX('JLR Materials'!$D$2:$D$20001,MATCH($K71,'JLR Materials'!$A$2:$A$20001,0)),$R71)),$R71) -> 2026-09 | I71: =IF($M71>0,"JLR rate card — material code "&$K71,$Q71) -> UK electrical steel Jul 2026. 0.27mm thin-gauge NO — high-speed EV traction (200–400 Hz), low iron loss. Notch-tool-wear intensive. | Refresh 2026-09: +£0.041/kg from 1kg crno £0.612→£0.653/kg; premiums held | J71: Low | K71: =IFERROR(INDEX(Mapping!$C$2:$C$549,MATCH($A71,Mapping!$A$2:$A$549,0)),"") | L71: =IF($K71="",0,COUNTIFS('JLR Materials'!$A$2:$A$20001,$K71,'JLR Materials'!$C$2:$C$20001,IF(Settings!$B$2="","<>",Settings!$B$2),'JLR Materials'!$D$2:$D$20001,IF(Settings!$B$4="","<>",Settings!$B$4))) -> 0 | M71: =IF($L71<>1,0,SUMIFS('JLR Materials'!$E$2:$E$20001,'JLR Materials'!$A$2:$A$20001,$K71,'JLR Materials'!$C$2:$C$20001,IF(Settings!$B$2="","<>",Settings!$B$2),'JLR Materials'!$D$2:$D$20001,IF(Settings!$B$4="","<>",Settings!$B$4))) -> 0 | N71: =IF($L71<>1,0,SUMIFS('JLR Materials'!$F$2:$F$20001,'JLR Materials'!$A$2:$A$20001,$K71,'JLR Materials'!$C$2:$C$20001,IF(Settings!$B$2="","<>",Settings!$B$2),'JLR Materials'!$D$2:$D$20001,IF(Settings!$B$4="","<>",Settings!$B$4))) -> 0 | O71: =IF($N71=0,0,IF(Settings!$B$5="percent",$M71*$N71/100,$N71)) -> 0 | P71: =IF($L71<>1,0,SUMIFS('JLR Materials'!$G$2:$G$20001,'JLR Materials'!$A$2:$A$20001,$K71,'JLR Materials'!$C$2:$C$20001,IF(Settings!$B$2="","<>",Settings!$B$2),'JLR Materials'!$D$2:$D$20001,IF(Settings!$B$4="","<>",Settings!$B$4))) -> 0 | Q71: UK electrical steel Jul 2026. 0.27mm thin-gauge NO — high-speed EV traction (200–400 Hz), low iron loss. Notch-tool-wear intensive. | Refresh 2026-09: +£0.041/kg from 1kg crno £0.612→£0.653/kg; premiums held | R71: 2026-09
A72: mat-no25-25a | B72: NO25 (0.25mm EV Traction) | C72: Electrical Steel Sheet | D72: =IF($M72>0,$M72,2.74) -> 2.74 | E72: =IF($O72>0,$O72,0.28) -> 0.28 | F72: 7600 | G72: UK | H72: =IF($M72>0,IF($L72<>1,$R72,IFERROR(INDEX('JLR Materials'!$D$2:$D$20001,MATCH($K72,'JLR Materials'!$A$2:$A$20001,0)),$R72)),$R72) -> 2026-09 | I72: =IF($M72>0,"JLR rate card — material code "&$K72,$Q72) -> UK electrical steel Jul 2026. 0.25mm high-efficiency EV motor lamination; very low core loss, high mechanical strength grades available. | Refresh 2026-09: +£0.041/kg from 1kg crno £0.612→£0.653/kg; premiums held | J72: Low | K72: =IFERROR(INDEX(Mapping!$C$2:$C$549,MATCH($A72,Mapping!$A$2:$A$549,0)),"") | L72: =IF($K72="",0,COUNTIFS('JLR Materials'!$A$2:$A$20001,$K72,'JLR Materials'!$C$2:$C$20001,IF(Settings!$B$2="","<>",Settings!$B$2),'JLR Materials'!$D$2:$D$20001,IF(Settings!$B$4="","<>",Settings!$B$4))) -> 0 | M72: =IF($L72<>1,0,SUMIFS('JLR Materials'!$E$2:$E$20001,'JLR Materials'!$A$2:$A$20001,$K72,'JLR Materials'!$C$2:$C$20001,IF(Settings!$B$2="","<>",Settings!$B$2),'JLR Materials'!$D$2:$D$20001,IF(Settings!$B$4="","<>",Settings!$B$4))) -> 0 | N72: =IF($L72<>1,0,SUMIFS('JLR Materials'!$F$2:$F$20001,'JLR Materials'!$A$2:$A$20001,$K72,'JLR Materials'!$C$2:$C$20001,IF(Settings!$B$2="","<>",Settings!$B$2),'JLR Materials'!$D$2:$D$20001,IF(Settings!$B$4="","<>",Settings!$B$4))) -> 0 | O72: =IF($N72=0,0,IF(Settings!$B$5="percent",$M72*$N72/100,$N72)) -> 0 | P72: =IF($L72<>1,0,SUMIFS('JLR Materials'!$G$2:$G$20001,'JLR Materials'!$A$2:$A$20001,$K72,'JLR Materials'!$C$2:$C$20001,IF(Settings!$B$2="","<>",Settings!$B$2),'JLR Materials'!$D$2:$D$20001,IF(Settings!$B$4="","<>",Settings!$B$4))) -> 0 | Q72: UK electrical steel Jul 2026. 0.25mm high-efficiency EV motor lamination; very low core loss, high mechanical strength grades available. | Refresh 2026-09: +£0.041/kg from 1kg crno £0.612→£0.653/kg; premiums held | R72: 2026-09
A73: mat-no20-20a | B73: NO20 (0.20mm High-Speed EV/aero) | C73: Electrical Steel Sheet | D73: =IF($M73>0,$M73,3.44) -> 3.44 | E73: =IF($O73>0,$O73,0.3) -> 0.3 | F73: 7600 | G73: UK | H73: =IF($M73>0,IF($L73<>1,$R73,IFERROR(INDEX('JLR Materials'!$D$2:$D$20001,MATCH($K73,'JLR Materials'!$A$2:$A$20001,0)),$R73)),$R73) -> 2026-09 | I73: =IF($M73>0,"JLR rate card — material code "&$K73,$Q73) -> UK electrical steel Jul 2026. 0.20mm ultra-thin NO — high-speed (>15k rpm) EV/aerospace traction; lowest loss, premium price, low stacking factor. | Refresh 2026-09: +£0.041/kg from 1kg crno £0.612→£0.653/kg; premiums held | J73: Low | K73: =IFERROR(INDEX(Mapping!$C$2:$C$549,MATCH($A73,Mapping!$A$2:$A$549,0)),"") | L73: =IF($K73="",0,COUNTIFS('JLR Materials'!$A$2:$A$20001,$K73,'JLR Materials'!$C$2:$C$20001,IF(Settings!$B$2="","<>",Settings!$B$2),'JLR Materials'!$D$2:$D$20001,IF(Settings!$B$4="","<>",Settings!$B$4))) -> 0 | M73: =IF($L73<>1,0,SUMIFS('JLR Materials'!$E$2:$E$20001,'JLR Materials'!$A$2:$A$20001,$K73,'JLR Materials'!$C$2:$C$20001,IF(Settings!$B$2="","<>",Settings!$B$2),'JLR Materials'!$D$2:$D$20001,IF(Settings!$B$4="","<>",Settings!$B$4))) -> 0 | N73: =IF($L73<>1,0,SUMIFS('JLR Materials'!$F$2:$F$20001,'JLR Materials'!$A$2:$A$20001,$K73,'JLR Materials'!$C$2:$C$20001,IF(Settings!$B$2="","<>",Settings!$B$2),'JLR Materials'!$D$2:$D$20001,IF(Settings!$B$4="","<>",Settings!$B$4))) -> 0 | O73: =IF($N73=0,0,IF(Settings!$B$5="percent",$M73*$N73/100,$N73)) -> 0 | P73: =IF($L73<>1,0,SUMIFS('JLR Materials'!$G$2:$G$20001,'JLR Materials'!$A$2:$A$20001,$K73,'JLR Materials'!$C$2:$C$20001,IF(Settings!$B$2="","<>",Settings!$B$2),'JLR Materials'!$D$2:$D$20001,IF(Settings!$B$4="","<>",Settings!$B$4))) -> 0 | Q73: UK electrical steel Jul 2026. 0.20mm ultra-thin NO — high-speed (>15k rpm) EV/aerospace traction; lowest loss, premium price, low stacking factor. | Refresh 2026-09: +£0.041/kg from 1kg crno £0.612→£0.653/kg; premiums held | R73: 2026-09
A74: mat-cgo-m120-27 | B74: M120-27S CGO (0.27mm Grain-Oriented) | C74: Electrical Steel Sheet | D74: =IF($M74>0,$M74,2.55) -> 2.55 | E74: =IF($O74>0,$O74,0.3) -> 0.3 | F74: 7650 | G74: UK | H74: =IF($M74>0,IF($L74<>1,$R74,IFERROR(INDEX('JLR Materials'!$D$2:$D$20001,MATCH($K74,'JLR Materials'!$A$2:$A$20001,0)),$R74)),$R74) -> 2026-09 | I74: =IF($M74>0,"JLR rate card — material code "&$K74,$Q74) -> UK electrical steel Jul 2026. Conventional grain-oriented — distribution/power transformer cores. | Refresh 2026-09: SPECIALTY — no public market index for this grade; held at the June 2026 price — refresh by supplier quote | J74: Low | K74: =IFERROR(INDEX(Mapping!$C$2:$C$549,MATCH($A74,Mapping!$A$2:$A$549,0)),"") | L74: =IF($K74="",0,COUNTIFS('JLR Materials'!$A$2:$A$20001,$K74,'JLR Materials'!$C$2:$C$20001,IF(Settings!$B$2="","<>",Settings!$B$2),'JLR Materials'!$D$2:$D$20001,IF(Settings!$B$4="","<>",Settings!$B$4))) -> 0 | M74: =IF($L74<>1,0,SUMIFS('JLR Materials'!$E$2:$E$20001,'JLR Materials'!$A$2:$A$20001,$K74,'JLR Materials'!$C$2:$C$20001,IF(Settings!$B$2="","<>",Settings!$B$2),'JLR Materials'!$D$2:$D$20001,IF(Settings!$B$4="","<>",Settings!$B$4))) -> 0 | N74: =IF($L74<>1,0,SUMIFS('JLR Materials'!$F$2:$F$20001,'JLR Materials'!$A$2:$A$20001,$K74,'JLR Materials'!$C$2:$C$20001,IF(Settings!$B$2="","<>",Settings!$B$2),'JLR Materials'!$D$2:$D$20001,IF(Settings!$B$4="","<>",Settings!$B$4))) -> 0 | O74: =IF($N74=0,0,IF(Settings!$B$5="percent",$M74*$N74/100,$N74)) -> 0 | P74: =IF($L74<>1,0,SUMIFS('JLR Materials'!$G$2:$G$20001,'JLR Materials'!$A$2:$A$20001,$K74,'JLR Materials'!$C$2:$C$20001,IF(Settings!$B$2="","<>",Settings!$B$2),'JLR Materials'!$D$2:$D$20001,IF(Settings!$B$4="","<>",Settings!$B$4))) -> 0 | Q74: UK electrical steel Jul 2026. Conventional grain-oriented — distribution/power transformer cores. | Refresh 2026-09: SPECIALTY — no public market index for this grade; held at the June 2026 price — refresh by supplier quote | R74: 2026-09
A75: mat-hgo-m090-23 | B75: M090-23P HGO Domain-Refined (0.23mm) | C75: Electrical Steel Sheet | D75: =IF($M75>0,$M75,3.4) -> 3.4 | E75: =IF($O75>0,$O75,0.3) -> 0.3 | F75: 7650 | G75: UK | H75: =IF($M75>0,IF($L75<>1,$R75,IFERROR(INDEX('JLR Materials'!$D$2:$D$20001,MATCH($K75,'JLR Materials'!$A$2:$A$20001,0)),$R75)),$R75) -> 2026-09 | I75: =IF($M75>0,"JLR rate card — material code "&$K75,$Q75) -> UK electrical steel Jul 2026. Laser-scribed domain-refined HGO — lowest-loss transformer grade, high-efficiency power transformers. | Refresh 2026-09: SPECIALTY — no public market index for this grade; held at the June 2026 price — refresh by supplier quote | J75: Low | K75: =IFERROR(INDEX(Mapping!$C$2:$C$549,MATCH($A75,Mapping!$A$2:$A$549,0)),"") | L75: =IF($K75="",0,COUNTIFS('JLR Materials'!$A$2:$A$20001,$K75,'JLR Materials'!$C$2:$C$20001,IF(Settings!$B$2="","<>",Settings!$B$2),'JLR Materials'!$D$2:$D$20001,IF(Settings!$B$4="","<>",Settings!$B$4))) -> 0 | M75: =IF($L75<>1,0,SUMIFS('JLR Materials'!$E$2:$E$20001,'JLR Materials'!$A$2:$A$20001,$K75,'JLR Materials'!$C$2:$C$20001,IF(Settings!$B$2="","<>",Settings!$B$2),'JLR Materials'!$D$2:$D$20001,IF(Settings!$B$4="","<>",Settings!$B$4))) -> 0 | N75: =IF($L75<>1,0,SUMIFS('JLR Materials'!$F$2:$F$20001,'JLR Materials'!$A$2:$A$20001,$K75,'JLR Materials'!$C$2:$C$20001,IF(Settings!$B$2="","<>",Settings!$B$2),'JLR Materials'!$D$2:$D$20001,IF(Settings!$B$4="","<>",Settings!$B$4))) -> 0 | O75: =IF($N75=0,0,IF(Settings!$B$5="percent",$M75*$N75/100,$N75)) -> 0 | P75: =IF($L75<>1,0,SUMIFS('JLR Materials'!$G$2:$G$20001,'JLR Materials'!$A$2:$A$20001,$K75,'JLR Materials'!$C$2:$C$20001,IF(Settings!$B$2="","<>",Settings!$B$2),'JLR Materials'!$D$2:$D$20001,IF(Settings!$B$4="","<>",Settings!$B$4))) -> 0 | Q75: UK electrical steel Jul 2026. Laser-scribed domain-refined HGO — lowest-loss transformer grade, high-efficiency power transformers. | Refresh 2026-09: SPECIALTY — no public market index for this grade; held at the June 2026 price — refresh by supplier quote | R75: 2026-09
A76: mat-cofe-hiperco50 | B76: Cobalt-Iron (Hiperco 50 / Vacodur 49) | C76: Electrical Steel Sheet | D76: =IF($M76>0,$M76,58) -> 58 | E76: =IF($O76>0,$O76,4) -> 4 | F76: 8120 | G76: UK | H76: =IF($M76>0,IF($L76<>1,$R76,IFERROR(INDEX('JLR Materials'!$D$2:$D$20001,MATCH($K76,'JLR Materials'!$A$2:$A$20001,0)),$R76)),$R76) -> 2026-09 | I76: =IF($M76>0,"JLR rate card — material code "&$K76,$Q76) -> UK speciality Jul 2026. CoFe (49Co-2V) — highest saturation (2.3T), aerospace/defence & high-power-density EV traction; needs final anneal in H₂. Premium. | Refresh 2026-09: NOT SOURCED — co: Not sourced this period: no June and September level on the same basis. Held at the June 2026 price. | J76: Low | K76: =IFERROR(INDEX(Mapping!$C$2:$C$549,MATCH($A76,Mapping!$A$2:$A$549,0)),"") | L76: =IF($K76="",0,COUNTIFS('JLR Materials'!$A$2:$A$20001,$K76,'JLR Materials'!$C$2:$C$20001,IF(Settings!$B$2="","<>",Settings!$B$2),'JLR Materials'!$D$2:$D$20001,IF(Settings!$B$4="","<>",Settings!$B$4))) -> 0 | M76: =IF($L76<>1,0,SUMIFS('JLR Materials'!$E$2:$E$20001,'JLR Materials'!$A$2:$A$20001,$K76,'JLR Materials'!$C$2:$C$20001,IF(Settings!$B$2="","<>",Settings!$B$2),'JLR Materials'!$D$2:$D$20001,IF(Settings!$B$4="","<>",Settings!$B$4))) -> 0 | N76: =IF($L76<>1,0,SUMIFS('JLR Materials'!$F$2:$F$20001,'JLR Materials'!$A$2:$A$20001,$K76,'JLR Materials'!$C$2:$C$20001,IF(Settings!$B$2="","<>",Settings!$B$2),'JLR Materials'!$D$2:$D$20001,IF(Settings!$B$4="","<>",Settings!$B$4))) -> 0 | O76: =IF($N76=0,0,IF(Settings!$B$5="percent",$M76*$N76/100,$N76)) -> 0 | P76: =IF($L76<>1,0,SUMIFS('JLR Materials'!$G$2:$G$20001,'JLR Materials'!$A$2:$A$20001,$K76,'JLR Materials'!$C$2:$C$20001,IF(Settings!$B$2="","<>",Settings!$B$2),'JLR Materials'!$D$2:$D$20001,IF(Settings!$B$4="","<>",Settings!$B$4))) -> 0 | Q76: UK speciality Jul 2026. CoFe (49Co-2V) — highest saturation (2.3T), aerospace/defence & high-power-density EV traction; needs final anneal in H₂. Premium. | Refresh 2026-09: NOT SOURCED — co: Not sourced this period: no June and September level on the same basis. Held at the June 2026 price. | R76: 2026-09
A77: mat-nife-permalloy80 | B77: Nickel-Iron Permalloy (80% Ni) | C77: Electrical Steel Sheet | D77: =IF($M77>0,$M77,24.06) -> 24.06 | E77: =IF($O77>0,$O77,2.01) -> 2.01 | F77: 8740 | G77: UK | H77: =IF($M77>0,IF($L77<>1,$R77,IFERROR(INDEX('JLR Materials'!$D$2:$D$20001,MATCH($K77,'JLR Materials'!$A$2:$A$20001,0)),$R77)),$R77) -> 2026-09 | I77: =IF($M77>0,"JLR rate card — material code "&$K77,$Q77) -> UK speciality Jul 2026. 80NiFe — ultra-high permeability small cores, sensors, resolvers, current transformers; low saturation, expensive. | Refresh 2026-09: +£0.061/kg from 0.8kg ni £12.302→£12.378/kg, 0.05kg mo £1.000→£1.000/kg; premiums held | J77: Low | K77: =IFERROR(INDEX(Mapping!$C$2:$C$549,MATCH($A77,Mapping!$A$2:$A$549,0)),"") | L77: =IF($K77="",0,COUNTIFS('JLR Materials'!$A$2:$A$20001,$K77,'JLR Materials'!$C$2:$C$20001,IF(Settings!$B$2="","<>",Settings!$B$2),'JLR Materials'!$D$2:$D$20001,IF(Settings!$B$4="","<>",Settings!$B$4))) -> 0 | M77: =IF($L77<>1,0,SUMIFS('JLR Materials'!$E$2:$E$20001,'JLR Materials'!$A$2:$A$20001,$K77,'JLR Materials'!$C$2:$C$20001,IF(Settings!$B$2="","<>",Settings!$B$2),'JLR Materials'!$D$2:$D$20001,IF(Settings!$B$4="","<>",Settings!$B$4))) -> 0 | N77: =IF($L77<>1,0,SUMIFS('JLR Materials'!$F$2:$F$20001,'JLR Materials'!$A$2:$A$20001,$K77,'JLR Materials'!$C$2:$C$20001,IF(Settings!$B$2="","<>",Settings!$B$2),'JLR Materials'!$D$2:$D$20001,IF(Settings!$B$4="","<>",Settings!$B$4))) -> 0 | O77: =IF($N77=0,0,IF(Settings!$B$5="percent",$M77*$N77/100,$N77)) -> 0 | P77: =IF($L77<>1,0,SUMIFS('JLR Materials'!$G$2:$G$20001,'JLR Materials'!$A$2:$A$20001,$K77,'JLR Materials'!$C$2:$C$20001,IF(Settings!$B$2="","<>",Settings!$B$2),'JLR Materials'!$D$2:$D$20001,IF(Settings!$B$4="","<>",Settings!$B$4))) -> 0 | Q77: UK speciality Jul 2026. 80NiFe — ultra-high permeability small cores, sensors, resolvers, current transformers; low saturation, expensive. | Refresh 2026-09: +£0.061/kg from 0.8kg ni £12.302→£12.378/kg, 0.05kg mo £1.000→£1.000/kg; premiums held | R77: 2026-09
A78: mat-amorphous-2605sa1 | B78: Amorphous Ribbon (Metglas 2605SA1) | C78: Electrical Steel Sheet | D78: =IF($M78>0,$M78,8.5) -> 8.5 | E78: =IF($O78>0,$O78,0.5) -> 0.5 | F78: 7180 | G78: UK | H78: =IF($M78>0,IF($L78<>1,$R78,IFERROR(INDEX('JLR Materials'!$D$2:$D$20001,MATCH($K78,'JLR Materials'!$A$2:$A$20001,0)),$R78)),$R78) -> 2026-09 | I78: =IF($M78>0,"JLR rate card — material code "&$K78,$Q78) -> UK speciality Jul 2026. Fe-based amorphous ribbon (~25µm) — ultra-low-loss distribution transformers, high-freq cut cores; brittle, cut/etched not conventionally stamped. | Refresh 2026-09: SPECIALTY — no public market index for this grade; held at the June 2026 price — refresh by supplier quote | J78: Low | K78: =IFERROR(INDEX(Mapping!$C$2:$C$549,MATCH($A78,Mapping!$A$2:$A$549,0)),"") | L78: =IF($K78="",0,COUNTIFS('JLR Materials'!$A$2:$A$20001,$K78,'JLR Materials'!$C$2:$C$20001,IF(Settings!$B$2="","<>",Settings!$B$2),'JLR Materials'!$D$2:$D$20001,IF(Settings!$B$4="","<>",Settings!$B$4))) -> 0 | M78: =IF($L78<>1,0,SUMIFS('JLR Materials'!$E$2:$E$20001,'JLR Materials'!$A$2:$A$20001,$K78,'JLR Materials'!$C$2:$C$20001,IF(Settings!$B$2="","<>",Settings!$B$2),'JLR Materials'!$D$2:$D$20001,IF(Settings!$B$4="","<>",Settings!$B$4))) -> 0 | N78: =IF($L78<>1,0,SUMIFS('JLR Materials'!$F$2:$F$20001,'JLR Materials'!$A$2:$A$20001,$K78,'JLR Materials'!$C$2:$C$20001,IF(Settings!$B$2="","<>",Settings!$B$2),'JLR Materials'!$D$2:$D$20001,IF(Settings!$B$4="","<>",Settings!$B$4))) -> 0 | O78: =IF($N78=0,0,IF(Settings!$B$5="percent",$M78*$N78/100,$N78)) -> 0 | P78: =IF($L78<>1,0,SUMIFS('JLR Materials'!$G$2:$G$20001,'JLR Materials'!$A$2:$A$20001,$K78,'JLR Materials'!$C$2:$C$20001,IF(Settings!$B$2="","<>",Settings!$B$2),'JLR Materials'!$D$2:$D$20001,IF(Settings!$B$4="","<>",Settings!$B$4))) -> 0 | Q78: UK speciality Jul 2026. Fe-based amorphous ribbon (~25µm) — ultra-low-loss distribution transformers, high-freq cut cores; brittle, cut/etched not conventionally stamped. | Refresh 2026-09: SPECIALTY — no public market index for this grade; held at the June 2026 price — refresh by supplier quote | R78: 2026-09
A79: mat-no-semiproc-50 | B79: Semi-Processed NO Electrical (0.50mm) | C79: Electrical Steel Sheet | D79: =IF($M79>0,$M79,1.09) -> 1.09 | E79: =IF($O79>0,$O79,0.25) -> 0.25 | F79: 7750 | G79: UK | H79: =IF($M79>0,IF($L79<>1,$R79,IFERROR(INDEX('JLR Materials'!$D$2:$D$20001,MATCH($K79,'JLR Materials'!$A$2:$A$20001,0)),$R79)),$R79) -> 2026-09 | I79: =IF($M79>0,"JLR rate card — material code "&$K79,$Q79) -> UK electrical steel Jul 2026. Semi-processed NO — magnetic properties developed by the stamper’s post-blank anneal; low coil cost, mandatory stress-relief/decarb anneal. | Refresh 2026-09: +£0.041/kg from 1kg crno £0.612→£0.653/kg; premiums held | J79: Low | K79: =IFERROR(INDEX(Mapping!$C$2:$C$549,MATCH($A79,Mapping!$A$2:$A$549,0)),"") | L79: =IF($K79="",0,COUNTIFS('JLR Materials'!$A$2:$A$20001,$K79,'JLR Materials'!$C$2:$C$20001,IF(Settings!$B$2="","<>",Settings!$B$2),'JLR Materials'!$D$2:$D$20001,IF(Settings!$B$4="","<>",Settings!$B$4))) -> 0 | M79: =IF($L79<>1,0,SUMIFS('JLR Materials'!$E$2:$E$20001,'JLR Materials'!$A$2:$A$20001,$K79,'JLR Materials'!$C$2:$C$20001,IF(Settings!$B$2="","<>",Settings!$B$2),'JLR Materials'!$D$2:$D$20001,IF(Settings!$B$4="","<>",Settings!$B$4))) -> 0 | N79: =IF($L79<>1,0,SUMIFS('JLR Materials'!$F$2:$F$20001,'JLR Materials'!$A$2:$A$20001,$K79,'JLR Materials'!$C$2:$C$20001,IF(Settings!$B$2="","<>",Settings!$B$2),'JLR Materials'!$D$2:$D$20001,IF(Settings!$B$4="","<>",Settings!$B$4))) -> 0 | O79: =IF($N79=0,0,IF(Settings!$B$5="percent",$M79*$N79/100,$N79)) -> 0 | P79: =IF($L79<>1,0,SUMIFS('JLR Materials'!$G$2:$G$20001,'JLR Materials'!$A$2:$A$20001,$K79,'JLR Materials'!$C$2:$C$20001,IF(Settings!$B$2="","<>",Settings!$B$2),'JLR Materials'!$D$2:$D$20001,IF(Settings!$B$4="","<>",Settings!$B$4))) -> 0 | Q79: UK electrical steel Jul 2026. Semi-processed NO — magnetic properties developed by the stamper’s post-blank anneal; low coil cost, mandatory stress-relief/decarb anneal. | Refresh 2026-09: +£0.041/kg from 1kg crno £0.612→£0.653/kg; premiums held | R79: 2026-09
A80: mat-hsno-rotor-700 | B80: High-Strength NO Electrical (~700 MPa, 0.30mm rotor) | C80: Electrical Steel Sheet | D80: =IF($M80>0,$M80,2.64) -> 2.64 | E80: =IF($O80>0,$O80,0.28) -> 0.28 | F80: 7650 | G80: UK | H80: =IF($M80>0,IF($L80<>1,$R80,IFERROR(INDEX('JLR Materials'!$D$2:$D$20001,MATCH($K80,'JLR Materials'!$A$2:$A$20001,0)),$R80)),$R80) -> 2026-09 | I80: =IF($M80>0,"JLR rate card — material code "&$K80,$Q80) -> UK electrical steel Jul 2026. High-yield thin-gauge NO for high-speed EV traction rotors (bridge stresses at 15–20k rpm) — BYD/Xiaomi-class hyper-motors. Higher Si+alloy, harder to notch. | Refresh 2026-09: +£0.041/kg from 1kg crno £0.612→£0.653/kg; premiums held | J80: Low | K80: =IFERROR(INDEX(Mapping!$C$2:$C$549,MATCH($A80,Mapping!$A$2:$A$549,0)),"") | L80: =IF($K80="",0,COUNTIFS('JLR Materials'!$A$2:$A$20001,$K80,'JLR Materials'!$C$2:$C$20001,IF(Settings!$B$2="","<>",Settings!$B$2),'JLR Materials'!$D$2:$D$20001,IF(Settings!$B$4="","<>",Settings!$B$4))) -> 0 | M80: =IF($L80<>1,0,SUMIFS('JLR Materials'!$E$2:$E$20001,'JLR Materials'!$A$2:$A$20001,$K80,'JLR Materials'!$C$2:$C$20001,IF(Settings!$B$2="","<>",Settings!$B$2),'JLR Materials'!$D$2:$D$20001,IF(Settings!$B$4="","<>",Settings!$B$4))) -> 0 | N80: =IF($L80<>1,0,SUMIFS('JLR Materials'!$F$2:$F$20001,'JLR Materials'!$A$2:$A$20001,$K80,'JLR Materials'!$C$2:$C$20001,IF(Settings!$B$2="","<>",Settings!$B$2),'JLR Materials'!$D$2:$D$20001,IF(Settings!$B$4="","<>",Settings!$B$4))) -> 0 | O80: =IF($N80=0,0,IF(Settings!$B$5="percent",$M80*$N80/100,$N80)) -> 0 | P80: =IF($L80<>1,0,SUMIFS('JLR Materials'!$G$2:$G$20001,'JLR Materials'!$A$2:$A$20001,$K80,'JLR Materials'!$C$2:$C$20001,IF(Settings!$B$2="","<>",Settings!$B$2),'JLR Materials'!$D$2:$D$20001,IF(Settings!$B$4="","<>",Settings!$B$4))) -> 0 | Q80: UK electrical steel Jul 2026. High-yield thin-gauge NO for high-speed EV traction rotors (bridge stresses at 15–20k rpm) — BYD/Xiaomi-class hyper-motors. Higher Si+alloy, harder to notch. | Refresh 2026-09: +£0.041/kg from 1kg crno £0.612→£0.653/kg; premiums held | R80: 2026-09
A81: mat-hsno-rotor-960 | B81: Ultra-High-Strength NO Electrical (~960 MPa, 0.20–0.27mm rotor) | C81: Electrical Steel Sheet | D81: =IF($M81>0,$M81,3.24) -> 3.24 | E81: =IF($O81>0,$O81,0.3) -> 0.3 | F81: 7600 | G81: UK | H81: =IF($M81>0,IF($L81<>1,$R81,IFERROR(INDEX('JLR Materials'!$D$2:$D$20001,MATCH($K81,'JLR Materials'!$A$2:$A$20001,0)),$R81)),$R81) -> 2026-09 | I81: =IF($M81>0,"JLR rate card — material code "&$K81,$Q81) -> UK electrical steel Jul 2026. Ultra-high-yield thin NO for >20k rpm rotors (Xiaomi HyperEngine V8s ~27,200 rpm class) — enables slim bridges + high tip speed. Premium, heavy notch-tool wear. | Refresh 2026-09: +£0.041/kg from 1kg crno £0.612→£0.653/kg; premiums held | J81: Low | K81: =IFERROR(INDEX(Mapping!$C$2:$C$549,MATCH($A81,Mapping!$A$2:$A$549,0)),"") | L81: =IF($K81="",0,COUNTIFS('JLR Materials'!$A$2:$A$20001,$K81,'JLR Materials'!$C$2:$C$20001,IF(Settings!$B$2="","<>",Settings!$B$2),'JLR Materials'!$D$2:$D$20001,IF(Settings!$B$4="","<>",Settings!$B$4))) -> 0 | M81: =IF($L81<>1,0,SUMIFS('JLR Materials'!$E$2:$E$20001,'JLR Materials'!$A$2:$A$20001,$K81,'JLR Materials'!$C$2:$C$20001,IF(Settings!$B$2="","<>",Settings!$B$2),'JLR Materials'!$D$2:$D$20001,IF(Settings!$B$4="","<>",Settings!$B$4))) -> 0 | N81: =IF($L81<>1,0,SUMIFS('JLR Materials'!$F$2:$F$20001,'JLR Materials'!$A$2:$A$20001,$K81,'JLR Materials'!$C$2:$C$20001,IF(Settings!$B$2="","<>",Settings!$B$2),'JLR Materials'!$D$2:$D$20001,IF(Settings!$B$4="","<>",Settings!$B$4))) -> 0 | O81: =IF($N81=0,0,IF(Settings!$B$5="percent",$M81*$N81/100,$N81)) -> 0 | P81: =IF($L81<>1,0,SUMIFS('JLR Materials'!$G$2:$G$20001,'JLR Materials'!$A$2:$A$20001,$K81,'JLR Materials'!$C$2:$C$20001,IF(Settings!$B$2="","<>",Settings!$B$2),'JLR Materials'!$D$2:$D$20001,IF(Settings!$B$4="","<>",Settings!$B$4))) -> 0 | Q81: UK electrical steel Jul 2026. Ultra-high-yield thin NO for >20k rpm rotors (Xiaomi HyperEngine V8s ~27,200 rpm class) — enables slim bridges + high tip speed. Premium, heavy notch-tool wear. | Refresh 2026-09: +£0.041/kg from 1kg crno £0.612→£0.653/kg; premiums held | R81: 2026-09
A82: mat-no15-15a | B82: NO15 Ultra-Thin NO Electrical (0.15mm) | C82: Electrical Steel Sheet | D82: =IF($M82>0,$M82,3.94) -> 3.94 | E82: =IF($O82>0,$O82,0.3) -> 0.3 | F82: 7600 | G82: UK | H82: =IF($M82>0,IF($L82<>1,$R82,IFERROR(INDEX('JLR Materials'!$D$2:$D$20001,MATCH($K82,'JLR Materials'!$A$2:$A$20001,0)),$R82)),$R82) -> 2026-09 | I82: =IF($M82>0,"JLR rate card — material code "&$K82,$Q82) -> UK electrical steel Jul 2026. 0.15mm ultra-thin NO — very high-frequency traction (SU7 Ultra V8s / high-speed EV); low eddy loss, low stacking factor, hard to blank (fine burr control). Bonded (backlack) stacks typical. | Refresh 2026-09: +£0.041/kg from 1kg crno £0.612→£0.653/kg; premiums held | J82: Low | K82: =IFERROR(INDEX(Mapping!$C$2:$C$549,MATCH($A82,Mapping!$A$2:$A$549,0)),"") | L82: =IF($K82="",0,COUNTIFS('JLR Materials'!$A$2:$A$20001,$K82,'JLR Materials'!$C$2:$C$20001,IF(Settings!$B$2="","<>",Settings!$B$2),'JLR Materials'!$D$2:$D$20001,IF(Settings!$B$4="","<>",Settings!$B$4))) -> 0 | M82: =IF($L82<>1,0,SUMIFS('JLR Materials'!$E$2:$E$20001,'JLR Materials'!$A$2:$A$20001,$K82,'JLR Materials'!$C$2:$C$20001,IF(Settings!$B$2="","<>",Settings!$B$2),'JLR Materials'!$D$2:$D$20001,IF(Settings!$B$4="","<>",Settings!$B$4))) -> 0 | N82: =IF($L82<>1,0,SUMIFS('JLR Materials'!$F$2:$F$20001,'JLR Materials'!$A$2:$A$20001,$K82,'JLR Materials'!$C$2:$C$20001,IF(Settings!$B$2="","<>",Settings!$B$2),'JLR Materials'!$D$2:$D$20001,IF(Settings!$B$4="","<>",Settings!$B$4))) -> 0 | O82: =IF($N82=0,0,IF(Settings!$B$5="percent",$M82*$N82/100,$N82)) -> 0 | P82: =IF($L82<>1,0,SUMIFS('JLR Materials'!$G$2:$G$20001,'JLR Materials'!$A$2:$A$20001,$K82,'JLR Materials'!$C$2:$C$20001,IF(Settings!$B$2="","<>",Settings!$B$2),'JLR Materials'!$D$2:$D$20001,IF(Settings!$B$4="","<>",Settings!$B$4))) -> 0 | Q82: UK electrical steel Jul 2026. 0.15mm ultra-thin NO — very high-frequency traction (SU7 Ultra V8s / high-speed EV); low eddy loss, low stacking factor, hard to blank (fine burr control). Bonded (backlack) stacks typical. | Refresh 2026-09: +£0.041/kg from 1kg crno £0.612→£0.653/kg; premiums held | R82: 2026-09
A83: mat-no10-10a | B83: NO10 Ultra-Thin NO Electrical (0.10mm) | C83: Electrical Steel Sheet | D83: =IF($M83>0,$M83,5.54) -> 5.54 | E83: =IF($O83>0,$O83,0.35) -> 0.35 | F83: 7600 | G83: UK | H83: =IF($M83>0,IF($L83<>1,$R83,IFERROR(INDEX('JLR Materials'!$D$2:$D$20001,MATCH($K83,'JLR Materials'!$A$2:$A$20001,0)),$R83)),$R83) -> 2026-09 | I83: =IF($M83>0,"JLR rate card — material code "&$K83,$Q83) -> UK electrical steel Jul 2026. 0.10mm foil-gauge NO — extreme high-speed / high-frequency rotors (aero/hypercar & top-end EV traction). Lowest iron loss; etched/bonded rather than hard-die blanked at volume. | Refresh 2026-09: +£0.041/kg from 1kg crno £0.612→£0.653/kg; premiums held | J83: Low | K83: =IFERROR(INDEX(Mapping!$C$2:$C$549,MATCH($A83,Mapping!$A$2:$A$549,0)),"") | L83: =IF($K83="",0,COUNTIFS('JLR Materials'!$A$2:$A$20001,$K83,'JLR Materials'!$C$2:$C$20001,IF(Settings!$B$2="","<>",Settings!$B$2),'JLR Materials'!$D$2:$D$20001,IF(Settings!$B$4="","<>",Settings!$B$4))) -> 0 | M83: =IF($L83<>1,0,SUMIFS('JLR Materials'!$E$2:$E$20001,'JLR Materials'!$A$2:$A$20001,$K83,'JLR Materials'!$C$2:$C$20001,IF(Settings!$B$2="","<>",Settings!$B$2),'JLR Materials'!$D$2:$D$20001,IF(Settings!$B$4="","<>",Settings!$B$4))) -> 0 | N83: =IF($L83<>1,0,SUMIFS('JLR Materials'!$F$2:$F$20001,'JLR Materials'!$A$2:$A$20001,$K83,'JLR Materials'!$C$2:$C$20001,IF(Settings!$B$2="","<>",Settings!$B$2),'JLR Materials'!$D$2:$D$20001,IF(Settings!$B$4="","<>",Settings!$B$4))) -> 0 | O83: =IF($N83=0,0,IF(Settings!$B$5="percent",$M83*$N83/100,$N83)) -> 0 | P83: =IF($L83<>1,0,SUMIFS('JLR Materials'!$G$2:$G$20001,'JLR Materials'!$A$2:$A$20001,$K83,'JLR Materials'!$C$2:$C$20001,IF(Settings!$B$2="","<>",Settings!$B$2),'JLR Materials'!$D$2:$D$20001,IF(Settings!$B$4="","<>",Settings!$B$4))) -> 0 | Q83: UK electrical steel Jul 2026. 0.10mm foil-gauge NO — extreme high-speed / high-frequency rotors (aero/hypercar & top-end EV traction). Lowest iron loss; etched/bonded rather than hard-die blanked at volume. | Refresh 2026-09: +£0.041/kg from 1kg crno £0.612→£0.653/kg; premiums held | R83: 2026-09
A84: mat-si65-jnex-10 | B84: 6.5% Si High-Frequency Electrical (JNEX/Super-Core class, 0.10mm) | C84: Electrical Steel Sheet | D84: =IF($M84>0,$M84,6.84) -> 6.84 | E84: =IF($O84>0,$O84,0.35) -> 0.35 | F84: 7490 | G84: UK | H84: =IF($M84>0,IF($L84<>1,$R84,IFERROR(INDEX('JLR Materials'!$D$2:$D$20001,MATCH($K84,'JLR Materials'!$A$2:$A$20001,0)),$R84)),$R84) -> 2026-09 | I84: =IF($M84>0,"JLR rate card — material code "&$K84,$Q84) -> UK speciality Jul 2026. 6.5% silicon steel (JFE JNEX / Super-Core class) — near-zero magnetostriction, lowest high-frequency core loss for high-rpm/high-pole EV & aerospace motors, reactors. Brittle, specialised processing. | Refresh 2026-09: +£0.041/kg from 1kg crno £0.612→£0.653/kg; premiums held | J84: Low | K84: =IFERROR(INDEX(Mapping!$C$2:$C$549,MATCH($A84,Mapping!$A$2:$A$549,0)),"") | L84: =IF($K84="",0,COUNTIFS('JLR Materials'!$A$2:$A$20001,$K84,'JLR Materials'!$C$2:$C$20001,IF(Settings!$B$2="","<>",Settings!$B$2),'JLR Materials'!$D$2:$D$20001,IF(Settings!$B$4="","<>",Settings!$B$4))) -> 0 | M84: =IF($L84<>1,0,SUMIFS('JLR Materials'!$E$2:$E$20001,'JLR Materials'!$A$2:$A$20001,$K84,'JLR Materials'!$C$2:$C$20001,IF(Settings!$B$2="","<>",Settings!$B$2),'JLR Materials'!$D$2:$D$20001,IF(Settings!$B$4="","<>",Settings!$B$4))) -> 0 | N84: =IF($L84<>1,0,SUMIFS('JLR Materials'!$F$2:$F$20001,'JLR Materials'!$A$2:$A$20001,$K84,'JLR Materials'!$C$2:$C$20001,IF(Settings!$B$2="","<>",Settings!$B$2),'JLR Materials'!$D$2:$D$20001,IF(Settings!$B$4="","<>",Settings!$B$4))) -> 0 | O84: =IF($N84=0,0,IF(Settings!$B$5="percent",$M84*$N84/100,$N84)) -> 0 | P84: =IF($L84<>1,0,SUMIFS('JLR Materials'!$G$2:$G$20001,'JLR Materials'!$A$2:$A$20001,$K84,'JLR Materials'!$C$2:$C$20001,IF(Settings!$B$2="","<>",Settings!$B$2),'JLR Materials'!$D$2:$D$20001,IF(Settings!$B$4="","<>",Settings!$B$4))) -> 0 | Q84: UK speciality Jul 2026. 6.5% silicon steel (JFE JNEX / Super-Core class) — near-zero magnetostriction, lowest high-frequency core loss for high-rpm/high-pole EV & aerospace motors, reactors. Brittle, specialised processing. | Refresh 2026-09: +£0.041/kg from 1kg crno £0.612→£0.653/kg; premiums held | R84: 2026-09
A85: mat-uhsno-1100 | B85: Ultra-High-Strength NO Electrical (~1100 MPa, 30k-rpm rotor) | C85: Electrical Steel Sheet | D85: =IF($M85>0,$M85,3.64) -> 3.64 | E85: =IF($O85>0,$O85,0.32) -> 0.32 | F85: 7600 | G85: UK | H85: =IF($M85>0,IF($L85<>1,$R85,IFERROR(INDEX('JLR Materials'!$D$2:$D$20001,MATCH($K85,'JLR Materials'!$A$2:$A$20001,0)),$R85)),$R85) -> 2026-09 | I85: =IF($M85>0,"JLR rate card — material code "&$K85,$Q85) -> UK electrical steel Jul 2026. ~1100 MPa yield thin-gauge NO for ~30,000 rpm flagship rotors (BYD Yangwang U7/U8/U9 quad-motor, Xiaomi flagship) — holds slim bridges at extreme tip speed. Premium alloy, severe notch-tool wear. | Refresh 2026-09: +£0.041/kg from 1kg crno £0.612→£0.653/kg; premiums held | J85: Low | K85: =IFERROR(INDEX(Mapping!$C$2:$C$549,MATCH($A85,Mapping!$A$2:$A$549,0)),"") | L85: =IF($K85="",0,COUNTIFS('JLR Materials'!$A$2:$A$20001,$K85,'JLR Materials'!$C$2:$C$20001,IF(Settings!$B$2="","<>",Settings!$B$2),'JLR Materials'!$D$2:$D$20001,IF(Settings!$B$4="","<>",Settings!$B$4))) -> 0 | M85: =IF($L85<>1,0,SUMIFS('JLR Materials'!$E$2:$E$20001,'JLR Materials'!$A$2:$A$20001,$K85,'JLR Materials'!$C$2:$C$20001,IF(Settings!$B$2="","<>",Settings!$B$2),'JLR Materials'!$D$2:$D$20001,IF(Settings!$B$4="","<>",Settings!$B$4))) -> 0 | N85: =IF($L85<>1,0,SUMIFS('JLR Materials'!$F$2:$F$20001,'JLR Materials'!$A$2:$A$20001,$K85,'JLR Materials'!$C$2:$C$20001,IF(Settings!$B$2="","<>",Settings!$B$2),'JLR Materials'!$D$2:$D$20001,IF(Settings!$B$4="","<>",Settings!$B$4))) -> 0 | O85: =IF($N85=0,0,IF(Settings!$B$5="percent",$M85*$N85/100,$N85)) -> 0 | P85: =IF($L85<>1,0,SUMIFS('JLR Materials'!$G$2:$G$20001,'JLR Materials'!$A$2:$A$20001,$K85,'JLR Materials'!$C$2:$C$20001,IF(Settings!$B$2="","<>",Settings!$B$2),'JLR Materials'!$D$2:$D$20001,IF(Settings!$B$4="","<>",Settings!$B$4))) -> 0 | Q85: UK electrical steel Jul 2026. ~1100 MPa yield thin-gauge NO for ~30,000 rpm flagship rotors (BYD Yangwang U7/U8/U9 quad-motor, Xiaomi flagship) — holds slim bridges at extreme tip speed. Premium alloy, severe notch-tool wear. | Refresh 2026-09: +£0.041/kg from 1kg crno £0.612→£0.653/kg; premiums held | R85: 2026-09
A86: mat-cofe-thin-010 | B86: Cobalt-Iron Thin-Gauge (0.10mm, Vacoflux/Hiperco) | C86: Electrical Steel Sheet | D86: =IF($M86>0,$M86,72) -> 72 | E86: =IF($O86>0,$O86,4.5) -> 4.5 | F86: 8120 | G86: UK | H86: =IF($M86>0,IF($L86<>1,$R86,IFERROR(INDEX('JLR Materials'!$D$2:$D$20001,MATCH($K86,'JLR Materials'!$A$2:$A$20001,0)),$R86)),$R86) -> 2026-09 | I86: =IF($M86>0,"JLR rate card — material code "&$K86,$Q86) -> UK speciality Jul 2026. 0.10mm cobalt-iron (49Co-2V) — highest saturation (2.3T) + high-frequency capability for maximum power-density motors (aerospace, hypercar/flagship EV traction); H₂ final anneal, very expensive. | Refresh 2026-09: NOT SOURCED — co: Not sourced this period: no June and September level on the same basis. Held at the June 2026 price. | J86: Low | K86: =IFERROR(INDEX(Mapping!$C$2:$C$549,MATCH($A86,Mapping!$A$2:$A$549,0)),"") | L86: =IF($K86="",0,COUNTIFS('JLR Materials'!$A$2:$A$20001,$K86,'JLR Materials'!$C$2:$C$20001,IF(Settings!$B$2="","<>",Settings!$B$2),'JLR Materials'!$D$2:$D$20001,IF(Settings!$B$4="","<>",Settings!$B$4))) -> 0 | M86: =IF($L86<>1,0,SUMIFS('JLR Materials'!$E$2:$E$20001,'JLR Materials'!$A$2:$A$20001,$K86,'JLR Materials'!$C$2:$C$20001,IF(Settings!$B$2="","<>",Settings!$B$2),'JLR Materials'!$D$2:$D$20001,IF(Settings!$B$4="","<>",Settings!$B$4))) -> 0 | N86: =IF($L86<>1,0,SUMIFS('JLR Materials'!$F$2:$F$20001,'JLR Materials'!$A$2:$A$20001,$K86,'JLR Materials'!$C$2:$C$20001,IF(Settings!$B$2="","<>",Settings!$B$2),'JLR Materials'!$D$2:$D$20001,IF(Settings!$B$4="","<>",Settings!$B$4))) -> 0 | O86: =IF($N86=0,0,IF(Settings!$B$5="percent",$M86*$N86/100,$N86)) -> 0 | P86: =IF($L86<>1,0,SUMIFS('JLR Materials'!$G$2:$G$20001,'JLR Materials'!$A$2:$A$20001,$K86,'JLR Materials'!$C$2:$C$20001,IF(Settings!$B$2="","<>",Settings!$B$2),'JLR Materials'!$D$2:$D$20001,IF(Settings!$B$4="","<>",Settings!$B$4))) -> 0 | Q86: UK speciality Jul 2026. 0.10mm cobalt-iron (49Co-2V) — highest saturation (2.3T) + high-frequency capability for maximum power-density motors (aerospace, hypercar/flagship EV traction); H₂ final anneal, very expensive. | Refresh 2026-09: NOT SOURCED — co: Not sourced this period: no June and September level on the same basis. Held at the June 2026 price. | R86: 2026-09
A87: mat-cu-hairpin | B87: Rectangular Enamelled Hairpin Copper (winding) | C87: Winding Copper (Hairpin) | D87: =IF($M87>0,$M87,13.9) -> 13.9 | E87: =IF($O87>0,$O87,6.32) -> 6.32 | F87: 8930 | G87: UK | H87: =IF($M87>0,IF($L87<>1,$R87,IFERROR(INDEX('JLR Materials'!$D$2:$D$20001,MATCH($K87,'JLR Materials'!$A$2:$A$20001,0)),$R87)),$R87) -> 2026-09 | I87: =IF($M87>0,"JLR rate card — material code "&$K87,$Q87) -> UK Jul 2026. Flat enamelled (grade-2/corona-resistant) rectangular copper wire for hairpin/bar-wound EV traction stators — stamped/bent hairpins, laser-welded crowns. ETP + enamel + forming premium over C110. | Refresh 2026-09: +£0.699/kg from 1kg cu £10.070→£10.768/kg; premiums held | J87: Low | K87: =IFERROR(INDEX(Mapping!$C$2:$C$549,MATCH($A87,Mapping!$A$2:$A$549,0)),"") | L87: =IF($K87="",0,COUNTIFS('JLR Materials'!$A$2:$A$20001,$K87,'JLR Materials'!$C$2:$C$20001,IF(Settings!$B$2="","<>",Settings!$B$2),'JLR Materials'!$D$2:$D$20001,IF(Settings!$B$4="","<>",Settings!$B$4))) -> 0 | M87: =IF($L87<>1,0,SUMIFS('JLR Materials'!$E$2:$E$20001,'JLR Materials'!$A$2:$A$20001,$K87,'JLR Materials'!$C$2:$C$20001,IF(Settings!$B$2="","<>",Settings!$B$2),'JLR Materials'!$D$2:$D$20001,IF(Settings!$B$4="","<>",Settings!$B$4))) -> 0 | N87: =IF($L87<>1,0,SUMIFS('JLR Materials'!$F$2:$F$20001,'JLR Materials'!$A$2:$A$20001,$K87,'JLR Materials'!$C$2:$C$20001,IF(Settings!$B$2="","<>",Settings!$B$2),'JLR Materials'!$D$2:$D$20001,IF(Settings!$B$4="","<>",Settings!$B$4))) -> 0 | O87: =IF($N87=0,0,IF(Settings!$B$5="percent",$M87*$N87/100,$N87)) -> 0 | P87: =IF($L87<>1,0,SUMIFS('JLR Materials'!$G$2:$G$20001,'JLR Materials'!$A$2:$A$20001,$K87,'JLR Materials'!$C$2:$C$20001,IF(Settings!$B$2="","<>",Settings!$B$2),'JLR Materials'!$D$2:$D$20001,IF(Settings!$B$4="","<>",Settings!$B$4))) -> 0 | Q87: UK Jul 2026. Flat enamelled (grade-2/corona-resistant) rectangular copper wire for hairpin/bar-wound EV traction stators — stamped/bent hairpins, laser-welded crowns. ETP + enamel + forming premium over C110. | Refresh 2026-09: +£0.699/kg from 1kg cu £10.070→£10.768/kg; premiums held | R87: 2026-09
A88: mat-al-hairpin | B88: Rectangular Enamelled Hairpin Aluminium (winding) | C88: Winding Aluminium (Hairpin) | D88: =IF($M88>0,$M88,4.74) -> 4.74 | E88: =IF($O88>0,$O88,1.09) -> 1.09 | F88: 2700 | G88: UK | H88: =IF($M88>0,IF($L88<>1,$R88,IFERROR(INDEX('JLR Materials'!$D$2:$D$20001,MATCH($K88,'JLR Materials'!$A$2:$A$20001,0)),$R88)),$R88) -> 2026-09 | I88: =IF($M88>0,"JLR rate card — material code "&$K88,$Q88) -> UK Jul 2026. Flat enamelled aluminium hairpin conductor — cost/weight-down alternative to copper in some EV traction motors; lower conductivity, larger slot fill. | Refresh 2026-09: −£0.060/kg from 0.97kg al £2.910→£2.849/kg; premiums held | J88: Low | K88: =IFERROR(INDEX(Mapping!$C$2:$C$549,MATCH($A88,Mapping!$A$2:$A$549,0)),"") | L88: =IF($K88="",0,COUNTIFS('JLR Materials'!$A$2:$A$20001,$K88,'JLR Materials'!$C$2:$C$20001,IF(Settings!$B$2="","<>",Settings!$B$2),'JLR Materials'!$D$2:$D$20001,IF(Settings!$B$4="","<>",Settings!$B$4))) -> 0 | M88: =IF($L88<>1,0,SUMIFS('JLR Materials'!$E$2:$E$20001,'JLR Materials'!$A$2:$A$20001,$K88,'JLR Materials'!$C$2:$C$20001,IF(Settings!$B$2="","<>",Settings!$B$2),'JLR Materials'!$D$2:$D$20001,IF(Settings!$B$4="","<>",Settings!$B$4))) -> 0 | N88: =IF($L88<>1,0,SUMIFS('JLR Materials'!$F$2:$F$20001,'JLR Materials'!$A$2:$A$20001,$K88,'JLR Materials'!$C$2:$C$20001,IF(Settings!$B$2="","<>",Settings!$B$2),'JLR Materials'!$D$2:$D$20001,IF(Settings!$B$4="","<>",Settings!$B$4))) -> 0 | O88: =IF($N88=0,0,IF(Settings!$B$5="percent",$M88*$N88/100,$N88)) -> 0 | P88: =IF($L88<>1,0,SUMIFS('JLR Materials'!$G$2:$G$20001,'JLR Materials'!$A$2:$A$20001,$K88,'JLR Materials'!$C$2:$C$20001,IF(Settings!$B$2="","<>",Settings!$B$2),'JLR Materials'!$D$2:$D$20001,IF(Settings!$B$4="","<>",Settings!$B$4))) -> 0 | Q88: UK Jul 2026. Flat enamelled aluminium hairpin conductor — cost/weight-down alternative to copper in some EV traction motors; lower conductivity, larger slot fill. | Refresh 2026-09: −£0.060/kg from 0.97kg al £2.910→£2.849/kg; premiums held | R88: 2026-09
A89: mat-al-busbar | B89: Aluminium Busbar (EV / battery) | C89: Aluminium Sheet | D89: =IF($M89>0,$M89,3.74) -> 3.74 | E89: =IF($O89>0,$O89,0.98) -> 0.98 | F89: 2700 | G89: UK | H89: =IF($M89>0,IF($L89<>1,$R89,IFERROR(INDEX('JLR Materials'!$D$2:$D$20001,MATCH($K89,'JLR Materials'!$A$2:$A$20001,0)),$R89)),$R89) -> 2026-09 | I89: =IF($M89>0,"JLR rate card — material code "&$K89,$Q89) -> UK Jul 2026. 1050/6101 aluminium busbar stock — battery-pack and inverter interconnects, cell-to-body (CTB/CTC) module bars; lighter/cheaper than copper, larger cross-section. | Refresh 2026-09: −£0.060/kg from 0.97kg al £2.910→£2.849/kg; premiums held | J89: Low | K89: =IFERROR(INDEX(Mapping!$C$2:$C$549,MATCH($A89,Mapping!$A$2:$A$549,0)),"") | L89: =IF($K89="",0,COUNTIFS('JLR Materials'!$A$2:$A$20001,$K89,'JLR Materials'!$C$2:$C$20001,IF(Settings!$B$2="","<>",Settings!$B$2),'JLR Materials'!$D$2:$D$20001,IF(Settings!$B$4="","<>",Settings!$B$4))) -> 0 | M89: =IF($L89<>1,0,SUMIFS('JLR Materials'!$E$2:$E$20001,'JLR Materials'!$A$2:$A$20001,$K89,'JLR Materials'!$C$2:$C$20001,IF(Settings!$B$2="","<>",Settings!$B$2),'JLR Materials'!$D$2:$D$20001,IF(Settings!$B$4="","<>",Settings!$B$4))) -> 0 | N89: =IF($L89<>1,0,SUMIFS('JLR Materials'!$F$2:$F$20001,'JLR Materials'!$A$2:$A$20001,$K89,'JLR Materials'!$C$2:$C$20001,IF(Settings!$B$2="","<>",Settings!$B$2),'JLR Materials'!$D$2:$D$20001,IF(Settings!$B$4="","<>",Settings!$B$4))) -> 0 | O89: =IF($N89=0,0,IF(Settings!$B$5="percent",$M89*$N89/100,$N89)) -> 0 | P89: =IF($L89<>1,0,SUMIFS('JLR Materials'!$G$2:$G$20001,'JLR Materials'!$A$2:$A$20001,$K89,'JLR Materials'!$C$2:$C$20001,IF(Settings!$B$2="","<>",Settings!$B$2),'JLR Materials'!$D$2:$D$20001,IF(Settings!$B$4="","<>",Settings!$B$4))) -> 0 | Q89: UK Jul 2026. 1050/6101 aluminium busbar stock — battery-pack and inverter interconnects, cell-to-body (CTB/CTC) module bars; lighter/cheaper than copper, larger cross-section. | Refresh 2026-09: −£0.060/kg from 0.97kg al £2.910→£2.849/kg; premiums held | R89: 2026-09
A90: mat-c67s-spring | B90: C67S / 1.1231 (CR Spring Strip) | C90: Spring Steel Strip | D90: =IF($M90>0,$M90,1.6) -> 1.6 | E90: =IF($O90>0,$O90,0.23) -> 0.23 | F90: 7850 | G90: UK | H90: =IF($M90>0,IF($L90<>1,$R90,IFERROR(INDEX('JLR Materials'!$D$2:$D$20001,MATCH($K90,'JLR Materials'!$A$2:$A$20001,0)),$R90)),$R90) -> 2026-09 | I90: =IF($M90>0,"JLR rate card — material code "&$K90,$Q90) -> UK spring strip Jul 2026. Hardened-and-tempered carbon spring strip — stamped flat springs, clips, retainers, blades; high yield after HT. | Refresh 2026-09: +£0.049/kg from 1kg crc £0.668→£0.717/kg; premiums held | J90: Low | K90: =IFERROR(INDEX(Mapping!$C$2:$C$549,MATCH($A90,Mapping!$A$2:$A$549,0)),"") | L90: =IF($K90="",0,COUNTIFS('JLR Materials'!$A$2:$A$20001,$K90,'JLR Materials'!$C$2:$C$20001,IF(Settings!$B$2="","<>",Settings!$B$2),'JLR Materials'!$D$2:$D$20001,IF(Settings!$B$4="","<>",Settings!$B$4))) -> 0 | M90: =IF($L90<>1,0,SUMIFS('JLR Materials'!$E$2:$E$20001,'JLR Materials'!$A$2:$A$20001,$K90,'JLR Materials'!$C$2:$C$20001,IF(Settings!$B$2="","<>",Settings!$B$2),'JLR Materials'!$D$2:$D$20001,IF(Settings!$B$4="","<>",Settings!$B$4))) -> 0 | N90: =IF($L90<>1,0,SUMIFS('JLR Materials'!$F$2:$F$20001,'JLR Materials'!$A$2:$A$20001,$K90,'JLR Materials'!$C$2:$C$20001,IF(Settings!$B$2="","<>",Settings!$B$2),'JLR Materials'!$D$2:$D$20001,IF(Settings!$B$4="","<>",Settings!$B$4))) -> 0 | O90: =IF($N90=0,0,IF(Settings!$B$5="percent",$M90*$N90/100,$N90)) -> 0 | P90: =IF($L90<>1,0,SUMIFS('JLR Materials'!$G$2:$G$20001,'JLR Materials'!$A$2:$A$20001,$K90,'JLR Materials'!$C$2:$C$20001,IF(Settings!$B$2="","<>",Settings!$B$2),'JLR Materials'!$D$2:$D$20001,IF(Settings!$B$4="","<>",Settings!$B$4))) -> 0 | Q90: UK spring strip Jul 2026. Hardened-and-tempered carbon spring strip — stamped flat springs, clips, retainers, blades; high yield after HT. | Refresh 2026-09: +£0.049/kg from 1kg crc £0.668→£0.717/kg; premiums held | R90: 2026-09
A91: mat-ss301-spring | B91: 301 Spring-Temper Stainless Strip | C91: Spring Steel Strip | D91: =IF($M91>0,$M91,4.53) -> 4.53 | E91: =IF($O91>0,$O91,0.93) -> 0.93 | F91: 7900 | G91: UK | H91: =IF($M91>0,IF($L91<>1,$R91,IFERROR(INDEX('JLR Materials'!$D$2:$D$20001,MATCH($K91,'JLR Materials'!$A$2:$A$20001,0)),$R91)),$R91) -> 2026-09 | I91: =IF($M91>0,"JLR rate card — material code "&$K91,$Q91) -> UK stainless spring strip Jul 2026. Work-hardened 301 (1/2–full hard) — corrosion-resistant springs, contacts, diaphragms, EMI fingers. | Refresh 2026-09: +£0.127/kg from 1kg ss_sur £2.037→£2.164/kg; premiums held | J91: Low | K91: =IFERROR(INDEX(Mapping!$C$2:$C$549,MATCH($A91,Mapping!$A$2:$A$549,0)),"") | L91: =IF($K91="",0,COUNTIFS('JLR Materials'!$A$2:$A$20001,$K91,'JLR Materials'!$C$2:$C$20001,IF(Settings!$B$2="","<>",Settings!$B$2),'JLR Materials'!$D$2:$D$20001,IF(Settings!$B$4="","<>",Settings!$B$4))) -> 0 | M91: =IF($L91<>1,0,SUMIFS('JLR Materials'!$E$2:$E$20001,'JLR Materials'!$A$2:$A$20001,$K91,'JLR Materials'!$C$2:$C$20001,IF(Settings!$B$2="","<>",Settings!$B$2),'JLR Materials'!$D$2:$D$20001,IF(Settings!$B$4="","<>",Settings!$B$4))) -> 0 | N91: =IF($L91<>1,0,SUMIFS('JLR Materials'!$F$2:$F$20001,'JLR Materials'!$A$2:$A$20001,$K91,'JLR Materials'!$C$2:$C$20001,IF(Settings!$B$2="","<>",Settings!$B$2),'JLR Materials'!$D$2:$D$20001,IF(Settings!$B$4="","<>",Settings!$B$4))) -> 0 | O91: =IF($N91=0,0,IF(Settings!$B$5="percent",$M91*$N91/100,$N91)) -> 0 | P91: =IF($L91<>1,0,SUMIFS('JLR Materials'!$G$2:$G$20001,'JLR Materials'!$A$2:$A$20001,$K91,'JLR Materials'!$C$2:$C$20001,IF(Settings!$B$2="","<>",Settings!$B$2),'JLR Materials'!$D$2:$D$20001,IF(Settings!$B$4="","<>",Settings!$B$4))) -> 0 | Q91: UK stainless spring strip Jul 2026. Work-hardened 301 (1/2–full hard) — corrosion-resistant springs, contacts, diaphragms, EMI fingers. | Refresh 2026-09: +£0.127/kg from 1kg ss_sur £2.037→£2.164/kg; premiums held | R91: 2026-09
